Workbook

Sheet Project Sheet 6
A1: Project Code | B1: Email Receiver | C1: email Sender | D1: Subject Line | E1: Date of email | F1: CC | G1: Email Body | H1: Customer Requirement Extract from email Body | I1: Sender DETAILS | J1: Web Links Picture hyperlinks Attachement | K1: Inside Comments | L1: LINKS STATUS | M1: ACKNOWEDGMENT | N1: Analysis of Customer Enquiry | O1: Database Prepared by Saad/Kaif/Zafar/Maaz | P1: Enquiry Analysis & links provided by | Q1: Enquiry Letter Made and Sent by | R1: Supplier email checked Yasir/Saad/ Arsalan/Zafar | S1: Price Calculated by Arsalan | T1: Quotation Prepared by | U1: Quotation Follow up done by | V1: Order Processed By | W1: Payment Follow up Done by | X1: Number of Quotation Received | Y1: Name of Database | Z1: Weblinks | AA1: Weblink status
A2: FEZW-XWQ-LQ
A3: ADAX-XQP-YA
A4: ANZF-FWR-JF
A5: VFIZ-YAI-QZ
A6: FMRB-BOR-ZB
A7: SULZ-ZFD-QZ
A8: QQOT-TKM-SO
A9: ZINY-YNI-PY
A10: HODL-LKS-DL
A11: SHHH-HWU-FH
A12: XZMI-IEB-NI
A13: YYMF-FNS-LY
... A1725: YCIW-SRO-JS

Sheet Project Sheet 5
A1: Project Code | B1: Internal Status | C1: Project External Process | D1: Enquiry Came through | E1: Date of enquiry | F1: Customer Requirement Arsalan | G1: CUSTOMER DETAILS | H1: Comments ANY ONE | I1: Enquiry Arrival Date | J1: LINKS STATUS | K1: ACKNOWEDGMENT | L1: Analysis of Customer Enquiry Zafar | M1: Database Prepared by Saad/Kaif/Zafar/Maaz | N1: Enquiry Analysis & links provided by | O1: Enquiry Letter Made and Sent by | P1: Supplier email checked Yasir/Saad/ Arsalan/Zafar | Q1: Price Calculated by Arsalan | R1: Quotation Prepared by | S1: Quotation Follow up done by | T1: Order Processed By | U1: Payment Follow up Done by | V1: Number of Quotation Received | W1: Name of Database | X1: Weblinks | Y1: Weblink status
A2: NFX-KY-AD | B2: Inquiry received by e-mail | F2: labmaster neo | G2: Ahmad Muslim. Product & Process Innovation Dept. (PPID) Qarshi Brands Pvt. Ltd. Hattar, KPK. ahmad.muslim@qarshi.com
A3: NFX-KY-AD | B3: Inquiry received by e-mail | F3: labmaster neo | G3: Ahmad Muslim. Product & Process Innovation Dept. (PPID) Qarshi Brands Pvt. Ltd. Hattar, KPK. ahmad.muslim@qarshi.com
A4: LTL-LJ-SI | B4: Quotation Sent | F4: FLUX PUMP | G4: AGP FAROOQ HAYAT Masab Ejaz
A5: AKC-FH-RL | B5: Inquiry received by e-mail | F5: Clutch Break | G5: AGP FAROOQ HAYAT
A6: PCI-SD-DO | B6: Inquiry received by e-mail | F6: Moisture Analyzer MS-70 A&D Japan MX-50 A&D Japan pH Meter HI-5222 Hanna USA | G6: Ahmad Muslim. Product & Process Innovation Dept. (PPID) Qarshi Brands Pvt. Ltd. Hattar, KPK.
A7: NAU-WJ-MT | B7: Quotation Sent | F7: VOC meter. | G7: Haider Ali |Manager EHS DIC Pakistan Limited A: Head office: Shahrah-e-Roomi,P.O. Amer Sidhu, Lahore-54760, Pakistan Karachi office: Plot # 06 Sector 28, Korangi Industrial Area, Karachi, Pakistan M: +92-301-8427331 P: +92-42-35822178-80, Ext.: 235 | H7: LAST ORDER Portable Gas Detector for VOCs (PGM-1800
A8: MHY-OF-NW | B8: Quotation Sent | F8: Sifter 1 stage stainless steel | G8: Asian Continental Address: D-32, S.I.T.E.ll,super Highway, Karachi Pakistan. Phone: (021) 36881775-8
A9: FYL-SA-GF | F9: Vibrator controller SDVC11-S EA 3 Vibrator Controller SDVC31-M EA 3 DHT11 Temperature and Humidity sensor EA 2 Sick Sensor wfs3-40p415 EA 1 | G9: Hussain Riaz | Associate Manager Procurement Address: C-14 SITE, Karachi, Pakistan Work: +(92-21) 32573391-5 | Ext: 387 Cell: +(92) 333 3829055 Email:Hussain.riaz@searlecompany.com
A10: JOR-QY-NP | B10: Request for further information sent to customer | F10: Synthetic Bag Filter 80-85% 3 Pockets 10 Pcs AAF Brand Synthetic Bag Filter 80-85% 6 Pockets 17 Pcs AAF Brand Synthetic Pre-Filters G4, 2'x2', 40-45% 10 Pcs AAF Brand Synthetic Pre-Filters G4, 1'x2', 40-45% 10 Pcs AAF Brand | G10: Tufail Khan Procurement Officer Ferozsons Laboratories Limited Post Office: Ferozsons, Amangarh, Nowshera, K.P.K. Phone: 0923-560145 | Cell: 0315-9890785
A11: GTR-QC-VO | B11: Quotation Sent | F11: DC/Potentiometer Converter (Model: CVR1) | G11: Saad Munir Engineering Store Officer, GSK Plot 5, Sector 21, Korangi Industrial Area, Karachi-74900, Pakistan Email saad.a.munir@gsk.com Mobile +92 312 370 9655 | +92 300 788 9092 Tel : 35205119-20 Ext:3084
A12: AYS-LJ-WB | B12: Quotation Sent | F12: Industrial Plug (5 Pin 32 Amp) 8571/12-506 STAHL 1 | G12: Mirza Imran Baig Senior Buyer, In-direct Sourcing Procurement, Pakistan Email mirzaimran.x.baig@haleon.com Haleon Pakistan Limited (Formerly GSK Consumer Healthcare Pakistan Ltd) 11-A, 11th Floor, Sky Tower (East Wing) Dolmen City, HC-3, Block-4, Marine Drive, Clifton Karachi-75600, Pakistan
A13: BLM-YY-PZ | F13: Thermal Insulation and Resistance Gloves Qty. 06 pairs. | G13: Mirza Imran Baig Senior Buyer, In-direct Sourcing Procurement, Pakistan Email mirzaimran.x.baig@haleon.com Haleon Pakistan Limited (Formerly GSK Consumer Healthcare Pakistan Ltd) 11-A, 11th Floor, Sky Tower (East Wing) Dolmen City, HC-3, Block-4, Marine Drive, Clifton Karachi-75600, Pakistan
A14: QLI-VW-HI | F14: Schneider Auxillary relay GVAN11 EA 12 Wecon LX2e PLC EA 1 Wecon HMI 7" LEVI2070D EA 1 Fatek PLC FBS-232P0 DB9 cable EA 2 | G14: Hussain Riaz | Associate Manager Procurement Address: C-14 SITE, Karachi, Pakistan Work: +(92-21) 32573391-5 | Ext: 387 Cell: +(92) 333 3829055 Email:Hussain.riaz@searlecompany.com
A15: HST-GT-TD | F15: color waize 26/10x43mm art no: 43600008 qty 20 Brand ETIBE | G15: BLI ASJAD
A16: KNZ-KH-SV | B16: Quotation Sent | F16: DRV5.V.2.1 Manufactured by ENDEX INC PARKER: STEPPER DRIVE (OEM750) | G16: BF BIO
A17: QNR-VP-HP | F17: Jenco 3177 3177M Conductivity/TDS/Salinity Basis Benchtop Meter | G17: Shakeel Ahmed Pharmaceutical
A18: LAR-UQ-BW | F18: HACH Spectrophotometer FLAME PHOTOMETER PH METER Dr 2800 Jenway with potassium filter | G18: Qadir chemicals Sobiaqumber48@gmail.com
A19: CZZ-GI-HI | F19: data logger -20 to 50 degree Qty 12 | G19: mavenhealthcare@gmail.com
A20: WAA-GC-YX | F20: Price labeler pagination device Blitz 2682 | G20: OTSUKA Talib hussain
A21: SWE-QM-CB | F21: TH4M Series LCD Temperature/Humidity Controllers | G21: OTSUKA Talib hussain
A22: UZP-QV-TX | B22: Quotation Sent | F22: THREE-PHASE VACUUM CLEANER FOR DUST, SOLIDS AND LIQUIDS DG 70 EXP, 5,5 KW | G22: Muhammad Zeeshan Mobile No.: 0335-2565477 Tel. Nos. ++92-21-35121963 - 64 Ext No. 2216 Healthtek (Pvt.)Limited
A23: AVW-LB-JJ | B23: Request for further information sent to customer | F23: 01: LoadSure Element QTY: 01 (As per Picture No: 2) 02: Tubing for material Transfer with Triclover end QTY: 04 Bore 10mm, Outer Dia 18mm, length 05Meters Triclover Outer Dia 25mm (As per picture No: 1) (As per picture No: 3) With food grade Certification Transferring Materials, Alcohol & Dimethylamine | G23: Contact Person is Mr. Faisal Aman Thanks and regards, Mirza Imran Baig Senior Buyer, In-direct Sourcing Procurement, Pakistan Email mirzaimran.x.baig@haleon.com
A24: TTF-JR-OS | B24: Quotation Sent | F24: Movable and Adjustable Conveyor as per below picture | G24: Mirza Imran Baig Senior Buyer, In-direct Sourcing Procurement, Pakistan Email mirzaimran.x.baig@haleon.com
A25: CAP-ON-SQ | B25: Quotation Sent | F25: Magnetic Stirerr for tank (1.1 to 1.5 KV) SS 316-L Qty-01 | G25: Tufh Engineering Javed Bhai
A26: QVY-XU-ZT | F26: 316L magnetic stirrer 1.5 kw class IE3 & 1.1 Kw class IE3 2 Nos 3 phase
A27: VWX-CZ-TU | F27: 60 100 150L stirrer tank | G27: Shahid Iqbal Sami pharma
A28: KVJ-AJ-QP | B28: Quotation Sent | F28: Hand crimping tool for 32mm vial cap | G28: Asad BF BIO
A29: CWG-RX-OS | B29: Quotation Sent | F29: Silicone Flexible Heating Foil Element Size: 0.8 x 365 x 165 mm with 8 holes, dia. 15 mm Voltage: 230 V | Power: 1500 W Connection: 2 x RHH 200mm cable Manufacturer: Uhlmann Origin: Sweden | G29: muhammad.jawad@agp.com.pk
A30: RFK-DP-UD | B30: Quotation Sent | F30: Conned Motor Pump for Refrigeration Model NR 100-50B/212 H4 – E-% Power 2.2 Kw Flow 20.75 M3/H Head 7.5m Speed 2900ROM Freq 50 Hz Volt. 400 V AMP 5.8A Pressure 0.5 Mpa NPS Hr 0.45m Star AMP 24 A Insulation Grade H Temp 90 oC Protection grade IP 54 Weight 4Pkg Order No X 7188 62-990 2 Serial No 6zn1403010 Do Not turn power on weight liquid Hefei X | G30: Mirza Imran Baig Senior Buyer, In-direct Sourcing Procurement, Pakistan Email mirzaimran.x.baig@haleon.com
A31: KKG-HU-YN | B31: Inquiry received by e-mail | F31: SS 316L mesh 3feet x 3feet mesh size=3MM 1 no SS 316L mesh 3feet x 3feet mesh size=1.5MM 1 no | G31: Ashraf Butt Procurement Officer Ashraf.x.butt@haleon.com Haleon Pakistan Limited (Formerly GSK Consumer Healthcare Pakistan Ltd) 11-A, 11TH floor, Sky Tower (East Wing) Dolman City, HC-3, Block 4, Marine Drive, Clifton, Karachi. Call : 03003567144
A32: SNL-IJ-QW | F32: SUBMERSIBLE WASTEWATER PUMPS SEG.50.40.2.50B +4kW /2 pole | G32: Agha khan hospital
A33: NTK-EE-YX | F33: Description Qty. Unit Clean Steam Supply system " 316L Stainless Steel as per ASME BPE 1.65mm thick internally polished (less than 0.5 microns) tubing for Purified water distribution loops. The piping to be of ALFA LAVAL." 25 mm Dia NB' 20 RFT "SS 316L elbow 90 degree 0.5 micron internal finish wall thickness 1.65 mm 25 mm dia" 10 Nos The valves and specialties shall be Spirax or approved equal. Steam traps, steam PRVs and other steam specialties to be only of SPIRAX SARCO. "Steam isloation /shutoff ball valve M70I AND M80I SANITARY BALL VALVES with ferrule type 20 mm dia" 4 NO "SS 316L Check valves. Dia 20 mm" "SS 316L Thermodynamic Steam Traps for clean steam application, ferrule connections with ferrule triclover clamps pressure PN 10 Temperature max 150 C Dia 20 mm" 4 No | G33: Ahmed Ali Baig | Deputy Manager Supply Chain M/s. Healthtek (Pvt.) Limited | Plot No. 14 Sector 19, Korangi Industrial Area, Karachi-74900 Phone: +92 21 35121963-64 | Ext: 2215 | Cell: +92 321 2128947, +92 303 0724067
A34: EAO-OB-OY | B34: Quotation Sent | F34: TESTOMAT WATER HARDNESS TESTER Model: TH 2005 | G34: ASJAD
A35: BUW-VV-QW | F35: Sloan SD-150 - JUMPSUIT, NON SKID, DISPOSABLE, 50 EA/CS
A36: ADV-WS-IC | F36: GE 4c convex probe | G36: RM Technical Services Islamabad
A37: RPF-EP-AV | B37: Inquiry received by e-mail | F37: SERVO MOTOR, SM100/40/050/P0/45/M1/B1, M 4 EA SERVO MOTOR, SM100/50/030/P0/45/M1/B1, M 2 EA SERVO-MOTOR, SM100/50/030/P0/45/S1/B0, M 4 EA SERVO MOTOR, SH100/40060/0/0/00/00/00/00 2 EA SERVO MOTOR, SH055/80013/0/0/00/00/00/00 2 EA MULTI DRIVE CONTROLLER C400/F.8 AXLES, M 2 EA MULTI-AXLE CONTROLLER MAX 4 F.8 AXLES, M 1 EA MOTOR CONTROLLER MC-4 (10A), MAKE SCHNEI 5 EA | G37: Hussain Riaz Associate Manager Procurement I Supply Chain Getz Pharma
A38: WBZ-KG-EY | F38: 00010 PLC make: Mitsubishi Model: FX3U 32MR Power: 220v AC 00020 HMI screen, Make: Mitsubishi Model: E1061 Note: All above parts required for Autoclav | G38: M. Faraz Khatri Senior Associate Manager Engineering Procurement| Ext:516 Martin Dow Limited Based at Korangi Plant, Karachi. Plot No. 37, Sector 19, Korangi Industrial Area, Karachi-74900, Pakistan
A39: TFM-CQ-TK | B39: Quotation Sent | F39: 00010 Digital Temperature Controller TZ4L-14R Sensor: Multi range, Range= Multi Range Out= Relay Power: 100 to 240v AC Made in Korea Required for Accela Coata 1 and 2, Glatt Fluid Bed Dryer and Liquid steam tank. 8 ea. 00020 Temperature controller make: Shinko Model no. JCM-33A-A/M (G) VCC= 100 - 240v ac input source= PT100, 0 TO 200°c Size= 72 x 72mm Made in Japan. Required for Fluid Bed Dryer make: YENCHEN 3 Ea. 00030 Proximity Switch 1A0032/Ae2010 EA 12.000 00040 Magnetic Contactor SW80-1 2 Ea. | G39: =G38 -> M. Faraz Khatri Senior Associate Manager Engineering Procurement| Ext:516 Martin Dow Limited Based at Korangi Plant, Karachi. Plot No. 37, Sector 19, Korangi Industrial Area, Karachi-74900, Pakistan
A40: QRB-PR-EA | B40: Inquiry received by e-mail | F40: DC Drive, make: ABB (VERITRON) Type: GCB 1302 A Supply: AC 220v (48-63hz) Output: DC 185v (4.5A 2 Ea. | G40: =G39 -> M. Faraz Khatri Senior Associate Manager Engineering Procurement| Ext:516 Martin Dow Limited Based at Korangi Plant, Karachi. Plot No. 37, Sector 19, Korangi Industrial Area, Karachi-74900, Pakistan
A41: GDH-JX-LS | B41: Inquiry received by e-mail | F41: Diaphragm Pump, Capacity: 20-25 KGs/M, Power Supply: Can Operate at/below 8 Bar As per attached URS | G41: Tufail Khan Executive Procurement Ferozsons Laboratories Limited Post Office: Ferozsons, Amangarh, Nowshera, K.P.K. Phone: 0923-560145 | Cell: 0315-9890785
A42: OLI-EC-MM | B42: Inquiry received by e-mail | F42: Sigma Aldrich 1.14815.001 Lot HC 161500) Qty 3 | G42: Syed Kafait Hussain ║ Purchase Department D.G. Khan Cement Co. Ltd. ║ Nishat House, 53-A, Lawrence Road, Lahore, Pakistan Tel: 0092 (42) 111-113-333, Ext: 4319 ║ M: 0092 321 4247688
A43: WVC-JG-UC | B43: Inquiry received by e-mail | F43: Automatic burette, borosilicate glass 3.3, with intermediate stopcock, capacity 50x0.01 mL, Order No. 48452050, Assistent-GmbH Qty 2 | G43: Syed Kafait Hussain ║ Purchase Department D.G. Khan Cement Co. Ltd. ║ Nishat House, 53-A, Lawrence Road, Lahore, Pakistan Tel: 0092 (42) 111-113-333, Ext: 4319 ║ M: 0092 321 4247688
A44: ENF-QL-PM | B44: Inquiry received by e-mail | F44: PP Hollow water Balls (Size 20 mm) Set 1 Plastic vials (Approximate Size 80 mm Long & 25 mm Dia) Numbers 100 | G44: Syed Kafait Hussain ║ Purchase Department D.G. Khan Cement Co. Ltd. ║ Nishat House, 53-A, Lawrence Road, Lahore, Pakistan Tel: 0092 (42) 111-113-333, Ext: 4319 ║ M: 0092 321 4247688
A45: DZL-ZQ-XT | B45: Inquiry received by e-mail | F45: Danfoss VLT Drive 11KW, 15HP, 3Phase, PN: 131L9869, SN: 432014A068 | G45: Tufail Khan Procurement Officer Ferozsons Laboratories Limited Post Office: Ferozsons, Amangarh, Nowshera, K.P.K. Phone: 0923-560145 | Cell: 0315-9890785
A46: KMD-GT-MA | B46: Closed | F46: A/C Fan Motor 220V 20W 0.32A 3P 50HZ Picture attached | G46: Tufail Khan Procurement Officer Ferozsons Laboratories Limited Post Office: Ferozsons, Amangarh, Nowshera, K.P.K. Phone: 0923-560145 | Cell: 0315-9890785 | H46: YSK-20W-4 CHANGZHOU HUATE MOTORS
A47: UWU-BK-RG | B47: Quotation Sent | F47: Stainless Steel Dissolution Basket 40 Mesh Make Pharma Test Germany/Dissotech –USA Qty 14 | G47: Afzal Ghani, EXECUTIVE PROCUREMENT
A48: ZBE-VD-ID | F48: SS 2 way valve with PTFF gasket 1/2" 38 pcs. 25mm. 03 pcs. 40mm 03 pcs SS pressure gauge glycerin filled 0 - 10 bar, 1/2" thread, 4" dial, bottom connection. 06 pcs Safety relief valve 15 bar PTFF gasket SS 0.05 - 0.85 with regulator 40 pcs. | G48: Otsuka Talib Hussain
A49: ANY-CA-XU | B49: Quotation Sent | F49: Water Bath Preservative – with Color Indicator, 250 ml (ALGEX Magenta) | G49: Afzal Ghani, EXECUTIVE PROCUREMENT
A50: MUP-VA-JT | F50: • flow switch 1252000z00000 Make: GEMU Qty.: 01 | G50: Mehboob Akhtar | Executive officer - General Procurement | SAMI Pharmaceuticals (Pvt.) Limited. Karachi  +92 21 32578081-83, Ext. 3682
A51: LET-QU-DI | F51: D2 Lamp PDA LC2030C 3D Plus, Part #228-55626-01 Qty 2 | G51: Afzal Ghani, EXECUTIVE PROCUREMENT
A52: CYF-RT-LS | B52: Inquiry letter sent | F52: LACTOSE MONOHYDRATE (200 MESH) 1,000 Kgs | G52: Afzal Ghani, EXECUTIVE PROCUREMENT | H52: Approved Manufacturers • KERRY INGREDIENT INDIA (PVT) LTD –USA • ARMOUR PHARMA –FRANCE
A53: KKG-FD-EP | B53: Quotation Sent | F53: Gloves for sulfuric Acid Material: Viton® Minimum layer thickness: 0,7 mm Break through time: 480 min Material tested:Vitoject® (KCL 890 / Aldrich Z677698, Size M) Qty: 04 Dozen. | G53: Ashraf Butt Procurement Officer Ashraf.x.butt@haleon.com Haleon Pakistan Limited (Formerly GSK Consumer Healthcare Pakistan Ltd) 11-A, 11TH floor, Sky Tower (East Wing) Dolman City, HC-3, Block 4, Marine Drive, Clifton, Karachi. Call : 03003567144
A54: GRN-UK-QI | F54: Dry Powder Line with auto catoner, details shared in URS and carton drawing attached | G54: Hinoon lab
A55: NOU-RZ-YZ | F55: I shared you metformin vidoes, want to break these solid blocks through crusher and pass the crushed material through 2mm mesh at discharge. capactity required: 500kg/hr | G55: Hinoon lab
A56: OQO-VP-DV | B56: Quotation Sent | F56: Electric Fire Pump Display Card (S/N-1728291-RE) Mark II XG-AS-1198-003 Make: Peerless Pump 1 EA Electric Pump I/O Board PC-1075G (BER18180912) Brand: Peerless Pump 1 EA Jockey Pump Magnetic Contractor (S/N- 1S1203001W1749000874101) Af-26-30- 00-11 (24-60V50/60hz 20-60VDC) Brand: Peerless Pump 1 EA | G56: Hussain Riaz Associate Manager Procurement I Supply Chain hussain.riaz@getzpharma.com
A57: RXX-UO-QB | B57: Quotation Sent | F57: Pressure Gauges - Reservoir Equipment PGB0631100 0-100 Bar Parker Qty 2 | G57: Mirza Imran Baig Senior Buyer, In-direct Sourcing Procurement, Pakistan Email mirzaimran.x.baig@haleon.com Haleon Pakistan Limited (Formerly GSK Consumer Healthcare Pakistan Ltd) 11-A, 11th Floor, Sky Tower (East Wing) Dolmen City, HC-3, Block-4, Marine Drive, Clifton Karachi-75600, Pakistan
A58: PYV-QQ-IQ | F58: Spare Parts for our Prominence – i 2030 HPLC System SAMPLE LOOP ASSY 100UL 228-50390 for LC 2030 Nos 01
A59: LLH-JP-JI | B59: Inquiry not clear | F59: BUCKET F70701665 ( CAM ) Nos 2 SILICON COVER 66440-0001 ( Sejong Compression ) Nos 2 | G59: Ashraf Butt Procurement Officer Ashraf.x.butt@haleon.com Haleon Pakistan Limited (Formerly GSK Consumer Healthcare Pakistan Ltd) 11-A, 11TH floor, Sky Tower (East Wing) Dolman City, HC-3, Block 4, Marine Drive, Clifton, Karachi. Call : 03003567144 | H59: -Contact Person: Mr. Zakir Raza – 03040729713/ Muhammad Iqbal - Cell #. 0304-0526942
A60: SSJ-NZ-PK | B60: Inquiry received by e-mail | F60: D2 lamp HPLC PDA, Part # 228-55626-01 Nos 05 D2 lamp HPLC UV, Part #228-34016-02 Nos 02 Tungsten Lamp for RID, Part# 228-32445-41 Nos 01 | G60: Afzal Ghani, EXECUTIVE PROCUREMENT Postal Address: P.O Ferozsons, Amangarh, Nowshera, K.P.K, |pro.nowshera@ferozsons-labs.com|Website:www.ferozsons-labs.com|0923-560145, 0312-9486757,03458553396|FAX: 0923-611302|
A61: CVW-CY-XT | B61: Inquiry received by e-mail | F61: Capacitive Proximity Sensor CM30-25NNP-K, Brand: SICK 2 Pcs Sensor WTB8-P1111 6033211 (SICK) 6 Pcs | G61: Tufail Khan Executive Procurement Ferozsons Laboratories Limited Post Office: Ferozsons, Amangarh, Nowshera, K.P.K. Phone: 0923-560145 | Cell: 0315-9890785
A62: ZBP-YF-XD | F62: X1JET HPMK2 Pro INK CARTRIDGES MODELS WDBLK2 (Water Base) – WEBER Ink Cartridges Qty 350 | G62: Tufail Ahmed Shaikh Engineering Store Officer tufail.a.shaikh@gsk.com
A63: WWW-SX-CA | B63: Quotation Sent | F63: Membrane Filter Sartolon Polymide 0.45um ,47mm Cat# 25006—47…N , Pack of 100 Sartorius Stedium–Germany/China Packet 40 | G63: Afzal Ghani, EXECUTIVE PROCUREMENT
A64: OLZ-LV-WH | B64: Inquiry received by e-mail | F64: 293 [HEK-293] – ATCC No. CRL-1573 Qty. 1 vial | G64: Asim Ali| Sr. Executive Material Management PABX: +92-42-36026700 EXT:150| Mobile: +92-301-8734364
A65: IGI-RG-RL | B65: Quotation Sent | F65: Peroxide Cured Silicone Tubing 9.48 - 9.5 I/D Size 150Mtr | G65: Junaid Mehmood BF Biosciences PABX: +92-42-36026700 EXT:150| Mobile: +92-300-8436534
A66: EYE-WP-BR | F66: Protein content by ELISA for Semaglutide | G66: Asim Ali| Sr. Executive Material Management PABX: +92-42-36026700 EXT:150| Mobile: +92-301-8734364
A67: KTJ-JK-FG | B67: Inquiry received by e-mail | F67: Tetpor air Filter cartridge Rating : 0.2 micron Model # ZCMT1-020C-A Part # 539503800, Brand = Parker Qty : 14 Nos. | G67: Saad Munir Engineering Store Officer, GSK Plot 5, Sector 21, Korangi Industrial Area, Karachi-74900, Pakistan Email saad.a.munir@gsk.com Mobile +92 312 370 9655 | +92 300 788 9092 Tel : 35205119-20 Ext:3084
A68: DGT-MF-AH | F68: pH Electrode,Model Sentix 81 WTW , Made in Germany WTW-Germany Nos 02 | G68: Afzal Ghani,
A69: BTK-RF-KX | F69: 1. L929 cell lines ATCC CC-1 (ADALIMUMAB) 2. HUVEC cell lines LONZA CC-2519A (BEVACIZUMAB) 3. WIL2S Cell line ATCC CRL-8885 (Rituximab) 4. BT-474 Clone 5 CRL-3247 ™ (Transtuzumab) | G69: Asim Ali
A70: HYX-EB-IW | F70: Submercible Pump Type Multi Stage (Deep Well) Size: 3" (75mm) Stainless Steel, min. Flow rate : 33 liter/ minutes Head: 50meter Discharge 1.25" Rating : 220Vac, 0.75HP/0.55k, 2850rpm, Copper Winding with controller box & Cable Make Jasco / Jiadi / Ingco | G70: rafiha.zaidi@asiapetroleum.com
A71: CRB-OC-QM | F71: Pneumatic Air Cylinder SAILB63BX200S-WZ1492B (AIRTAC CYLINDER) 04 nos | G71: Tanveer Rasheed Team Lead Pharma Engineering Scilife Pharma (Pvt.) Ltd. Phone: +92 21 111 724 543 | Ext: 4057 Mobile: +92 333 3297413 Web: https://scilife.biz | H71: Machine Serial No 21064031 Equipment Fluid Bed Dryer (FG200B)
A72: ZVI-JL-OY | B72: Quotation Sent | F72: • FA Flow transducer,UFA-N2,Hontzsch Make Hon1tzsch Type UFA-N2 Power 24 VDC Filter standard Input FA Output 4....20mA Picture attached | G72: Mehboob Akhtar | Executive - General Procurement | SAMI Pharmaceuticals (Pvt.) Limited. Karachi  +92 21 32578081-83, Ext. 3682 |  +92 301 1150277
A73: ULC-TU-XR | F73: ampule and pre filled inspection machine Used | G73: Bf Bio
A74: BOR-TH-SX | B74: Quotation Sent | F74: Vacuum Pump (Becker)made in germany Type= U5.101/0-01 Frequency=50/60 Hz Speed=1420/1720 min-1 Power required=2.2/2.6 kW Inlet Capacity 100/120 m3/hr Max Vacuum=0.1/0.1 mbar | G74: Sami pharmaceutical
A75: LSR-XT-YW | B75: Quotation Sent | F75: Data logger temp+humid with rj45 output Qty 5 | G75: Starways Pharmaceuticals 7, 90 The Mall Nowshera Cantt. Email: info@starwayspharma.com Phone: (92) 321-8585555 / (92) 333-9394177 threestar2010@gmail.com
A76: ZFK-IQ-JE | B76: Quotation Sent | F76: Magnehelic DP Gauge Model: 2000-750PA 6 Pcs | G76: Tufail Khan Procurement Officer Ferozsons Laboratories Limited Post Office: Ferozsons, Amangarh, Nowshera, K.P.K. Phone: 0923-560145 | Cell: 0315-9890785 | H76: Dywer price $75.35
A77: ELD-TU-CW | B77: Quotation Sent | F77: EX RECEPTACLE 20Amp Model: 8570/21-505 STAHL (Qty 1) 8570/21-505 EX Plug 16Amp 8570/12-306 , 3 -Pin STAHL (Qty 3) EX RECEPTACLE 16Amp , Model: 8570/11-306 ,Make STAHL (Qty 3) | G77: Mirza Imran Baig Senior Buyer, In-direct Sourcing Procurement, Pakistan Email mirzaimran.x.baig@haleon.com | H77: Contact Person is Mr. Syed Yasir
A78: EBY-AS-YX | B78: Quotation Sent | F78: Stainless Steel Dissolution Basket 10 Mesh Nos 14 | G78: Afzal Ghani, EXECUTIVE PROCUREMENT Postal Address: P.O Ferozsons, Amangarh, Nowshera, K.P.K, |pro.nowshera@ferozsons-labs.com|Website:www.ferozsons-labs.com|0923-560145, 0312-9486757,03458553396|FAX: 0923-611302| | H78: Pharma test Dissolution Apparatus PTWS 1220-Germany
A79: MVO-PA-DX | B79: Quotation Sent | F79: - Vacuum Pump EV40V-T Dry Rotary Vacuum Pump Capacity 40 m3/h Motor 1.25Kw 380V, 50Hz | G79: Hamdard Laboratories (WAQF) Pakistan 13th Floor, Bahria Town Tower, Main Tariq Road, Karachi. Tel: +92-21-38244000 (Ext:1351) | H79: BLI RATES
A80: AIS-CF-MB | F80: Fotek Proximity Sensor SP-05N 10-30V DC 6 Pcs Sensor WTB8-P1111 6033211 (SICK) 6 Pcs Sick Sensor – IQ08-02BPSKT0S 3 Pcs SMC Sensor NCRB1BW10 Series Reed Switch 6 Pcs | G80: Tufail Khan Executive Procurement Ferozsons Laboratories Limited Post Office: Ferozsons, Amangarh, Nowshera, KP. Phone: 0923-560145 | Cell: 0315-9890785
A81: FHU-SR-GG | F81: Burkert Flow Meter 12-36V 4-20mA 2 Pcs Burkert Sensor DN08 ASME BPE 2x3x811306 2 Pcs | G81: Tufail Khan Executive Procurement Ferozsons Laboratories Limited Post Office: Ferozsons, Amangarh, Nowshera, KP. Phone: 0923-560145 | Cell: 0315-9890785
A82: AHM-FS-LG | F82: Pt 100 6mm RTD Sensor With M12 Connector 6 Nos | G82: Tufail Khan Executive Procurement Ferozsons Laboratories Limited Post Office: Ferozsons, Amangarh, Nowshera, KP. Phone: 0923-560145 | Cell: 0315-9890785
A83: ZAL-RO-CU | F83: Vacuum Filter P.N 22680002 FC 60 3/4" 1 Pc | G83: Tufail Khan Executive Procurement Ferozsons Laboratories Limited Post Office: Ferozsons, Amangarh, Nowshera, KP. Phone: 0923-560145 | Cell: 0315-9890785
A84: STM-ZE-GM | B84: Inquiry received by e-mail | F84: Mini Reflow Solder System with vacuum for fluxless soldering Model RSS-160-SC make: UniTemp GmbH | G84: Ahmad Muslim. Product & Process Innovation Dept. (PPID) Qarshi Brands Pvt. Ltd. 56/2-3, Hattar Industrial Estate, City Haripur-22610, KPK-Pakistan Ph# +92 995 617173 Fax# +92 995 617275
A85: HRY-UZ-TW | B85: Inquiry received by e-mail | F85: Performa Control Valve Assy For Softening Plant Part# 1244651, Make: Pentair, Italy | G85: Tufail Khan Executive Procurement Ferozsons Laboratories Limited Post Office: Ferozsons, Amangarh, Nowshera, KP. Phone: 0923-560145 | Cell: 0315-9890785
A86: GWM-AG-SA | F86: "Circuit breaker Compact NSX160N - MA - 150 A - 3 poles Schneider" Qty 01 "Circuit breaker Tembreaker S160-SCF- 125 A - 3 poles Terasaki" Qty 02 "Circuit breaker Tembreaker MCCB S250NJ-200 A - 4 Poles Terasaki" Qty 01 | G86: Mirza Imran Baig Senior Buyer, In-direct Sourcing Procurement, Pakistan Email mirzaimran.x.baig@haleon.com
A87: MRO-ZP-TW | B87: Quotation Sent | F87: FOIL HEATER Mat Type Heating Element size L 26 inch * w 3.5 inch 220v 1500w Qty 12 | G87: Uzair.ahmed@pfizer.com | H87: QAMAR
A88: DZW-MY-UP | B88: Quotation Sent | F88: FOIL HEATER Mat Type Heating Element size L 26 inch * w 3.5 inch 220v 1500w Qty 18 | G88: muhammad.jawad@agp.com.pk | H88: Brought Sample
A89: KZS-FS-JJ | B89: Quotation Sent | F89: D2 lamp HPLC UV, PN 228-34016-02 BDS Nos 02 | G89: Afzal Ghani,
A90: RVI-WE-LK | F90: Toner Printer Model # HL-L2360DN Printer Make : Brother Qty 1 | G90: Mirza Imran Baig Senior Buyer, In-direct Sourcing Procurement, Pakistan Email mirzaimran.x.baig@haleon.com
A91: USP-LG-JO | B91: Quotation Sent | F91: 01: Tri Clover Clamp SS316L (Sanitary Pipe Weld Ferrule) 1" Tri Clamp Complete Set QTY: 02 As per Pictures Attached 02: Food Grade Silicone Tube Transparent QTY: 100 ft FDA Approved Silicone Tubing Inner Dia: 10mm, Outer Dia: 14mm Brand: Hardware MISE (Picture Attached) With Food Grade Certificate | G91: Mirza Imran Baig Senior Buyer, In-direct Sourcing Procurement, Pakistan Email mirzaimran.x.baig@haleon.com
A92: WRA-XB-CB | F92: - VOC meter - LEL meter - Thermography Camera | G92: Tayyaba Ijaz Assistant Manager EHS DIC Pakistan Limited tayyaba.ijaz@dic.com.pk
A93: YQP-JK-JB | F93: S.S 316L filter cartridges (5-Micron) for filtration Assembly QTY : 12 Micro-Membrane STP5 226FIN | G93: "Mirza Imran Baig Senior Buyer, In-direct Sourcing Procurement, Pakistan Email mirzaimran.x.baig@haleon.com "
A94: DMD-CV-JB | F94: EX RECEPTACLE 20Amp Model: 8570/21-505, 5-Pin, STAHL Nos 1 | G94: Ashraf Butt Procurement Officer Ashraf.x.butt@haleon.com Haleon Pakistan Limited (Formerly GSK Consumer Healthcare Pakistan Ltd) 11-A, 11TH floor, Sky Tower (East Wing) Dolman City, HC-3, Block 4, Marine Drive,Clifton, Karachi. Call : 03003567144
A95: INT-IJ-FN | F95: Switch Amplifier RELAY WE 77/EX-2-230 , PEPPERL+FUCHS | G95: Ashraf Butt Procurement Officer Ashraf.x.butt@haleon.com Haleon Pakistan Limited (Formerly GSK Consumer Healthcare Pakistan Ltd) 11-A, 11TH floor, Sky Tower (East Wing) Dolman City, HC-3, Block 4, Marine Drive,Clifton, Karachi. Call : 03003567144
A96: RKM-KK-YP | F96: Delavan Hollow Cone Nozzle 1/4" AG Art.-Nr. WM1008 STST 30.1 LITRES/HOUR AT 3 Bar.G | G96: Ghulam Rasool GSK
A97: MQP-AQ-UX | B97: Quotation Sent | F97: SS SIEVE 1.25X0.8MM Model: 636, 316/316L Part no: 407425 , Make: Frewitt Origin: Switzerland | H97: SX1-4KS-827N-18J
A98: ATT-PP-HP | B98: Quotation Sent | F98: MONTA FILM 257F COLOURED THERMOFORMING / SPLICING TAPE, COLOR : RED, SIZE : 38mm X 66mm Brand = Monta Qty : 25 Nos. | G98: GSK SAAD
A99: FTL-SS-WI | F99: PK4-7800076 Capacitive Sensor BAE SA-CS-001-PS, BAE009E,367178 BALLUFF Nos 2 | G99: ASHRAF BUTT
A100: SFF-CE-JD | F100: PK4-7224455 - Capacitive Proximity Switch 10 to 40 VDC, 0.2A, EC3016NPAPL Carlo Gavazzi, Qty: 02 Nos | G100: ASHRAF BUTT
...

Sheet Project Sheet 4
A1: Project Code | B1: Internal Status | C1: Project External Process | D1: Enquiry Came through | E1: Date of enquiry | F1: Customer Requirement Arsalan | G1: CUSTOMER DETAILS | H1: Comments ANY ONE | I1: Enquiry Arrival Date | J1: LINKS STATUS | K1: ACKNOWEDGMENT | L1: Analysis of Customer Enquiry Zafar | M1: Database Prepared by Saad/Kaif/Zafar/Maaz | N1: Enquiry Analysis & links provided by | O1: Enquiry Letter Made and Sent by | P1: Supplier email checked Yasir/Saad/ Arsalan/Zafar | Q1: Price Calculated by Arsalan | R1: Quotation Prepared by | S1: Quotation Follow up done by | T1: Order Processed By | U1: Payment Follow up Done by | V1: Number of Quotation Received | W1: Name of Database | X1: Weblinks | Y1: Weblink status
A2: ABFQ-EKZ-CF | B2: Closed | F2: 1. Worm Gear Box 1:50 Ratio Size 70 nos 2. Motor 1440rpm 2Hp single phase 3. Motor 1440rpm 3Hp three phase | G2: Mohsin Javed FABRICON(PRIVATE) LTD 46-247, Sector: 24, Korangi Industrial Area, Karachi – 74900, Pakistan Pakistan 92-331-5064957 / 92-21-35067736 mohsinjaved@fabricon.com.pk
A3: ABII-JOQ-UJ | B3: Quotation Sent | F3: 20 HP of 2P/2900RPM 3-Ph/400V TEFC Electric Motor (1 Unit) | G3: mueez.ansari@kineticflowsystems.com Syed Zahid Hasan
A4: ADCJ-USH-ZJ | B4: Inquiry received by e-mail | F4: Dissolution Test Apparatus, Model-PTWS 1220 12 position Tablet Instrument with Full IQ and OQ with External Pinter Facility Pharma Test Tablet Dissolution, Tester PT –DT70 instrument with Printers Model PT-RP80 Pharma Test Germany or any best Quality Brand | G4: Afzal Ghani, PROCUREMENT OFFICER Postal Address: P.O Ferozsons, Amangarh, Nowshera, K.P.K, |pro.nowshera@ferozsons-labs.com|Website:www.ferozsons-labs.com|0923-650145, 0312-9486757,03458553396|FAX: 0923-611302|
A5: ADFX-PJC-OA | B5: Inquiry received by e-mail | F5: Polarimeter Digital Model ADP 450 Bellingham & Stanley Instrument with Pinter Model CBM 910 Bellingham & Stanley , Made in England or any best Quality Brand | G5: Afzal Ghani, PROCUREMENT OFFICER Postal Address: P.O Ferozsons, Amangarh, Nowshera, K.P.K, |pro.nowshera@ferozsons-labs.com|Website:www.ferozsons-labs.com|0923-650145, 0312-9486757,03458553396|FAX: 0923-611302|
A6: ADLY-CEM-VP | B6: Quotation Sent | F6: Digital Multimeter 87V Max Fluke 1 Digital Multimeter CD800b Sanwa 2 | G6: Ashraf Butt CHC Procurement Officer GlaxoSmithKline CHC Pakistan Limited. 35 - Dockyard Road, west wharf , Karachi-74000, Pakistan Tel: +92 21 32315478-82 & (Dir) 35274744 UAN:+92 21 111 475 725 (Ext: 4744)
A7: ADOI-SAV-BU | B7: Quotation Sent | F7: BECKER vacuum pump motor type D 71 B4 P motor no : 15085540 nample attached | G7: Ashraf Butt CHC Procurement Officer GlaxoSmithKline CHC Pakistan Limited. 35 - Dockyard Road, west wharf , Karachi-74000, Pakistan Tel: +92 21 32315478-82 & (Dir) 35274744 UAN:+92 21 111 475 725 (Ext: 4744) | K7: Send
A8: AEIH-LDM-MW | B8: Quotation Sent | F8: GAS REGULATOR Model AG/RC DN25 MAKE MADAS Italy | G8: Gunj Glass Head Office: A-26 Site Area Karachi Info@gunjglass.com Tell: 0213-2414862 | K8: Send
A9: AEIL-PXX-JJ | B9: Inquiry received by e-mail | F9: Heat Exchanger plate with epdm gasket model NT150 LH, plate thickness 0.5mm, material 316L qty 136 pcs model VT 80 LH, plate thisckness 0.5mm 316L qty 26 | G9: HASSAN ENGINEERING R-712 sector-15A/5 Buffer zone,North karachi, phone 021-36999059 cell: 0305-2108958 saleem.he_engg@yahoo.com | K9: Send
A10: AEVM-AQR-PS | B10: Closed | F10: Automatic Hand Dryer-220 V-AC,1800 Watt ,White Siemens 2 | G10: Asim Laique Assistant Manager Procurement Cell #0345-3127098 asim.laiq@herbion.com | H10: 8,500 price local available
A11: AEZO-PYA-KX | F11: Metal Detector 4 • Type of tablets both round and oblong. • Speed up to 300,000 to 400,000 tablets per hour | G11: Pharmevo
A12: AFCH-CKO-SE | F12: BALL, CHECK ( PTFE ) P/N 050.018.600, DIAPHRAGM PUMP SIZE: 2" 21/05/26BAL. 4.000 BALL, CHECK ( PTFE ) RS MODEL: S20B1AGTANS000 TYPE: A.0.D.D. PUMP MAKE: SAND PIPER PUMP Approved 29868/002 280424899 .00000 PC 2.000 .00 LE 21/07/15 00000 .00 E13 BUYER J RUBBER DIAPHRAGM 2" P/N 286.007.365, DIAPHRAGM PUMP SIZE: 2" 21/05/26BAL. 2.000 RUBBER DIAPHRAGM 2" RS MODEL: S20B1AGTANS000 TYPE: A.0.D.D. PUMP MAKE: SAND PIPER PUMP Approved 29868/003 280424900 .00000 PC 2.000 .00 LE 21/07/15 00000 .00 E13 BUYER J DIAPHRAGM ( PTFE OVERLAY ) P/N 286.020.604, DIAPHRAGM PUMP SIZE: 2" 21/05/26BAL. 2.000 DIAPHRAGM ( PTFE OVERLAY ) RS MODEL: S20B1AGTANS000 TYPE: A.0.D.D. PUMP MAKE: SAND PIPER PUMP Approved 29868/004 280424901 .00000 PC 4.000 .00 LE 21/07/15 00000 .00 E13 BUYER J SEAT, VALVE ( TEFLONE ) P/N 722.040.600, DIAPHRAGM PUMP SIZE: 2" 21/05/26BAL. 4.000 SEAT, VALVE ( TEFLONE ) RS MODEL: S20B1AGTANS000 TYPE: A.0.D.D. PUMP MAKE: SAND PIPER PUMP Approved 29868/005 280424902 .00000 PC 1.000 .00 LE 21/07/15 00000 .00 E13 BUYER J ROD, DIAPHRAGM P/N 685.058.120, DIAPHRAGM PUMP SIZE: 2" 21/05/26BAL. 1.000 ROD, DIAPHRAGM RS MODEL: S20B1AGTANS000 TYPE: A.0.D.D. PUMP MAKE: SAND PIPER PUM
A13: AGDT-OVW-WT | B13: Inquiry received by e-mail | F13: Specification of fillter Fillter coller size 15 x15 inches Fillter pockets size 18x13 inches Fillter pocket 09 With fillter pockets gripping spring As per sample | G13: Ashraf Butt CHC Procurement Officer GlaxoSmithKline CHC Pakistan Limited. 35 - Dockyard Road, west wharf , Karachi-74000, Pakistan Tel: +92 21 32315478-82 & (Dir) 35274744 UAN:+92 21 111 475 725 (Ext: 4744) | K13: Send
A14: AGYM-EMX-TO | B14: Inquiry received by e-mail | F14: PSR 11 – 21 Oxygen sensor qty 1 OX – 3 Oxygen sensor qty 1 | G14: Archroma Pakistan Limited | Plot #LX-10 & LX11 Landhi Industrial Trade Zone Karachi 74900 | Pakistan Tel: +9221 35081371-72 | Mobile: +92306 2349660 | E-Mail: bashir.ahmed@archroma.com | K14: Send
A15: AHBM-QME-HX | B15: Quotation Sent | F15: BRAKE RECTIFIER BG 1.5 FOR SEW MOTORS - AT PACKING PLANT PART NO 8- 253 846 FOR FA40/G DT100LS4/BMG EA 04 | G15: ='Projects sheet 3'!G980 -> Riffat Tahira Procurement Officer Processing Section Department of Procurement Bestway Cement Limited | 8th Floor | UBL Building, Jinnah Avenue | Islamabad 44000, Pakistan. Tel: +92 51 835 5139 | UAN:+92 51 111 111 722 EXT: 324 Website: www.bestway.com.pk E-mail: riffat.tahira@bestway.com.pk | H15: Riffat Tahira | K15: Send
A16: AHHN-KCV-BA | B16: Quotation Sent | F16: REXROTH DOOR LOCK MNR: 3 842 530 352 qty 50 | G16: Business Links Int’l (Pvt) Ltd Address: 2nd Floor, Twin Star Chambers, Mumtaz Hasan Road, Karachi, Pakistan Phone: + 92 21 3241 9227 asjad@businesslinks-pk.com | H16: G9T-PQ5-JWI-X5U4
A17: AHRY-LFE-QJ | F17: GEARED MOTOR, TYPE=RF27DRE80M4 ITEM # 646BW410-M01, 0.75 KW, 4- -POLE, 400 VAC, MAKE = SEW EURO DRIVE EA 06 | G17: ='Projects sheet 3'!G912 -> Muhammad Rehan Anwar Officer Procurement Department of Procurement Bestway Cement Limited | 8th Floor | UBL Building, Jinnah Avenue | Islamabad 44000, Pakistan. Tel: +92 51 835 5118 | Fax: +92 51 265 4865 | UAN:+92 51 111 111 722 Website: www.bestway.com.pk CC: rehan.anwar@bestway.com.pk mahboob.shakir@bestway.com.pk | K17: Send
A18: AIOO-RXH-AQ | F18: GEAR UNIT, 11KW, 1400 RPM, I=137 CRLB147-137-M11+E30- B5-0-ZS06615 FOR ROTARY FEEDER, BONENG FOR LINE-II EA 01 | G18: =G17 -> Muhammad Rehan Anwar Officer Procurement Department of Procurement Bestway Cement Limited | 8th Floor | UBL Building, Jinnah Avenue | Islamabad 44000, Pakistan. Tel: +92 51 835 5118 | Fax: +92 51 265 4865 | UAN:+92 51 111 111 722 Website: www.bestway.com.pk CC: rehan.anwar@bestway.com.pk mahboob.shakir@bestway.com.pk | K18: Send
A19: AJFA-NXL-LS | B19: Quotation Sent | F19: H.M.I PROFACE GP-4501TW, model= PFxGP4501TADW, 24V, 0.71AYenchen super coater m/c model= YC-SC-170F, no.= OB320 160090 capacity=0.8-1.4 Kg/batch 1 EA | G19: Muhammad Ahsan Sadiq Assistant manager Technical purchase | Procurement | Ext: 1409 Martin Dow Marker Ltd D-7, Shaheed-e-Millat Road Karachi-75350, Pakistan UAN : +92 21 111 523 523 Cell: +92-3166550042 Ext: 1409 https://martindowmarker.com/ | K19: Send
A20: AJPG-AVS-WU | B20: Quotation Sent | F20: FLUKE 376FC 4 pcs | G20: Wilson Bulembo Operations Supervisor Novotech Enterprises Limited P.O.Box 10692 Tausi Street No.5,Mikocheni B, Dar-es-salaam, Tanzania, Mobile: +255 (0774) 888831 | Direct +255 (0763) 082645 Email: info@novotechtz.com |info@novotechtz.co.tz| novotech13@gmail.com Website: www.novotechtz.com
A21: AKRO-IZR-WN | B21: Inquiry received by e-mail | F21: Fuji Electric RYS302S3-RPS FALDIC | G21: Abdul Majid National Care Pack Pvt Ltd. Cell. 0092 300 8252089. | K21: Send
A22: AKYP-EZJ-XJ | B22: Request for further information sent to customer | F22: Chemical Pump Caustic Soda NaOH 50% Sodium Hypochlorite NaOCL 13% HCL | G22: Nobel Enterprises Karachi Pakistan nobel.enterprises@yahoo.com info@nobelent.com (021) 34979978
A23: AMHE-UUO-IR | F23: DIGITEN 22mm YELLOW LED Flash Alarm 80dB Indicator Light Lamp with Buzzer Color : Yellow Volt : AC 220V 03 Nos | G23: ='Projects sheet 3'!G975 -> Mirza Imran Baig Senior Buyer, In-direct Sourcing Procurement, Pakistan GSK 35 Dockyard Road, West Wharf, Karachi 74000, Pakistan Email mirza.i.baig@gsk.com Tel +92 21 35274743 Ext: 4743 | K23: Send
A24: ANNR-BOT-SH | B24: Inquiry received by e-mail | F24: Required spare parts of air compressor Make boge Germany Model # SLF 75-3 Serial # 5139398 & 5094203 Rate of flow = 2.10 – 8.50 cum/min Max service pressure = 10 bar Motor power 55 kw . SPARE PRTS Wearing part of MPV = 02 2230337671 Solonaid Valve =01 644006301 Wearing part of intake =01 2420088671 Wearing part of oil regulator =01 2420164671 Suction hose pipe = 01 529001410 Temperature Sensor =01 639002803 Service kit = 03 | G24: Saeed Ahmed Barrett Hodgson Pakistan | K24: Send
A25: ANWW-IFC-VR | F25: 1090000055 CONNECTION PLATE FOR MOTOR 4KW, SIZE: 4MM, WITH DELTA LINK COMPLETE (COMPLETE) EA 08 1090000056 CONNECTION PLATE FOR MOTOR 5.5KW TYPE - : ILA7130-4AA60-Z,TYPE 132- S-4 WITH DELTA LINK(COMPLETE) EA 08 1090000057 CONNECTION PLATE FOR MOTOR 11KW TYPE Y160M2-6 WITH DELTA LINK MPLETE) EA 05 1090000052 CONNECTION PLATE FOR 15KW MOTOR EA 05 1090000059 CONNECTION PLATE FOR MOTOR 18.5KW TYPEY180M-4WITH DELTA LINK MPLETE) EA 05 1090000060 CONNECTION PLATE FOR 45KW MOTOR, TYPE:- Y225M-4WITH DELTA LINK COMPLETE) EA 05 1090005828 TERMINAL PLATE 75KW EA 05 1090000061 CONNECTION PLATE FOR MOTOR 90KW TYPE:- 280S-4 WITH DELTA LINK PLETE) EA 05 | G25: =G15 -> Riffat Tahira Procurement Officer Processing Section Department of Procurement Bestway Cement Limited | 8th Floor | UBL Building, Jinnah Avenue | Islamabad 44000, Pakistan. Tel: +92 51 835 5139 | UAN:+92 51 111 111 722 EXT: 324 Website: www.bestway.com.pk E-mail: riffat.tahira@bestway.com.pk
A26: AOVU-XFK-XN | F26: 1090010887 CONNECTION/TERMINA L PLATE FOR SEW MOTOR TYPE DT 63 N4,0.16 KW EA 06 1090010888 CONNECTION/TERMINA L PLATE FOR SEW MOTOR TYPE DT 71 D4, 0.37 KW EA 06 1090010889 CONNECTION/TERMINA L PLATE FOR SEW MOTOR TYPE RF 40DT 80N4,0.75 KW EA 06 1090010890 CONNECTION/TERMINA L PLATE FOR SEW MOTOR TYPE RF 73DT 100LS4, 2.2 KW EA 06 1090010891 CONNECTION/TERMINA L PLATE FOR SEW MOTOR TYPE R 97 DV 112M4, 4 KW EA 06 1090010892 CONNECTION/TERMINA L PLATE FOR SEW MOTOR TYPE R 87 DV 132M4, 7.5 KW EA 06 1090010893 CONNECTION/TERMINA L PLATE FOR MOTOR TYPE UD 63 SGD,0.25 KW EA 06 1090010894 CONNECTION/TERMINA L PLATE FOR ABB MOTOR TYPE MT100 LA28-8 FF-165,0.75 KW EA 06 1090010895 CONNECTION/TERMINA L PLATE FOR ABB MOTOR TYPE MT90 L24-F-165,MK1007S,1.1 KW EA 06 1090010896 CONNECTION/TERMINA L PLATE FOR ABB MOTOR TYPE M2AA 090 L-2, 2.2 KW EA 06 1090010897 CONNECTION/TERMINA L PLATE FOR ABB MOTOR TYPE M3AA 132-A4, 7.5 KW EA 06 1090010898 CONNECTION/TERMINA L PLATE FOR SIEMENS MOTOR TYPE 1LA 2080-4AA93, 0.55 KW EA 06 1090010899 CONNECTION/TERMINA L PLATE FOR SIEMENS MOTOR TYPE 1LG6-283-2AB91-Z, 90 KW EA 06 1090010900 CONNECTION/TERMINA L PLATE FOR FRIEDRICH SCHWINGTECHNIK MAKE VIBRATOR MOTOR TYPE EX 700-6, 3 KW EA 06 1090010901 CONNECTION/TERMINA L PLATE FOR MOTOR TYPE UD 63 SGD,0.25 KW EA 06 | G26: =G25 -> Riffat Tahira Procurement Officer Processing Section Department of Procurement Bestway Cement Limited | 8th Floor | UBL Building, Jinnah Avenue | Islamabad 44000, Pakistan. Tel: +92 51 835 5139 | UAN:+92 51 111 111 722 EXT: 324 Website: www.bestway.com.pk E-mail: riffat.tahira@bestway.com.pk
A27: AOWX-WYW-QD | F27: Amber Color Glass Bottle 15ml with sealed Caps ,Glass Type -1 CNW –Germany or You may also quote any best Quality Brand i.e Duran, Pyrex & Lauda, Glassco. etc. 2,000 Nos | G27: =G4 -> Afzal Ghani, PROCUREMENT OFFICER Postal Address: P.O Ferozsons, Amangarh, Nowshera, K.P.K, |pro.nowshera@ferozsons-labs.com|Website:www.ferozsons-labs.com|0923-650145, 0312-9486757,03458553396|FAX: 0923-611302|
A28: APCQ-OIW-ZH | B28: Quotation Sent | F28: 6ES7214-1AG40-0XBO, S7 1200, Qty 1 6ES7222-1HH32-0XBO, 16DO Card, Qty 3 | G28: junaid@raeng.com Qazi Junaid junaid@raeng.com R.A ENGINEERING & SERVICES (PVT) LTD.
A29: APFV-LMQ-KI | B29: Quotation Sent | F29: Wintek HMI 7 INCH | G29: Qazi Junaid junaid@raeng.com R.A ENGINEERING & SERVICES (PVT) LTD.
A30: APNA-ULC-NM | F30: Portable Dehumidifier Model # 36B | G30: Helix Pharma Umair
A31: APXH-VKY-EG | F31: GSM data Logger with digital and analog signal for Alarm | G31: Helix Pharma Umair
A32: AQCX-UYY-EX | B32: Inquiry received by e-mail | F32: Killian Machine LX hydraulic cylinder complete set or Seal kit Round-Zylinder Z100 -101 40/20/20-201-100 40/20/20-201 503 KOM 1C 455 picture attached | G32: Muhammad Faizan Electronics Maintenance Officer, GlaxoSmithKline F-268 S.I.T.E., Karachi, Pakistan Email muhammad.8.faizan@gsk.com Cell +92-304-0941792 | H32: https://hollandmotiongroup.com/en/wp-content/uploads/sites/2/2019/02/Brochure-Round-Cylinder-Z100.pdf
A33: AQSB-BOQ-BG | B33: Quotation Sent | F33: Hangcha battery operated stacker controller, D.C motor controller Part no: 360104220 Voltage: 24-36V Model: 1243-4220 Currnt:200A. | G33: Hussain Riaz | Assistant Manager Procurement The Searle Company Limited Address: F-319 SITE, Karachi, Pakistan Work: +(92-21) 3257-8001-7 | Ext: 3084 Cell: +(92) 333 3829055 Email:Hussain.riaz@searlecompany.com | K33: Send
A34: AQXR-RLZ-DC | F34: Pls check the Icar capacitor Model: Msr25-B-1-85: 100pcs | G34: Công Sang Nguyễn <cosavn@gmail.com> VIETNAM
A35: ARAJ-SOV-ZA | F35: Eaton P611 - Switched socket, 13A, 1G, 1p White | G35: Agha Khan Hospital Bright Engineering <brightengg.pk@gmail.com>
A36: ARFV-YUB-TS | B36: Inquiry Letter and Database Ready | F36: FPF Filter Fans IP54 Single Phase QTY: 02 Complete assembly with fan & Filters Model: FPF13KPU 115BE-110 Voltage: 110/115 Vac 50/60Hz Power: 18/20 watt 02: Electrical Cabinet Filter QTY: 06 Cut Out Size: 177*177mm IP: 55 G4 Filter Made in China | G36: Ashraf Butt CHC Procurement Officer GlaxoSmithKline CHC Pakistan Limited. 35 - Dockyard Road, west wharf , Karachi-74000, Pakistan Tel: +92 21 32315478-82 & (Dir) 35274744 UAN:+92 21 111 475 725 (Ext: 4744) | K36: Send
A37: ARRR-WYC-QQ | B37: Quotation Sent | F37: Dispensing booth QTY 2 URS ATTACHED | G37: Syed Nouman Ali Zaidi Deputy Manager Engineering AGP Limited. B-23-C, S.I.T.E., Karachi - 75700, Pakistan. UAN: +92-21-111247247 (Ext. 317) nouman.ali@agp.com.pk | K37: Send
A38: ARUA-XMP-XF | B38: Quotation Sent | F38: Indicator Reagent, Gebruder Heyl, 8028033, 500 ml | G38: Muhammad Nauman Tariq Assistant Manager Engineering 00923434146319 +92-42-35297273-5 Ext: 519 m.nauman@dynatispakistan.com
A39: ARUM-VAW-RP | B39: Inquiry letter sent | F39: 1070021671 BACKSTOP CLUTCH FOR GEARBOX N 20,3,700NM, BORE 130DH7,120KG OF COAL RECLAIMER INCLINED BELT, TYPE OF GEARBOX:ZQ850-5, REDUCTION RATIO: 50, DRIVING MOTOR POWER:30KW, JIANGSU TAILONG DECELARATOR MACHINERY CO.LTD. CHINA. EA 1 | G39: =G26 -> Riffat Tahira Procurement Officer Processing Section Department of Procurement Bestway Cement Limited | 8th Floor | UBL Building, Jinnah Avenue | Islamabad 44000, Pakistan. Tel: +92 51 835 5139 | UAN:+92 51 111 111 722 EXT: 324 Website: www.bestway.com.pk E-mail: riffat.tahira@bestway.com.pk | K39: Send
A40: ASSE-UHQ-YV | B40: Quotation Sent | F40: Through Beam (Fork) Photoelectric Sensor QTY: 02 Part No: BGL 120A-001-S49 Make: BALLUFF Through Beam (Fork) Photoelectric Sensor QTY: 02 Part No: BGL 180A-001-S49 Make: BALLUFF Inductive Sensor QTY: 02 Part No: BES M12ME-PSC40B-S04G-003 Make: BALLUFF Inductive Sensor QTY: 02 Part No: BES M08MI-PSC20B-S49G Make: BALLUFF Inductive Sensor QTY: 02 Part No: BES M12ME-PSC40B-S04G-003 Make: BALLUFF | G40: "Mirza Imran Baig Senior Buyer, In-direct Sourcing Procurement, Pakistan GSK 35 Dockyard Road, West Wharf, Karachi 74000, Pakistan Email mirza.i.baig@gsk.com Tel +92 21 35274743 Ext: 4743 " | K40: Send
A41: ATFG-HXF-DB | B41: Inquiry Letter and Database Ready | F41: Paper Roll for Printer Balance Shimadzu EP90 /EP-100 Part # 321-73902 Shimadzu-Japan 10 Packs Paper Roll for Printer Built-in with pH meter 7310p WTW- Germany 10 Packs | G41: =G27 -> Afzal Ghani, PROCUREMENT OFFICER Postal Address: P.O Ferozsons, Amangarh, Nowshera, K.P.K, |pro.nowshera@ferozsons-labs.com|Website:www.ferozsons-labs.com|0923-650145, 0312-9486757,03458553396|FAX: 0923-611302| | K41: Send
A42: AUTQ-ATI-WU | B42: Quotation Sent | F42: 2D / PHARMACODE CAMERA BANNER IVU2PRBW08 1 | G42: =G23 -> Mirza Imran Baig Senior Buyer, In-direct Sourcing Procurement, Pakistan GSK 35 Dockyard Road, West Wharf, Karachi 74000, Pakistan Email mirza.i.baig@gsk.com Tel +92 21 35274743 Ext: 4743 | H42: RUHAIL EBAN ALI | K42: Send
A43: AVWS-NYO-WH | B43: Quotation Sent | F43: Photo electric Sensor QTY: 02 Part No: E3Z-B86 Make: OMRON With rectangular reflector 38x20 Inductive Sensor QTY: 02 Part No: E2A-M12KN08-M1-B1 Make: OMRON Inductive Proximity Sensor QTY: 02 Part No: E2A-S08KS02-M5-B1 Make: OMRON | G43: Mirza Imran Baig Senior Buyer, In-direct Sourcing Procurement, Pakistan GSK 35 Dockyard Road, West Wharf, Karachi 74000, Pakistan Email mirza.i.baig@gsk.com Tel +92 21 35274743 Ext: 4743 | K43: Send
A44: AWKI-URJ-SE | B44: Quotation Sent | F44: Ultrasonic Part No: MIC+35/DD/TC QTY: 02 Make: MICROSONIC Sensor Microsonic | G44: Mirza Imran Baig Senior Buyer, In-direct Sourcing Procurement, Pakistan GSK 35 Dockyard Road, West Wharf, Karachi 74000, Pakistan Email mirza.i.baig@gsk.com Tel +92 21 35274743 Ext: 4743 | K44: Send
A45: AWYZ-JFZ-MN | B45: Quotation Sent | F45: Float level sensor (Magnetic Sensor) QTY: 02 Part No: ILM82MT Make: CARLO GAVAZZI | G45: Mirza Imran Baig Senior Buyer, In-direct Sourcing Procurement, Pakistan GSK 35 Dockyard Road, West Wharf, Karachi 74000, Pakistan Email mirza.i.baig@gsk.com Tel +92 21 35274743 Ext: 4743 | K45: Send
A46: AXKZ-KSZ-DF | B46: Quotation Sent | F46: SAFETY RFID SENSOR QTY: 02 Part NO: ST DD310M01-D1T Make: PIZZATO | G46: Mirza Imran Baig Senior Buyer, In-direct Sourcing Procurement, Pakistan GSK 35 Dockyard Road, West Wharf, Karachi 74000, Pakistan Email mirza.i.baig@gsk.com Tel +92 21 35274743 Ext: 4743 | K46: Send
A47: AXVP-EEX-ZT | B47: Quotation Sent | F47: V2066203109 WA-XV 1,0mm SK-VA, Vorderk. V4A Air Cap and Front body made of stainless steel 1.4571, Nozzle and Needle also made of stainless steel. Qty –02 | G47: Asjad@businesslinks-pk.com
A48: AYQA-CKP-CP | B48: Quotation Sent | F48: Differential Pressure Transmitter QTY: 02 Rage: 20.6 Kpa PXPLX03F Make: Veris Industries Made in USA | G48: =G36 -> Ashraf Butt CHC Procurement Officer GlaxoSmithKline CHC Pakistan Limited. 35 - Dockyard Road, west wharf , Karachi-74000, Pakistan Tel: +92 21 32315478-82 & (Dir) 35274744 UAN:+92 21 111 475 725 (Ext: 4744) | H48: -Contact Person: Mr. Faisal Aman. 0303-0665403 EMAIL SENT | K48: Send
A49: BBDR-QWK-OP | B49: Waiting for supplier Reply | F49: GLOVES for DRY BOX GLOVES 97800 y 9 e4 5 ITEM Code 001294 Brand: Piercan™ | G49: Saad Munir saad.a.munir@gsk.com | H49: EMAIL SENT TO MANUFACTURER | K49: Send
A50: BBSA-PKH-DJ | B50: Request for further information sent to customer | F50: 1. Circular Chart Recorder – (Paper Type). Make: Honeywell / Supco / Dickson Model: As per Brand Power: 220V AC, 50Hz Required Specification: (1) Chart recorder should be able to capture temperature + Humidity (both) dual pen type. (2) required ranges are for Temperature: 10 to 50 degree C. Humidity: 25% to 60%. (3) Chart recorder should have an inside battery backup to continue its operation during any short term power failure. (4) Chart Recorder should have its own probe for RH & Temperature, either input for process signal transmitter: universal type (i.e. 4-20 ma, 0 -10V or RTD). 2. Sensor Probe or Signal Transmitter (for above chart recorder). Make: Branded according to the chart recorder suitability. Required Quantities: Area Type Quantity Warehouse (R.M, P.M F.G) Only Temperature 6 Nos. Vitamins RH & Temp Both 22 Nos. New Solid Block RH & Temp Both 3 Nos. Total: 31 Nos. (Complete Unit with Sensor Probe). | G50: =G46 -> Mirza Imran Baig Senior Buyer, In-direct Sourcing Procurement, Pakistan GSK 35 Dockyard Road, West Wharf, Karachi 74000, Pakistan Email mirza.i.baig@gsk.com Tel +92 21 35274743 Ext: 4743 | K50: Send
A51: BDYQ-HZE-DM | B51: Inquiry received by e-mail | F51: Eye Mark Sensor DATALOGIC M1817 Made In Hungary Qty 1 | G51: Tufail Khan Procurement Officer Ferozsons Laboratories Limited Post Office: Ferozsons, Amangarh, Nowshera, K.P.K. Phone: 0923-560145 | Cell: 0315-9890785 | K51: Send
A52: BFKR-HLO-AN | F52: VALVE, GLOBE, 3/4"X1500# SCH80,A 105, BW VALVE GLOBE, 3/4"X1500# SCH 80 A 105, BW, MAKE: TEXT:CARBON STEEL - GLOBE-WB-RED.B-THDD SEAT - BS5352 - CL1500 - BW BODY MAT.: ASTM A105, TRIM MAT.: 304 STELLITED, PRESSURE TEST ACC. TO BS6755 PART-1. BONNET WELDED, OUTSIDE SCREW RISING STEM, SHUTTER TYPE: PISTON, SEAT TYPE: THREADED RING, CFFT: EA 10 | G52: Arsalan Ahmed
A53: BGEL-JEG-HV | F53: Filter F6 and F9 20x40x1 Inch F6=12, F9=12 - GI Frame, Filter fabric Imported AHU Filter G4 578x756x40 Mm 4 - G.I. Frame with filter Imported MFG Blower | G53: Herbion M. Ahmed Memon Engineering Department Maintenance Officer 0334-3208748 | K53: Send
A54: BGTR-HVA-QT | F54: Capacitor for GUTOR UPS , 110 micro F , 250VAC , P/N: 234-0117 MFR: GUTOR , QTY: 426 Ea. | G54: Hami Bahramian Behyneh Palayesh Spadan Co. (BEHPACO) Head Office: Tell: +98 31 32370700 - 2 Fax: +98 31 32370703 Cell: +98 913 310 3640 Add: Unit 10, 520 Office Building, 42nd Dead-Alley, Sheikh Bahaie St., P.O. Box 8134975354, Isfahan, Iran | K54: Send
A55: BGXP-YFX-MV | B55: Order Arrived | F55: Post Flame Nozzle (Bausch) 8 EA Required Pre Flame Nozzle (Bausch) 4 EA Required | G55: Akbar muhammad.akber@macter.com Muhammad Akber Purchase Officer (Local-NPS) Cell #0345-2501059 Phone : 32591000 (Extn: 4110 ) | K55: Send
A56: BHNR-CBG-HZ | B56: Inquiry received by e-mail | F56: Gas struts with angle joints Qty 4 each Nameplates in email | G56: Mohsin Iqbal Assistant Manager Procurement 0324-8288970 / 0333-7437086 PRQ # 1010012413 mohsin.iqbal@herbion.com
A57: BHRB-DFX-IL | B57: Inquiry received by e-mail | F57: Model: M3 BLACK Manufactured By: M3 Mobile Quantity: 02 Nos For Reference, Pic is attached For details, you may contact with Toaha Ali Khan Planned Maintenance Engineer Ext 322 Cell +92 3035078029 | G57: =G46 -> Mirza Imran Baig Senior Buyer, In-direct Sourcing Procurement, Pakistan GSK 35 Dockyard Road, West Wharf, Karachi 74000, Pakistan Email mirza.i.baig@gsk.com Tel +92 21 35274743 Ext: 4743 | K57: Send
A58: BHSZ-QLO-KD | F58: FILTRATION ASSEMBLIES (AUTOCLAVABLE) for Microbiology testing of water samples 47mm Sterile Filters | G58: Qarshi Research International Pvt. Limited Plot # 56/1-4, Phase - III, Hattar Industrial Estate, Hattar mbl@qarshi.com 0995-111-200-300, 617273 (Ext. 340) | K58: Send
A59: BIXG-TJW-AL | B59: Data is ready | F59: Numatics Solenoid Valve 031SA4004012B61 Qty 3 | G59: Hussain Riaz | Assistant Manager Procurement The Searle Company Limited Address: F-319 SITE, Karachi, Pakistan Work: +(92-21) 3257-8001-7 | Ext: 3084 Cell: +(92) 333 3829055 Email:Hussain.riaz@searlecompany.com | K59: Send
A60: BJIU-YLU-RF | B60: Quotation Sent | F60: ULTRA65 SILICONE TUBING - 3/4'' X 5/4''X 1/4'' – 50 FT. - (SAINT-GOBAIN) | G60: Syed Masood Hasan Imports Department BF BIOSCIENCES LIMITED (A Subsidiary of Ferozsons Labs Ltd) Head Office/Biotech Factory, 5-Km; Sundar-Raiwind Road, Opposite Ijtima Chowk Raiwind, Lahore-Pakistan. Tel Dir # : +92-42-3602 6789 PABX # : +92-42-3602 6700 Cell # : +92-307-444 00 78 Cell # : +92-301-44 66 851 Email : masood.hasan@bfbio.com masood.hasan@ferozsons-labs.com | H60: ULTRA-C-750-6 3/4 (19.1) 1-1/4 (31.7) 1/4
A61: BKZX-YHB-DZ | B61: Quotation Sent | F61: SS316L mesh 3MM 3feet x 6 feet 1 | G61: Ashraf Butt CHC Procurement Officer GlaxoSmithKline CHC Pakistan Limited. 35 - Dockyard Road, west wharf , Karachi-74000, Pakistan Tel: +92 21 32315478-82 & (Dir) 35274744 UAN:+92 21 111 475 725 (Ext: 4744)
A62: BNKR-WDH-PW | B62: Quotation Sent | F62: Filter Syring PTFE Membrane(Hydrophilic), (Pink) ,0.45um, 25mm, Grade: Preclean, Cat # 2.CF6201.0001, 100/Pk qty 24 box 2. Filter Syringe Nylon Membrane 0.45um, 25mm (White) Cat # 2.CF2201.0001, 100/Pk = 400 box 3. Filter syringe PVDF Membrane, Hydrophobic 0.45um, 25mm,(Red) Grade: Preclean, Cat # 2.CF4201.0001, 100/Pk = 10 box 4. Filter Syringe Nylon Membrane 0.22um, 25mm (Green) Grade: 2.CF2202.0001,100/Pk = 100 box | G62: Afzal Ghani, PROCUREMENT OFFICER Postal Address: P.O Ferozsons, Amangarh, Nowshera, K.P.K, |pro.nowshera@ferozsons-labs.com
A63: BOHG-JPW-TU | B63: Inquiry received by e-mail | F63: Supply of PLC Model FBS-60MCR2-AC(D24) FATEK Qty 1 | G63: Mirza Imran Baig Senior Buyer, In-direct Sourcing Procurement, Pakistan GSK 35 Dockyard Road, West Wharf, Karachi 74000, Pakistan Email mirza.i.baig@gsk.com Tel +92 21 35274743 Ext: 4743
A64: BOLE-PNF-ZV | B64: Inquiry received by e-mail | F64: Supply of Mountable Accessories for MPCB 11SM1B Model:11SMX1211 Aux qty 4 | G64: Mirza Imran Baig Senior Buyer, In-direct Sourcing Procurement, Pakistan GSK 35 Dockyard Road, West Wharf, Karachi 74000, Pakistan Email mirza.i.baig@gsk.com Tel +92 21 35274743 Ext: 4743
A65: BOLR-GCR-JB | B65: Inquiry received by e-mail | F65: Supply of safety switch FR series PIZZATO ELETTRIC for Door Guarding Qty 8 | G65: Mirza Imran Baig Senior Buyer, In-direct Sourcing Procurement, Pakistan GSK 35 Dockyard Road, West Wharf, Karachi 74000, Pakistan Email mirza.i.baig@gsk.com Tel +92 21 35274743 Ext: 4743
A66: BOMK-HRJ-NA | B66: Inquiry received by e-mail | F66: Supply of Miniature Relay With Base 24VDC 8 Pin Make: TSHRACK Qty 16 | G66: Mirza Imran Baig Senior Buyer, In-direct Sourcing Procurement, Pakistan GSK 35 Dockyard Road, West Wharf, Karachi 74000, Pakistan Email mirza.i.baig@gsk.com Tel +92 21 35274743 Ext: 4743
A67: BOXV-FPG-QJ | B67: Inquiry received by e-mail | F67: Supply of MRK SERIES SCREWED TYPE RAIL TERMINAL BLOCKS MRK 1.5 Color: GREY Order No: 1002 Size: 1.5mm Make: ONKA qty 50 Supply of MRK SERIES SCREWED TYPE RAIL TERMINAL BLOCKS MRK 2.5 Color: GREY Order No: 1012 Size: 2.5mm Make: ONKA Qty 50 Supply of MRK SERIES SCREWED TYPE RAIL TERMINAL BLOCKS MRK 6 Color: GREY Order No: 1032 Size: 6mm Make: ONKA Qty 20 Supply of MRK SERIES SCREWED EARTH RAIL TERMINAL BLOCKS MTK 4 Order No: 1293 Size: 4mm Make: ONK Qty 40 | G67: Mirza Imran Baig Senior Buyer, In-direct Sourcing Procurement, Pakistan GSK 35 Dockyard Road, West Wharf, Karachi 74000, Pakistan Email mirza.i.baig@gsk.com Tel +92 21 35274743 Ext: 4743
A68: BPQL-REA-WX | B68: Inquiry received by e-mail | F68: Portable Label Printer KL-P350W CASIO | G68: Mirza Imran Baig Senior Buyer, In-direct Sourcing Procurement, Pakistan GSK 35 Dockyard Road, West Wharf, Karachi 74000, Pakistan Email mirza.i.baig@gsk.com Tel +92 21 35274743 Ext: 4743 | H68: WORKING
A69: BPZP-BNF-TX | B69: Quotation Sent | F69: Portable Diesel Powered 3 GPM, 2500 psi Cold Water Pressure Washer. Make: Cam Spray Model: 25006DX (for more details please find the link https://www.camspray.com/portable-diesel-powered-3-gpm-2500-psi-cold-water-pressure-washer-p-97.html) Qty: 01 Nos. | G69: Mirza Imran Baig Senior Buyer, In-direct Sourcing Procurement, Pakistan GSK 35 Dockyard Road, West Wharf, Karachi 74000, Pakistan Email mirza.i.baig@gsk.com Tel +92 21 35274743 Ext: 4743
A70: BQGY-LAO-UQ | B70: Inquiry not clear | F70: Inflatable Gasket for filter bag FBG-500E-05-04 Nos 2 | G70: Ashraf Butt CHC Procurement Officer GlaxoSmithKline CHC Pakistan Limited. 35 - Dockyard Road, west wharf , Karachi-74000, Pakistan Tel: +92 21 32315478-82 & (Dir) 35274744 UAN:+92 21 111 475 725 (Ext: 4744) | K70: Send
A71: BSEE-MJA-QC | B71: Inquiry letter sent | F71: GEARED MOTOR HOLLOW TYPE,2.2KW,15-20RPM, HOLLOW SIZE:50MM EA 06 GEARED MOTOR HOLLOW TYPE,1.1KW,15-20RPM, HOLLOW SIZE:35MM EA 06 | G71: Riffat Tahira Procurement Officer Processing Section Department of Procurement Bestway Cement Limited | 8th Floor | UBL Building, Jinnah Avenue | Islamabad 44000, Pakistan. Tel: +92 51 835 5139 | UAN:+92 51 111 111 722 EXT: 324 Website: www.bestway.com.pk E-mail: riffat.tahira@bestway.com.pk | K71: Send
A72: BSEJ-MEJ-SC | B72: Quotation Sent | F72: Sachet Filling Machine Bedi & Cranzo (Powder Sachet), Fluace & Evo (Granular Sachet) Sealing: Three Side Seal Fill Weight: 2-15 Gram Per Minute Speed: 150-200 Sachet Finished Sachet: 95mm(L) * 50mm(W) Foil size 110mm*100mm | G72: Ali Raza Procurement & Supply Coordinator Highnoon Laboratories Limited 17.5 km. Multan Road, Lahore - 53700 Pakistan +92 42 111 000 465 (Ext): 2479 +92 3114454878 www.highnoon-labs.com
A73: BSUU-GSK-OV | F73: Stepping motor DG21KGML PC 1 0 SANYO Chiller Temperature sensor DG21KGML PC 4 0 SANYO Chiller Sight glass chiller DG21KGML PC 3 3 Glass SANYO Chiller | G73: Syed Feham Ali Executive Procurement (Engineering) Supply Chain Department 0331-2477981 | K73: Send
A74: BVAK-RSS-SN | F74: Mechanical seal 10mm PC 1 2 0 Taiwan Mono block pump boiler Chemical dosing pump DI Etatron PKX 07 L/h-05 Bar pc 1 1 0 ITALY DI plant Mono block pump boiler 1 HP single phase PC 1 0 0 Taifu For boiler Plastic vinyl air curtain strip 7.5" x 3 mm Feet 100 Ft 0 Plastic vinyl strip Local Dispensing booth | G74: Syed Feham Ali Executive Procurement (Engineering) Supply Chain Department 0331-2477981 | K74: Send
A75: BVWO-JUY-WV | B75: Inquiry received by e-mail | F75: Membrane Filter 0.2um ,47mm (Sartolon Polymide) Cat# 25007—47…N , Pack of 100 = 5 box Membrane Filter Cellulose Acetate 0.2um ,47mm (Sartolon Polymide) ,Cat# 11107—47….ACN , Pack of 100 = 10 box Membrane Filter Cellulose Acetate 0.2um ,47mm (Sartolon Polymide) ,Cat# 11107—47----N , Pack of 100 = 10 box Membrane Filter 0.45um ,47mm (Sartolon Polymide) Cat# 25006—47…N , Pack of 100 = 10 box Sartorius Stedium–Germany | G75: Afzal Ghani, PROCUREMENT OFFICER | K75: Send
A76: BWKP-VIU-MT | B76: Inquiry received by e-mail | F76: Nylon Syringe Filter 1.0um, 25mm (1000 Nos Box), Part # 6753-2510, Make: Whatman Qty 2 Filter Glass Microfiber Binder Free GF/C Circles 47mm Cat # WHA1822047 Make: Aldrich 100/Pk Qty 1 Filter Paper No.40 12.5cm (Whatman) , Cat # 1440 125 Qty 50 packet Filter paper No. 41 12.5 cm (Whatman), Qty 10 packet Filter Glass Microfiber Grade: GF/F 47mm Cat # WHA1825047 Make: Aldrich 100/Pk Qty 1 Whatman(Merck) –Germany | G76: Afzal Ghani, PROCUREMENT OFFICER | K76: Send
A77: BWLQ-KWK-SX | B77: Inquiry received by e-mail | F77: Filter Membrane PTFE (Hydrophilic) 0.45um, 47mm Cat # FBm04PTFE045, Make: Filter-Bio 200/Pk Qty 10 | G77: Afzal Ghani, PROCUREMENT OFFICER | K77: Send
A78: BYPP-DBF-SA | B78: Inquiry received by e-mail | F78: Filter Membrane Nylon (0.45um, 47mm) Cat: HNWP04700 Millipore 100/Pk Qty 5 Filter Membrane Nylon (0.20µm, 47mm) Cat: Cat # GNWP04700 Millipore 100/Pk Qty 2 | G78: Afzal Ghani, PROCUREMENT OFFICER | K78: Send
A79: BZQB-PTJ-VO | B79: Inquiry received by e-mail | F79: 01 0-5000 gm 0.00 digits Moveable in Scope Premises For Bulk density of extruded pallet and semi-finished Pellets upto 02 Kg , Fried pellet upto 05 kg. 02 0-1000 gm 0.00 digits Lites Packing Section For validation or counter checking of automatic multi head weigh machines by weighing of product packets. | G79: Tanzeem Baig Senior Manager Supply Chain Rasul Flour Mills 0334-6207617 tanzeem@bakeparlor.com | K79: Send
A80: CBTB-HPC-CZ | B80: Quotation Sent | F80: Sponge for Labeling 8" * 1000 * 50 mm 203.20*1000*50 mm | G80: warisdogar@gmail.com Waris Ali
A81: CCEX-MKD-VK | F81: 1 Controller TAC I/A Series MNL-13R PC 2 0 Electronic 0 2 15007336 Temperature sensor Sensor TE-702-A-5-B PC 6 0 Electronic 0 3 15006811 R-H sensor HU-224-3-MA PC 4 0 Electronic USA 4 Pneumatic valve actuator DG21KGML Valve PC 2 0 Schneider | G81: Feham Ali Herbion
A82: CCSK-CIU-CP | B82: Data is ready | F82: Handheld multi-frequency underground service locator The Leica DD100 Series cable locators Buried Utility Services Locator (Brochure is attached for reference). Make: Leica (Switzerland). Model: DD130 Qty: 01 Nos. | G82: Mirza Imran Baig
A83: CDAM-ZJZ-SI | B83: Inquiry received by e-mail | F83: 3 PHASE INDUCTION MOTOR, HP 01, AMP 02, 1450RPM, 400VOLT, FRAME 56C, 50HZ, CODE NO TF 6739C, FOOT MOUNTED, MAKE LINCOLN ELECTRIC CO., USA EA 01 3 PHASE INDUCTION MOTOR, 01HP, 2.05AMP, 1465RPM, 400VOLT, FRAME 145T, 50HZ, CODE NO NP 210, FOOT MOUNTED, MAKE LINCOLN ELECTRIC CO., USA EA 01 | G83: Riffat Tahira Procurement Officer Processing Section Department of Procurement Bestway Cement Limited | 8th Floor | UBL Building, Jinnah Avenue | Islamabad 44000, Pakistan. Tel: +92 51 835 5139 | UAN:+92 51 111 111 722 EXT: 324 Website: www.bestway.com.pk E-mail: riffat.tahira@bestway.com.pk | K83: Send
A84: CDKE-HZJ-BY | F84: UV COATING MACHINE | G84: Siddiqui Process
A85: CDOJ-ELW-PF | F85: ELECTRIC SPRING RETURN ACTATOR , P/N- M9206-BDB-1S MANUFACTURER JOHNSON CONTROLS QTY 2 EA | G85: Tarik Aziz Aziz Engineering / Aziz Group Pakistan | K85: Send
A86: CEGH-WVR-ZQ | F86: 13mm Stainless Steel Syringe Filter Holder ( Picture Attached ) | G86: Navid Nawaz Senior Procurement Officer BF Biosciences Limited (A Subsidiary of Ferozsons Laboratories Ltd.) 5-km Raiwind Road Opposite Ijtima Chowk, Sunder Road, Raiwind, Lahore PABX: 042-3602700, Ext: 140 Cell: 0308-4442549 | K86: Send
A87: CFKN-WQV-ID | F87: Glass Ware With and without Certificate | G87: Muhammad Zeeshan Mobile No.: 0335-2565477 Tel. Nos. ++92-21-35121963 - 64 Ext No. 2216 Healthtek (Pvt.)Limited | K87: Send
A88: CFYT-DQJ-RS | B88: Inquiry received by e-mail | F88: Automa valve actuator double Model AD 40-25Si serial number A110819-08 Made in Korea | G88: Ashraf Butt CHC Procurement Officer GlaxoSmithKline CHC Pakistan Limited. 35 - Dockyard Road, west wharf , Karachi-74000, Pakistan Tel: +92 21 32315478-82 & (Dir) 35274744 UAN:+92 21 111 475 725 (Ext: 4744 | H88: -Contact Person: Mr. Zakir Raza - 0304-0729713 | K88: Send
A89: CHBF-IRI-UM | B89: Quotation Sent | F89: Gear box Cone Drive model HHU 35A754-W3 nameplate attached | G89: Ashraf Butt CHC Procurement Officer GlaxoSmithKline CHC Pakistan Limited. 35 - Dockyard Road, west wharf , Karachi-74000, Pakistan Tel: +92 21 32315478-82 & (Dir) 35274744 UAN:+92 21 111 475 725 (Ext: 4744) | H89: -Contact Person; Mr. Zakir Raza- 03040729713 | K89: Send
A90: CHSV-WHK-EG | B90: Quotation Sent | F90: THREE PHASE ASYNCHRONOUS MOTOR FOR THRUSTER (TROLLEY TRAVELLING),THREE PHASE ASYNCHRONOUS MOTOR, YDT80 , POWER: 80W, 2800R/MIN, CURRENT:0.26A, FREQUENCY: 50HZ, IP44, TIANLI ELECTRICAL MICROMACHINE FACTORY OF NANZHAO COUNTY (FOR CRAB CRANE) EA 02 | G90: Riffat Tahira Procurement Officer Processing Section Department of Procurement Bestway Cement Limited | 8th Floor | UBL Building, Jinnah Avenue | Islamabad 44000, Pakistan. Tel: +92 51 835 5139 | UAN:+92 51 111 111 722 EXT: 324 Website: www.bestway.com.pk E-mail: riffat.tahira@bestway.com.pk | K90: Send
A91: CHVZ-WKL-WQ | B91: Inquiry received by e-mail | F91: Automa valve actuator double Model AD 40-25Si \ serial number A110819-08 Made in Korea | G91: Ashraf Butt CHC Procurement Officer GlaxoSmithKline CHC Pakistan Limited. 35 - Dockyard Road, west wharf , Karachi-74000, Pakistan Tel: +92 21 32315478-82 & (Dir) 35274744 UAN:+92 21 111 475 725 (Ext: 4744) | K91: Send
A92: CILA-SCQ-CB | B92: Quotation Sent | F92: 1. Numatics Solenoid Valve 031SA4004000061 03 Nos | G92: Hussain Riaz | Assistant Manager Procurement The Searle Company Limited Address: F-319 SITE, Karachi, Pakistan Work: +(92-21) 3257-8001-7 | Ext: 3084 Cell: +(92) 333 3829055 Email:Hussain.riaz@searlecompany.com | K92: Send
A93: CKFA-FFI-KI | B93: Quotation Sent | F93: TRUCLEAN SPONGE MOP(BLUE) HB#9603.90.0000 Part No. 22-34 Qty 10 | G93: Azeem Soomro Associate Manager Procurement Tel : +9221-111-111-511 Ext. 2866 Direct : +9221- 38636046 Mobile : +92320-1212340 | H93: U9R-EHF-9TUF-QOV previous code | K93: Send
A94: CLDK-DUW-ET | B94: Inquiry received by e-mail | F94: 1011601057 Bumhan Transformer 1? 0.3KVA BHTB-DR300 EA 1 1011601057 Bumhan Transformer 1? 0.075KVA BHTBD01G1 EA 1 | G94: Hussain Riaz | Assistant Manager Procurement The Searle Company Limited Address: F-319 SITE, Karachi, Pakistan Work: +(92-21) 3257-8001-7 | Ext: 3084 Cell: +(92) 333 3829055 Email:Hussain.riaz@searlecompany.com | K94: Send
A95: CLDQ-FGK-MD | B95: Quotation Sent | F95: Sensor Z3N-T22 No's 6 6 Sensor JULONG | G95: • Mr. Javed Iqbal 0301-2501645 (Engineering) • Mr. Mazhar 0300-2381732 (Maintenance Engg) • Mr. Rashid 0333-3732737 (Electrical) • Mr. Ahmed 0334-3208748 (Maintenance Engg) Regards, Syed Feham Ali Executive Procurement (Engineering) Supply Chain Department 0331-2477981
A96: CMHR-IOY-YC | B96: Quotation Sent | F96: Gast Air motor Model NL32-NCC-1 Qty 2 | G96: Ashraf Butt CHC Procurement Officer GlaxoSmithKline CHC Pakistan Limited. 35 - Dockyard Road, west wharf , Karachi-74000, Pakistan Tel: +92 21 32315478-82 & (Dir) 35274744 UAN:+92 21 111 475 725 (Ext: 4744)
A97: CMHX-RVD-IV | B97: Quotation Sent | F97: Watson Marlow pump 520 loadsure Element TL Bioprene 9.6MM with PVDF Part No. 903.0096.PFT Qty 1 | G97: Ashraf Butt CHC Procurement Officer GlaxoSmithKline CHC Pakistan Limited. 35 - Dockyard Road, west wharf , Karachi-74000, Pakistan Tel: +92 21 32315478-82 & (Dir) 35274744 UAN:+92 21 111 475 725 (Ext: 4744)
A98: CNJC-VBC-KG | B98: Order Arrived | F98: Mechanical Seal for KPA Pumps Type : KNL 35H/1A with Viton O-Ring For High Temperature 03 Nos. | G98: Syed Masood Hasan Imports Department BF BIOSCIENCES LIMITED (A Subsidiary of Ferozsons Labs Ltd) Head Office/Biotech Factory, 5-Km; Sundar-Raiwind Road, Opposite Ijtima Chowk Raiwind, Lahore-Pakistan. Tel Dir # : +92-42-3602 6789 PABX # : +92-42-3602 6700 Cell # : +92-307-444 00 78 Cell # : +92-301-44 66 851 Email : masood.hasan@bfbio.com masood.hasan@ferozsons-labs.com
A99: COAQ-MPD-OD | B99: Inquiry received by e-mail | F99: VFD Siemens 480v 2.2 KW SED2-2.2/35B EA 1 VFD Siemens 480v 15.0 KW SED2-15/35B EA 1 Siemens Safety Relays 3TK2845-1DB41 EA 1 | G99: Hussain Riaz | Assistant Manager Procurement The Searle Company Limited Address: F-319 SITE, Karachi, Pakistan Work: +(92-21) 3257-8001-7 | Ext: 3084 Cell: +(92) 333 3829055 Email:Hussain.riaz@searlecompany.com
A100: CPXE-DFM-PP | B100: Inquiry received by e-mail | F100: Really White-Rodgers 90-2930RBM Type 84 EA 2 | G100: Hussain Riaz | Assistant Manager Procurement The Searle Company Limited Address: F-319 SITE, Karachi, Pakistan Work: +(92-21) 3257-8001-7 | Ext: 3084 Cell: +(92) 333 3829055 Email:Hussain.riaz@searlecompany.com
...

Sheet Projects sheet 3
B1: Internal Status | C1: Project External Process | D1: Enquiry Came through | E1: Date of enquiry | F1: Customer Requirement Arsalan | G1: CUSTOMER DETAILS | H1: Comments ANY ONE | I1: Enquiry Arrival Date | J1: LINKS STATUS | K1: ACKNOWEDGMENT | L1: Analysis of Customer Enquiry Zafar | M1: Database Prepared by Saad/Kaif/Zafar/Maaz | N1: Enquiry Analysis & links provided by | O1: Enquiry Letter Made and Sent by | P1: Supplier email checked Yasir/Saad/ Arsalan/Zafar | Q1: Price Calculated by Arsalan | R1: Quotation Prepared by | S1: Quotation Follow up done by | T1: Order Processed By | U1: Payment Follow up Done by | V1: Number of Quotation Received | W1: Name of Database | X1: Weblinks | Y1: Weblink status | AA1: Project code Raw
A2: =_xludf.CONCAT(AH2,_xludf.CONCAT("-",AI2)) -> #NAME? | B2: Quotation Sent | D2: Qamar uddin | F2: Dissolution test apparatus with 12 vessels | G2: Barrett Hodgson Pakistan (Pvt) Ltd. saeed.ahmed@BarrettHodgson.com general.purchase@barretthodgson.com | H2: 9M9-5FR-JEY-TZZI QHD-RAK-4Y3-K055 KU8-TAB-YZX-5A1X check above codes for old quotation Hasan: Quotation Sent on 15-04-19 Hasan: Quotation validity reminder sent on 22-04-19 | I2: 43563 | J2: =IF(X2="","LINKS REQUIRED",IF(X2="Completed","LINKS HARVESTED","LINKS AVAILABLE")) -> LINKS REQUIRED | AA2: 3TEBFSTXUYK3IOU | AB2: =LEFT(AA2,6) -> 3TEBFS | AC2: =LEFT(AB2,3) -> 3TE | AD2: =RIGHT(AB2,3) -> BFS | AE2: =RIGHT(AA2,7) -> UYK3IOU | AF2: =LEFT(AE2,4) -> UYK3 | AG2: =RIGHT(AE2,3) -> IOU | AH2: =_xludf.CONCAT(AC2,_xludf.CONCAT("-",AD2)) -> #NAME? | AI2: =_xludf.CONCAT(AF2,_xludf.CONCAT("-",AG2)) -> #NAME?
A3: =_xludf.CONCAT(AH3,_xludf.CONCAT("-",AI3)) -> #NAME? | B3: Request for further information sent to customer | D3: Qamar uddin | F3: Liquid borne particle counter | G3: Barrett Hodgson Pakistan (Pvt) Ltd. saeed.ahmed@BarrettHodgson.com general.purchase@barretthodgson.com | H3: Arsalan: forwaded supplier questions to Barret | I3: 43563 | J3: =IF(X3="","LINKS REQUIRED",IF(X3="Completed","LINKS HARVESTED","LINKS AVAILABLE")) -> LINKS HARVESTED | M3: Saad | O3: Saad | W3: liquid borne particle counter | X3: Completed | Y3: https://www.google.com/search?newwindow=1&biw=1745&bih=852&ei=pdiqXLC6K9GUkgXc3YrQAg&q=liquid+borne+particle+counter+manufacturers&oq=liquid+borne+particle+counter+manufa&gs_l=psy-ab.1.0.0i22i30.7214.10829..12181...0.0..0.186.1279.0j7......0....1..gws-wiz.......0i71j0.yIL2-8f4Pew https://www.google.com/search?newwindow=1&biw=1745&bih=852&ei=stiqXNjmHOTjkgX9_ZDQAg&q=liquid+borne+particle+counter+suppliers&oq=liquid+borne+particle+counter+suppliers&gs_l=psy-ab.3..33i160.18364.20827..20980...0.0..0.222.1764.0j6j3......0....1..gws-wiz.......0i71j35i39j0j0i22i30j33i22i29i30j33i21j33i13i21.aZIHlBwTD58 | AA3: 3UXQ3I9XHBN89ID | AB3: =LEFT(AA3,6) -> 3UXQ3I | AC3: =LEFT(AB3,3) -> 3UX | AD3: =RIGHT(AB3,3) -> Q3I | AE3: =RIGHT(AA3,7) -> HBN89ID | AF3: =LEFT(AE3,4) -> HBN8 | AG3: =RIGHT(AE3,3) -> 9ID | AH3: =_xludf.CONCAT(AC3,_xludf.CONCAT("-",AD3)) -> #NAME? | AI3: =_xludf.CONCAT(AF3,_xludf.CONCAT("-",AG3)) -> #NAME?
A4: =_xludf.CONCAT(AH4,_xludf.CONCAT("-",AI4)) -> #NAME? | B4: Quotation Sent | D4: A. Anwar Khan | F4: Current Transducer Model:COR IA AC Make: REVALCO INPUT lA, 5A AC OUTPUT SELECTABLE V-DC 1.5-10 mA DC 1.5-10-20 qty: 4 | G4: Engro Fertilizer Muhammad Baqar Ali Cell #:+923008690335 Email:mbali@engro.com | H4: Hasan: Quotation sent on 09-04-19 Hasan: Quotation validity reminder sent (16-04-19) | I4: 43562 | J4: =IF(X4="","LINKS REQUIRED",IF(X4="Completed","LINKS HARVESTED","LINKS AVAILABLE")) -> LINKS HARVESTED | M4: Maaz | O4: Saad | W4: current transducer (REVALCO) | X4: Completed | Y4: https://www.google.com/search?newwindow=1&biw=1745&bih=852&ei=PtmqXOSUMK3osAfc6p6gCQ&q=REVALCO+COR+IA+&oq=REVALCO+COR+IA+&gs_l=psy-ab.3..35i39j0i22i30l2.129088.129088..129520...0.0..0.306.306.3-1......0....1..gws-wiz.F3PpfaLFglk https://www.google.com/search?newwindow=1&biw=1745&bih=852&ei=wdmqXOjHC4vhkgXs-KKQCg&q=revalco+cor+ia+ac+current+transducer&oq=REVALCO+COR+IA&gs_l=psy-ab.1.2.35i39l2j0i22i30.11453.14852..16775...1.0..0.310.899.2-2j1......0....1..gws-wiz.......0i22i10i30.pbO_olUQ_aw https://www.google.com/search?newwindow=1&biw=1745&bih=852&ei=0tmqXLeLL8SMkgXWhp64Dw&q=revalco+suppliers&oq=revalco+suppliers&gs_l=psy-ab.3..0.18952.28039..28928...0.0..0.287.2788.2-10......0....1..gws-wiz.......35i39j0i20i263j0i22i30.FY6okmunimY | AA4: 4X87RUE7HX4Z5DX | AB4: =LEFT(AA4,6) -> 4X87RU | AC4: =LEFT(AB4,3) -> 4X8 | AD4: =RIGHT(AB4,3) -> 7RU | AE4: =RIGHT(AA4,7) -> HX4Z5DX | AF4: =LEFT(AE4,4) -> HX4Z | AG4: =RIGHT(AE4,3) -> 5DX | AH4: =_xludf.CONCAT(AC4,_xludf.CONCAT("-",AD4)) -> #NAME? | AI4: =_xludf.CONCAT(AF4,_xludf.CONCAT("-",AG4)) -> #NAME?
A5: =_xludf.CONCAT(AH5,_xludf.CONCAT("-",AI5)) -> #NAME? | B5: Quotation Sent | D5: A. Anwar Khan | F5: Positive Displacement Air Blower Model GM4S Make Aerzen , excluding Electric motor for CF silo, | G5: STAR IMPEX INTERNATIONAL Suite # 5, 3rd Floor Imtiaz Centre, Gulberg II, Main Market, Lahore, 54660, Pakistan Mohammad Abdullah | Manager Commercial Tel: +92-42-35712969 Email: abdullah@starimpex.com | H5: Hasan: Quotation sent on 18-04-19 Hasan: Quotation validity reminder sent (25-04-19) | I5: 43562 | J5: =IF(X5="","LINKS REQUIRED",IF(X5="Completed","LINKS HARVESTED","LINKS AVAILABLE")) -> LINKS HARVESTED | M5: Maaz | O5: Saad | W5: Positive Displacement Air Blower (Aerzen) | X5: Completed | Y5: https://www.google.com/search?newwindow=1&ei=AdqqXImzN4j5sAfdxpewAQ&q=Aerzen+GM4S&oq=Aerzen+GM4S&gs_l=psy-ab.3...4941.7964..8245...0.0..0.288.1106.2-4......0....1j2..gws-wiz.......0i71j35i39.eLAGPVJcO30 https://www.google.com/search?newwindow=1&ei=C9qqXMeLBci1sAf7oLMw&q=Aerzen+GM4S+suppliers&oq=Aerzen+GM4S+suppliers&gs_l=psy-ab.3...7970.11802..12978...0.0..0.373.2948.2-7j3......0....1..gws-wiz.......0i71j0i22i30j33i160.fZu-rZ2fR_Q | AA5: 4XJS7MZIFM92BGS | AB5: =LEFT(AA5,6) -> 4XJS7M | AC5: =LEFT(AB5,3) -> 4XJ | AD5: =RIGHT(AB5,3) -> S7M | AE5: =RIGHT(AA5,7) -> FM92BGS | AF5: =LEFT(AE5,4) -> FM92 | AG5: =RIGHT(AE5,3) -> BGS | AH5: =_xludf.CONCAT(AC5,_xludf.CONCAT("-",AD5)) -> #NAME? | AI5: =_xludf.CONCAT(AF5,_xludf.CONCAT("-",AG5)) -> #NAME?
A6: =_xludf.CONCAT(AH6,_xludf.CONCAT("-",AI6)) -> #NAME? | B6: Quotation Sent | D6: A. Anwar Khan | F6: Choke 250 W (HID BALLAST) Rating 220V-AC. Model: BSNE 250L-3001TS, 9137 130 194 :250W Manufacturer: PHILIPS Qty: 25 SI 51 Plus Ignitor, wattage : 250-400-1000W Voltage : 220V AC -240V AC fn :50/60Hz Manufacturer: PHILIPS Qty: 30 Due Date 11.04.2019 | G6: Muhammad Baqar Ali Cell #:+923008690335 Email:mbali@engro.com RFQ Number 3700022339 | H6: Hasan: Quotation sent on 11-04-19 Hasan: Quotation validity reminder sent (18-04-19) | I6: 43563 | J6: =IF(X6="","LINKS REQUIRED",IF(X6="Completed","LINKS HARVESTED","LINKS AVAILABLE")) -> LINKS HARVESTED | M6: Maaz | O6: Saad | W6: Choke 250 W (HID BALLAST) (PHILIPS) | X6: Completed | Y6: https://www.google.com/search?q=BSNE+250L-3001TS&oq=BSNE+250L-3001TS&aqs=chrome..69i57&sourceid=chrome&ie=UTF-8 https://www.google.com/search?newwindow=1&ei=LCCrXNTyLo2rgwfYyJzYCQ&q=BSNE+250L-3001TS+suppliers&oq=BSNE+250L-3001TS+suppliers&gs_l=psy-ab.3..33i160l2.77140.79418..79595...0.0..0.609.3443.4-4j3......0....1..gws-wiz.......35i302i39.NdSw5i5wD_M https://www.google.com/search?q=SI+51+Plus+Ignitor&oq=SI+51+Plus+Ignitor&aqs=chrome..69i57&sourceid=chrome&ie=UTF-8 | AA6: 41WJDX57X1BV8TC | AB6: =LEFT(AA6,6) -> 41WJDX | AC6: =LEFT(AB6,3) -> 41W | AD6: =RIGHT(AB6,3) -> JDX | AE6: =RIGHT(AA6,7) -> X1BV8TC | AF6: =LEFT(AE6,4) -> X1BV | AG6: =RIGHT(AE6,3) -> 8TC | AH6: =_xludf.CONCAT(AC6,_xludf.CONCAT("-",AD6)) -> #NAME? | AI6: =_xludf.CONCAT(AF6,_xludf.CONCAT("-",AG6)) -> #NAME?
A7: =_xludf.CONCAT(AH7,_xludf.CONCAT("-",AI7)) -> #NAME? | B7: Request for further information sent to customer | D7: Qamar uddin | F7: Sejong dust collector cartage filter Model SFC-170FSH Serial number SC 11278 Description Cartridge filter Material Polyester Size as in manual Ø145MM X 600L x 75th Required quantity 16 nos | G7: Ashraf Butt Procurement Officer GlaxoSmithKline Consumer Healthcare Pakistan Ltd. 35 - Dockyard Road, west wharf , Karachi Tel: 35274744 (Ext: 4744) ashraf.x.butt@gsk.com Contact Person: Mr. Zakir Raza - 03112317017 - 0222109534 | H7: Boss requested more informaiton on filter | I7: 43563 | J7: =IF(X7="","LINKS REQUIRED",IF(X7="Completed","LINKS HARVESTED","LINKS AVAILABLE")) -> LINKS REQUIRED | AA7: 42B8NUJHXUJHGC4 | AB7: =LEFT(AA7,6) -> 42B8NU | AC7: =LEFT(AB7,3) -> 42B | AD7: =RIGHT(AB7,3) -> 8NU | AE7: =RIGHT(AA7,7) -> XUJHGC4 | AF7: =LEFT(AE7,4) -> XUJH | AG7: =RIGHT(AE7,3) -> GC4 | AH7: =_xludf.CONCAT(AC7,_xludf.CONCAT("-",AD7)) -> #NAME? | AI7: =_xludf.CONCAT(AF7,_xludf.CONCAT("-",AG7)) -> #NAME?
A8: =_xludf.CONCAT(AH8,_xludf.CONCAT("-",AI8)) -> #NAME? | B8: Quotation Sent | D8: A. Anwar Khan | F8: 3 PHASE INDUCTION MOTOR WITH COOLING FAN, TYPE:VFD MOTOR ,YVF2-132S2-2,7.5KW,14.5A, 380V,2900RPM,25.6NM,CL. F, 5-50HZ,50-100HZ,IM V1,COOLING,FAN:TYPE: G-132,80W,380V,0.41A,1300RPM,AIR VOLUME 760M3/H,AIR PRESSURE 50PA,LINE-II NOS 1 3 PHASE INDUCTION MOTOR, TYPE: 132M-4 , 7.5KW, 14.8A, 1440RPM, IP55, 50HZ, 400V, CONN. D, PF 0.84, INSCL. F,DUTY S1, IM B5 FOR LINE-II NOS 1 YVF2-132M-4 SPI # 603 & RFQ # 6273-ELEC | G8: Best Regards, Muhammad Rehan Anwar Officer Procurement Department of Procurement Bestway Cement Limited | 8th Floor | UBL Building, Jinnah Avenue | Islamabad 44000, Pakistan. Tel: +92 51 835 5118 | Fax: +92 51 265 4865 | UAN:+92 51 111 111 722 Website: www.bestway.com.pk E-mail: rehan.anwar@bestway.com.pk | H8: https://www.google.com/search?newwindow=1&ei=SCqsXNrcJ8y4mAWskpDYCQ&q=siemens+YVF2-132S2-2&oq=siemens+YVF2-132S2-2&gs_l=psy-ab.3...4903.8205..8326...2.0..0.145.1168.0j9......0....1..gws-wiz.......0i13i30j0i13i5i30.c0bAJH7CDZo both motors specs are in first link of above link Hasan: Quotation sent on 11-04-19 Hasan: Quotation validity reminder sent Maaz: inquiry letter again fly on 3 phase motor merged database and the CODE no. is 42M-J3H-XXCC-JLE-1 (30-Apr-19) | I8: 43563 | J8: =IF(X8="","LINKS REQUIRED",IF(X8="Completed","LINKS HARVESTED","LINKS AVAILABLE")) -> LINKS HARVESTED | M8: Maaz | O8: Saad | W8: 3 PHASE INDUCTION MOTOR YVF2 | X8: Completed | Y8: http://www.beide-motor.cn/ssml/lxwm.asp https://www.google.com/search?newwindow=1&ei=SCqsXNrcJ8y4mAWskpDYCQ&q=siemens+YVF2-132S2-2&oq=siemens+YVF2-132S2-2&gs_l=psy-ab.3...4903.8205..8326...2.0..0.145.1168.0j9......0....1..gws-wiz.......0i13i30j0i13i5i30.c0bAJH7CDZo https://www.google.com/search?newwindow=1&ei=UiqsXOj5AeLUmAXurKTQDg&q=siemens+YVF2-132M-4&oq=siemens+YVF2-132M-4&gs_l=psy-ab.3...512527.512527..513427...0.0..0.151.151.0j1......0....2j1..gws-wiz.PM7Dorj_Vpo | AA8: 42MJ3HPSXXCCJLE | AB8: =LEFT(AA8,6) -> 42MJ3H | AC8: =LEFT(AB8,3) -> 42M | AD8: =RIGHT(AB8,3) -> J3H | AE8: =RIGHT(AA8,7) -> XXCCJLE | AF8: =LEFT(AE8,4) -> XXCC | AG8: =RIGHT(AE8,3) -> JLE | AH8: =_xludf.CONCAT(AC8,_xludf.CONCAT("-",AD8)) -> #NAME? | AI8: =_xludf.CONCAT(AF8,_xludf.CONCAT("-",AG8)) -> #NAME?
A9: =_xludf.CONCAT(AH9,_xludf.CONCAT("-",AI9)) -> #NAME? | B9: Request for further information sent to customer | D9: A. Anwar Khan | F9: 3-PHASE INDUCTION MOTOR INVERTER DUTY, TYPE: DRE180L4/TF, 22 KW, 42AMP, 400V, 1480 RPM, IM B5, MAKE: SEW EURODRIVE FOR LINE-II 3-PHASE INDUCTION MOTOR INVERTER DUTY, TYPE: HJN1 100L2-4, 3 KW, 6.18 AMP, 400V, 1425 RPM, IM V1, MAKE: SEW EURODRIVE FOR LINE-II SPI # 602 & RFQ # 6245-ELEC | G9: Best Regards, Muhammad Rehan Anwar Officer Procurement Department of Procurement Bestway Cement Limited | 8th Floor | UBL Building, Jinnah Avenue | Islamabad 44000, Pakistan. Tel: +92 51 835 5118 | Fax: +92 51 265 4865 | UAN:+92 51 111 111 722 Website: www.bestway.com.pk E-mail: rehan.anwar@bestway.com.pk | H9: Nameplate requested databse already availble SEW Request for further information sent to customer (No Answer) | I9: 43556 | J9: =IF(X9="","LINKS REQUIRED",IF(X9="Completed","LINKS HARVESTED","LINKS AVAILABLE")) -> LINKS REQUIRED | M9: Internal Office Staff (All for one) | O9: Saad | AA9: 4AHISH7ACSDHUFS | AB9: =LEFT(AA9,6) -> 4AHISH | AC9: =LEFT(AB9,3) -> 4AH | AD9: =RIGHT(AB9,3) -> ISH | AE9: =RIGHT(AA9,7) -> CSDHUFS | AF9: =LEFT(AE9,4) -> CSDH | AG9: =RIGHT(AE9,3) -> UFS | AH9: =_xludf.CONCAT(AC9,_xludf.CONCAT("-",AD9)) -> #NAME? | AI9: =_xludf.CONCAT(AF9,_xludf.CONCAT("-",AG9)) -> #NAME?
A10: =_xludf.CONCAT(AH10,_xludf.CONCAT("-",AI10)) -> #NAME? | B10: Quotation Sent | D10: A. Anwar Khan | F10: 3 PHASE INDUCTION MOTOR, TYPE: 1LA7063-4AB12, 63M, IM B14, 0.18KW, 400V, 0.58A, Y-CONN, 1350RPM, IP55, 50HZ FOR LINE-II NOS 1 SPI # 603 & RFQ # 6273-ELEC | G10: Best Regards, Muhammad Rehan Anwar Officer Procurement Department of Procurement Bestway Cement Limited | 8th Floor | UBL Building, Jinnah Avenue | Islamabad 44000, Pakistan. Tel: +92 51 835 5118 | Fax: +92 51 265 4865 | UAN:+92 51 111 111 722 Website: www.bestway.com.pk E-mail: rehan.anwar@bestway.com.pk | H10: Hasan: Quotation sent on 15-04-19 Hasan: Quotation validity reminder sent on 22-04-19 | I10: 43563 | J10: =IF(X10="","LINKS REQUIRED",IF(X10="Completed","LINKS HARVESTED","LINKS AVAILABLE")) -> LINKS HARVESTED | M10: Maaz | N10: Anwar Khan | O10: Saad | W10: 3 PHASE INDUCTION MOTOR 1LA7063 | X10: Completed | Y10: https://www.google.com/search?q=1LA7063-4AB12&oq=1LA7063-4AB12&aqs=chrome..69i57j0l3.527j0j9&sourceid=chrome&ie=UTF-8 https://www.google.com/search?newwindow=1&ei=ICusXMyUBMODoASc27D4Aw&q=1LA7063-4AB12+suppliers&oq=1LA7063-4AB12+suppliers&gs_l=psy-ab.3...337612.340898..341322...0.0..0.151.1274.0j10......0....1..gws-wiz.......0i30j0i5i30j0i13i30j0i22i30j33i160.VlNWkLSy24U | AA10: 4BCWTLC8SSGKW8O | AB10: =LEFT(AA10,6) -> 4BCWTL | AC10: =LEFT(AB10,3) -> 4BC | AD10: =RIGHT(AB10,3) -> WTL | AE10: =RIGHT(AA10,7) -> SSGKW8O | AF10: =LEFT(AE10,4) -> SSGK | AG10: =RIGHT(AE10,3) -> W8O | AH10: =_xludf.CONCAT(AC10,_xludf.CONCAT("-",AD10)) -> #NAME? | AI10: =_xludf.CONCAT(AF10,_xludf.CONCAT("-",AG10)) -> #NAME?
A11: =_xludf.CONCAT(AH11,_xludf.CONCAT("-",AI11)) -> #NAME? | B11: Quotation Sent | D11: A. Anwar Khan | F11: Sachet filling and sealing machine complete S.S. body sealing : four side sealing sealing type : graphic product : free flowing powder weight range : 5 - 25 gms free flowing powder filling : cup type folder size: 170 mm If possible we need batch # and expiry in sealer as well as hot ink roller printer installed ( so we can use both options simultaneously ) capacity : > 50 bags per min | G11: Qasim Mehmood Cell # 0333 2166792 Focus and Rulz Pharmaceutical Islamabad | H11: Maaz: merged it with sachet & FFS machine database Hasan: Quotation sent on 15-04-19 Hasan: Quotation validity reminder sent on 22-04-19 | I11: 43564 | J11: =IF(X11="","LINKS REQUIRED",IF(X11="Completed","LINKS HARVESTED","LINKS AVAILABLE")) -> LINKS HARVESTED | M11: Maaz | O11: Saad | W11: Sachet filling and sealing machine | X11: Completed | Y11: https://www.google.com/search?newwindow=1&ei=XL-tXMyJE5mGoAS0l6XgAw&q=Sachet+filling+and+sealing+machine+manufacturers+&oq=Sachet+filling+and+sealing+machine+manufacturers+&gs_l=psy-ab.3..0i22i30.14434.17737..18018...0.0..0.163.2230.0j15......0....1..gws-wiz.......0i71j0j33i22i29i30.5R6L0QTVMcM | AA11: 4BDJNXDRU5GWI05 | AB11: =LEFT(AA11,6) -> 4BDJNX | AC11: =LEFT(AB11,3) -> 4BD | AD11: =RIGHT(AB11,3) -> JNX | AE11: =RIGHT(AA11,7) -> U5GWI05 | AF11: =LEFT(AE11,4) -> U5GW | AG11: =RIGHT(AE11,3) -> I05 | AH11: =_xludf.CONCAT(AC11,_xludf.CONCAT("-",AD11)) -> #NAME? | AI11: =_xludf.CONCAT(AF11,_xludf.CONCAT("-",AG11)) -> #NAME?
A12: =_xludf.CONCAT(AH12,_xludf.CONCAT("-",AI12)) -> #NAME? | B12: Request for further information sent to customer | D12: Qamar uddin | F12: Cartoner Machine mouth 2 pic Pictures in email | G12: Ashraf Butt Procurement Officer GlaxoSmithKline Consumer Healthcare Pakistan Ltd. 35 - Dockyard Road, west wharf , Karachi Tel: 35274744 (Ext: 4744) ashraf.x.butt@gsk.com | I12: 43564 | J12: =IF(X12="","LINKS REQUIRED",IF(X12="Completed","LINKS HARVESTED","LINKS AVAILABLE")) -> LINKS REQUIRED | AA12: 4CIDRQRGTNA1YB9 | AB12: =LEFT(AA12,6) -> 4CIDRQ | AC12: =LEFT(AB12,3) -> 4CI | AD12: =RIGHT(AB12,3) -> DRQ | AE12: =RIGHT(AA12,7) -> TNA1YB9 | AF12: =LEFT(AE12,4) -> TNA1 | AG12: =RIGHT(AE12,3) -> YB9 | AH12: =_xludf.CONCAT(AC12,_xludf.CONCAT("-",AD12)) -> #NAME? | AI12: =_xludf.CONCAT(AF12,_xludf.CONCAT("-",AG12)) -> #NAME?
A13: =_xludf.CONCAT(AH13,_xludf.CONCAT("-",AI13)) -> #NAME? | B13: Inquiry letter sent | D13: Qamar uddin | F13: Becteriological Agar For Molecular Biology 1 KG Biological Indicator-Strips ATCC No.2714 2 EA Bordetella Bronchiseptica ATCC#4617 1 EA Candida Albican ATCC # 10231 1 EA Clostridrium Sporogens ATCC # 11437 1 EA Dextrose Oxoid Cat#LP0071 200 KG E. Coli ATCC# 14169 1 EA E.Coli ATCC # 8739 1 EA Enterococcus Hirac ATCC # 8043 1 EA Pseudomonas Aeroginosa ATCC # 9027 1 EA | G13: saeed.ahmed@BarrettHodgson.com | H13: From first link find all europe distributor and germany nebour countires Saad: Inquiry Letter Sent Again with Ameneded Letter (12 Apr 19) on Merged Bacteria Database | I13: 43565 | J13: =IF(X13="","LINKS REQUIRED",IF(X13="Completed","LINKS HARVESTED","LINKS AVAILABLE")) -> LINKS HARVESTED | M13: Maaz | O13: Saad | W13: Becteriological Agar For Molecular Biology | X13: Completed | Y13: https://www.atcc.org/Support/Find_ATCC_Distributors.aspx https://www.google.com/search?newwindow=1&ei=eYKtXOmyDYT1wAOjsI7IBQ&q=ATCC%23+10231&oq=ATCC%23+10231&gs_l=psy-ab.3..0i22i30l7.21201.21201..22063...0.0..0.115.115.0j1......0....2j1..gws-wiz.......0i71.w46ioEBQmUQ https://www.google.com/search?newwindow=1&ei=kIKtXMaSKMz4hwPS6LO4Dg&q=ATCC+suppliers+in+europe&oq=ATCC+suppliers+in+europe&gs_l=psy-ab.3..33i22i29i30.98873.106711..106825...0.0..0.122.2318.0j20......0....1..gws-wiz.......0i71j35i39j0i67j0j0i20i263j0i22i30j0i22i10i30.FRiEwgTUzqQ | AA13: 4DGUNXICKT4FZ3S | AB13: =LEFT(AA13,6) -> 4DGUNX | AC13: =LEFT(AB13,3) -> 4DG | AD13: =RIGHT(AB13,3) -> UNX | AE13: =RIGHT(AA13,7) -> KT4FZ3S | AF13: =LEFT(AE13,4) -> KT4F | AG13: =RIGHT(AE13,3) -> Z3S | AH13: =_xludf.CONCAT(AC13,_xludf.CONCAT("-",AD13)) -> #NAME? | AI13: =_xludf.CONCAT(AF13,_xludf.CONCAT("-",AG13)) -> #NAME?
A14: =_xludf.CONCAT(AH14,_xludf.CONCAT("-",AI14)) -> #NAME? | B14: Quotation Sent | D14: A. Anwar Khan | F14: PH METER RANGE=0.0 TO 14.0 PH, HAND HELD TYPE, RANGE= 0.014 PH, RESOLUTION= 0.1 PH, ACCURACY= + OR - 0.1 pH, HOLD FUNCTION= YES, MAKE: EU TECH INSTRUMENT, MADE IN MALAYSIA. Qty 02 | G14: Martin Dow Marker Ltd Formerly Merck (Pvt.) Ltd. D-7, Shaheed-e-Millat Road, Karachi-75350, Pakistan UAN : +92 21 111 523 523 Fax : +92 21 3455 92 21 Nasiruddin Khan Manager Sourcing- Technical operations services) | Procurement nasiruddin.khan@martindow.com | H14: Arsalan: EcoTestr pH 1 do work on this Hasan: Quotation sent on 16-04-19 Hasan: Quotation validity reminder sent (23-04-19) | I14: 43565 | J14: =IF(X14="","LINKS REQUIRED",IF(X14="Completed","LINKS HARVESTED","LINKS AVAILABLE")) -> LINKS HARVESTED | M14: Maaz | O14: Maaz | W14: PH METER HAND HELD TYPE | X14: Completed | Y14: http://www.eutechinst.com/contact-offices.html https://www.google.com/search?newwindow=1&biw=1745&bih=852&ei=hqCtXPquGsXbhwPwubPYBQ&q=eutech+instruments+malaysia&oq=EUTECH+INSTRUMENT+mal&gs_l=psy-ab.1.0.0i22i30.110934.112069..113421...0.0..0.119.475.0j4......0....1..gws-wiz.......0i71j0i22i10i30.9N8hUJN6RdE https://www.google.com/search?newwindow=1&biw=1745&bih=852&ei=-KCtXNzeJ42A-Qb67qe4Cg&q=eutech+instruments+ph+meter+suppliers&oq=eutech+instruments+ph+meter+suppl&gs_l=psy-ab.1.0.33i21l2j33i160.172904.176639..177968...0.0..0.208.1014.0j6j1......0....1..gws-wiz.......0i71j35i39j0j0i22i30j33i22i29i30.jdNBhSvhFBA https://www.google.com/search?newwindow=1&ei=Xxu0XKmLE8rfvgT444Iw&q=EcoTestr+pH+1+Eutech+Instruments&oq=EcoTestr+pH+1+Eutech+Instruments&gs_l=psy-ab.3...85233.87376..87896...0.0..0.192.572.0j4......0....1j2..gws-wiz.......0i22i30.MsyQvcUVF5s https://www.google.com/search?newwindow=1&ei=uBu0XOC2D4zSvwSsgonADw&q=EcoTestr+pH+1+Eutech+Instruments+SUPPLIERS&oq=EcoTestr+pH+1+Eutech+Instruments+SUPPLIERS&gs_l=psy-ab.3...10138.11994..12138...0.0..0.150.1370.0j10......0....1..gws-wiz.......0i71j35i302i39j33i160j33i21.nip6Y6Wm1i0 | AA14: 4DTCWASZ9X17QE6 | AB14: =LEFT(AA14,6) -> 4DTCWA | AC14: =LEFT(AB14,3) -> 4DT | AD14: =RIGHT(AB14,3) -> CWA | AE14: =RIGHT(AA14,7) -> 9X17QE6 | AF14: =LEFT(AE14,4) -> 9X17 | AG14: =RIGHT(AE14,3) -> QE6 | AH14: =_xludf.CONCAT(AC14,_xludf.CONCAT("-",AD14)) -> #NAME? | AI14: =_xludf.CONCAT(AF14,_xludf.CONCAT("-",AG14)) -> #NAME?
A15: =_xludf.CONCAT(AH15,_xludf.CONCAT("-",AI15)) -> #NAME? | B15: Quotation Sent | D15: A. Anwar Khan | F15: ENCODER 942670 Z HENGSTLER Encoder 0 543 118/2 RA58-P/0012 EK. 4 2 CICB 10-30VDC = /0.2A/V 1.04 Qty 1 | G15: Mohammad Abdullah | Manager Commercial Tel: +92-42-35712969 Email: abdullah@starimpex.com STAR IMPEX INTERNATIONAL Suite # 5, 3rd Floor Imtiaz Centre, Gulberg II, Main Market, Lahore, 54660, Pakistan | H15: H9A-95-MSC-AB R6U-7X-2EW-PR R81-BS-9NW-4C info@hengstler.com Merge above codes databases and flly the Enquiry Hasan: Quotation sent on 11-04-19 Hasan: Quotation validity reminder sent (18-04-19) | I15: 43565 | J15: =IF(X15="","LINKS REQUIRED",IF(X15="Completed","LINKS HARVESTED","LINKS AVAILABLE")) -> LINKS HARVESTED | M15: Maaz | O15: Saad | W15: HENGSTLER Encoder 942670 Z | X15: Completed | AA15: 4FNJEDZF4FJGS8Y | AB15: =LEFT(AA15,6) -> 4FNJED | AC15: =LEFT(AB15,3) -> 4FN | AD15: =RIGHT(AB15,3) -> JED | AE15: =RIGHT(AA15,7) -> 4FJGS8Y | AF15: =LEFT(AE15,4) -> 4FJG | AG15: =RIGHT(AE15,3) -> S8Y | AH15: =_xludf.CONCAT(AC15,_xludf.CONCAT("-",AD15)) -> #NAME? | AI15: =_xludf.CONCAT(AF15,_xludf.CONCAT("-",AG15)) -> #NAME?
A16: =_xludf.CONCAT(AH16,_xludf.CONCAT("-",AI16)) -> #NAME? | B16: Closed | D16: Qamar uddin | F16: Media bottle 2L ISO LAB | G16: saeed.ahmed@BarrettHodgson.com | H16: (Arsalan)Quantity confirm nai inquiry flow kr di bhang peetay ho | I16: 43566 | J16: =IF(X16="","LINKS REQUIRED",IF(X16="Completed","LINKS HARVESTED","LINKS AVAILABLE")) -> LINKS HARVESTED | M16: Saad | O16: Saad | X16: Completed | Y16: http://www.isolab.de/en-us/contact-info https://www.google.com/search?newwindow=1&biw=1745&bih=852&ei=femuXNGzG4T4vgTcg4agCQ&q=media+bottle+2L+ISOLAB+supplier&oq=media+bottle+2L+ISOLAB+supplier&gs_l=psy-ab.3..33i160.179210.180927..182160...0.0..0.168.1343.0j9......0....1..gws-wiz.......35i302i39.cIHbvsWVwps | AA16: 4IIJXRPFRJRCTZG | AB16: =LEFT(AA16,6) -> 4IIJXR | AC16: =LEFT(AB16,3) -> 4II | AD16: =RIGHT(AB16,3) -> JXR | AE16: =RIGHT(AA16,7) -> RJRCTZG | AF16: =LEFT(AE16,4) -> RJRC | AG16: =RIGHT(AE16,3) -> TZG | AH16: =_xludf.CONCAT(AC16,_xludf.CONCAT("-",AD16)) -> #NAME? | AI16: =_xludf.CONCAT(AF16,_xludf.CONCAT("-",AG16)) -> #NAME?
A17: =_xludf.CONCAT(AH17,_xludf.CONCAT("-",AI17)) -> #NAME? | B17: Closed | D17: Qamar uddin | F17: Media bottle 2L VWR | G17: saeed.ahmed@BarrettHodgson.com | H17: (Arsalan)Quantity confirm nai inquiry flow kr di bhang peetay ho | I17: 43566 | J17: =IF(X17="","LINKS REQUIRED",IF(X17="Completed","LINKS HARVESTED","LINKS AVAILABLE")) -> LINKS HARVESTED | M17: Maaz | O17: Saad | W17: Media bottle 2L VWR | X17: Completed | Y17: https://www.google.com/search?q=%22%40avantorsciences.com%22+Emails&oq=%22%40avantorsciences.com%22+Emails&aqs=chrome..69i57.12927j0j9&sourceid=chrome&ie=UTF-8 https://us.vwr.com/cms/contact_main https://www.google.com/search?newwindow=1&ei=U-muXPa7DsLZvgTi7bOICg&q=media+bottle+2L+VWR+suppliers&oq=media+bottle+2L+VWR+suppliers&gs_l=psy-ab.3..33i160.245931.248787..248907...0.0..0.152.1330.0j10......0....1..gws-wiz.......0i71j35i39j33i22i29i30j33i21.b-33bTZReW4 | AA17: 4K1EN8XET47ADI1 | AB17: =LEFT(AA17,6) -> 4K1EN8 | AC17: =LEFT(AB17,3) -> 4K1 | AD17: =RIGHT(AB17,3) -> EN8 | AE17: =RIGHT(AA17,7) -> T47ADI1 | AF17: =LEFT(AE17,4) -> T47A | AG17: =RIGHT(AE17,3) -> DI1 | AH17: =_xludf.CONCAT(AC17,_xludf.CONCAT("-",AD17)) -> #NAME? | AI17: =_xludf.CONCAT(AF17,_xludf.CONCAT("-",AG17)) -> #NAME?
A18: =_xludf.CONCAT(AH18,_xludf.CONCAT("-",AI18)) -> #NAME? | B18: Quotation Sent | C18: second quotatioin sent | D18: Qamar uddin | F18: 1. Electronic Thermostat (Digital). Make: Novus /Autonics / Omron / Mitsubishi / AKO (Spain). Temperature range: 50 ˚C to 300 ˚C. Inputs: Two PT100 inputs. Outputs: Two dry contact outputs (SPDT). Access Level: Minimum 3 digits Password protection. Quantity: 04 Nos (Controller With Sensor Complete Unit). | G18: Ashraf Butt Procurement Officer GlaxoSmithKline Consumer Healthcare Pakistan Ltd. 35 - Dockyard Road, west wharf , Karachi Tel: 35274744 (Ext: 4744) ashraf.x.butt@gsk.com | H18: Do not put Brand name in enquiry my links include all brands Hasan: Quotation sent on 16-04-19 Hasan: Quotation validity reminder sent on 23-04-19 Hasan: 2nd Quotation sent on 17-04-19 Hasan: Quotation validity reminder sent on 24-04-19 | I18: 43567 | J18: =IF(X18="","LINKS REQUIRED",IF(X18="Completed","LINKS HARVESTED","LINKS AVAILABLE")) -> LINKS HARVESTED | M18: Maaz | O18: Maaz | W18: Electronic Thermostat Digital (All brands) | X18: Completed | Y18: https://www.google.com/search?newwindow=1&ei=kWiwXM_gJ8LTz7sP8beDkAg&q=ako+%28spain%29+electronic+thermostat+%28digital%29+suppliers+-%22pdf%22+-%22amazon%22+-%22ebay%22+-%22youtube%22&oq=ako+%28spain%29+electronic+thermostat+%28digital%29+suppliers+-%22pdf%22+-%22amazon%22+-%22ebay%22+-%22youtube%22&gs_l=psy-ab.3...2285.2285..2578...0.0..0.109.109.0j1......0....1..gws-wiz.8eWJ8gVYVr8 https://www.google.com/search?newwindow=1&q=Mitsubishi+electric+thermostat+(digital)+suppliers+-%22pdf%22+-%22amazon%22+-%22ebay%22+-%22youtube%22&spell=1&sa=X&ved=0ahUKEwisuLXIrMrhAhW1_XMBHW4ACTYQBQgoKAA&biw=1745&bih=852 https://www.google.com/search?newwindow=1&ei=XGiwXNL-GdKYmgefxIL4DQ&q=Omron+electronic+thermostat+%28digital%29+suppliers+-%22pdf%22+-%22amazon%22+-%22ebay%22+-%22youtube%22&oq=Omron+electronic+thermostat+%28digital%29+suppliers+-%22pdf%22+-%22amazon%22+-%22ebay%22+-%22youtube%22&gs_l=psy-ab.3...91378.91646..92265...0.0..0.119.227.0j2......0....1j2..gws-wiz.......0i71j35i39j0i67j0.9uLanjzCZEk https://www.google.com/search?newwindow=1&biw=1745&bih=852&ei=UWiwXK2GD97dz7sP6sO4WA&q=honeywell+electronic+thermostat+%28digital%29+suppliers+-%22pdf%22+-%22amazon%22+-%22ebay%22+-%22youtube%22&oq=honeywell+electronic+thermostat+%28digital%29+suppliers+-%22pdf%22+-%22amazon%22+-%22ebay%22+-%22youtube%22&gs_l=psy-ab.3...117907.117907..118424...0.0..0.101.101.0j1......0....2j1..gws-wiz.......0i71.nzdI7vi4vaU https://www.google.com/search?newwindow=1&biw=1745&bih=852&ei=-GewXIyJOOXbz7sPtPSLgAU&q=Autonics+electronic+thermostat+%28digital%29+suppliers+-%22pdf%22+-%22amazon%22+-%22ebay%22+-%22youtube%22&oq=Autonics+electronic+thermostat+%28digital%29+suppliers+-%22pdf%22+-%22amazon%22+-%22ebay%22+-%22youtube%22&gs_l=psy-ab.3...220907.220907..221928...0.0..0.110.110.0j1......0....2j1..gws-wiz.......0i71.KpyBRO8A3Nc https://www.google.com/search?newwindow=1&biw=1745&bih=852&ei=7WewXJ_gINLDz7sPqcimuAM&q=Novus+electronic+thermostat+%28digital%29+suppliers+-%22pdf%22+-%22amazon%22+-%22ebay%22+-%22youtube%22&oq=Novus+electronic+thermostat+%28digital%29+suppliers+-%22pdf%22+-%22amazon%22+-%22ebay%22+-%22youtube%22&gs_l=psy-ab.3...244824.244824..245686...0.0..0.101.101.0j1......0....2j1..gws-wiz.......0i71.5-Glelb1NJI | AA18: 4KCJ3Y57B12I0QH | AB18: =LEFT(AA18,6) -> 4KCJ3Y | AC18: =LEFT(AB18,3) -> 4KC | AD18: =RIGHT(AB18,3) -> J3Y | AE18: =RIGHT(AA18,7) -> B12I0QH | AF18: =LEFT(AE18,4) -> B12I | AG18: =RIGHT(AE18,3) -> 0QH | AH18: =_xludf.CONCAT(AC18,_xludf.CONCAT("-",AD18)) -> #NAME? | AI18: =_xludf.CONCAT(AF18,_xludf.CONCAT("-",AG18)) -> #NAME?
A19: =_xludf.CONCAT(AH19,_xludf.CONCAT("-",AI19)) -> #NAME? | B19: Quotation Sent | D19: A. Anwar Khan | F19: Motor Cooling Fan (35Watts) Cooling Fan (Ac Axial Fan) Power: 35 watts, Volts: 220-240v 50/60Hz,Amps: 0.29A, Model: FP-108EX-SI-B,Impendance Protected, Size:172x150x51mm, Make: T&B OR EQUIVALENT | G19: Muhammad Baqar Ali Cell #:+923008690335 Email:mbali@engro.com | H19: Hasan: Quotation sent on 16-04-19 Hasan: Quotation validity reminder sent on 23-04-19 | I19: 43566 | J19: =IF(X19="","LINKS REQUIRED",IF(X19="Completed","LINKS HARVESTED","LINKS AVAILABLE")) -> LINKS HARVESTED | M19: Maaz | W19: Motor Cooling Fan (T&B) | X19: Completed | Y19: https://www.google.com/search?q=FP-108EX-SI-B&newwindow=1&source=lnms&sa=X&ved=0ahUKEwifmfbz98fhAhVHgrwKHWwfCvgQ_AUICSgA&biw=1745&bih=852&dpr=1.1 https://www.google.com/search?newwindow=1&biw=1745&bih=852&ei=DSWvXPnuFsiBvwSVpIPgCw&q=T%26B++FP-108EX-SI-B&oq=T%26B++FP-108EX-SI-B&gs_l=psy-ab.3...42068.42345..43201...0.0..0.112.224.0j2......0....2j1..gws-wiz.......0i71.bOZCgjCeNS4 | AA19: 4KXIEAJRBIHZ93A | AB19: =LEFT(AA19,6) -> 4KXIEA | AC19: =LEFT(AB19,3) -> 4KX | AD19: =RIGHT(AB19,3) -> IEA | AE19: =RIGHT(AA19,7) -> BIHZ93A | AF19: =LEFT(AE19,4) -> BIHZ | AG19: =RIGHT(AE19,3) -> 93A | AH19: =_xludf.CONCAT(AC19,_xludf.CONCAT("-",AD19)) -> #NAME? | AI19: =_xludf.CONCAT(AF19,_xludf.CONCAT("-",AG19)) -> #NAME?
A20: =_xludf.CONCAT(AH20,_xludf.CONCAT("-",AI20)) -> #NAME? | B20: Request for further information sent to customer | D20: Qamar uddin | F20: Vacuum pump with filtration assembly | G20: saeed.ahmed@BarrettHodgson.com | I20: 43566 | J20: =IF(X20="","LINKS REQUIRED",IF(X20="Completed","LINKS HARVESTED","LINKS AVAILABLE")) -> LINKS REQUIRED | AA20: 4L3UYZLX7DMHV11 | AB20: =LEFT(AA20,6) -> 4L3UYZ | AC20: =LEFT(AB20,3) -> 4L3 | AD20: =RIGHT(AB20,3) -> UYZ | AE20: =RIGHT(AA20,7) -> 7DMHV11 | AF20: =LEFT(AE20,4) -> 7DMH | AG20: =RIGHT(AE20,3) -> V11 | AH20: =_xludf.CONCAT(AC20,_xludf.CONCAT("-",AD20)) -> #NAME? | AI20: =_xludf.CONCAT(AF20,_xludf.CONCAT("-",AG20)) -> #NAME?
A21: =_xludf.CONCAT(AH21,_xludf.CONCAT("-",AI21)) -> #NAME? | B21: Inquiry letter sent | D21: A. Anwar Khan | F21: HERION Solenoid valve PIC AS ATTACHED QTY : 03 | G21: Muhammad Asjad 0300 8295079 Business Links Int’l (Pvt) Ltd. 2nd Floor, Twin Star Chambers, Mumtaz Hasan Road, Karachi - 74000. P A K I S T A N . Tel: 32417280 - 32419227 asjad@businesslinks-pk.com | H21: Arsaln: further details needed for valve Hasan: quote poppet valve with it | I21: 43566 | J21: =IF(X21="","LINKS REQUIRED",IF(X21="Completed","LINKS HARVESTED","LINKS AVAILABLE")) -> LINKS HARVESTED | M21: Maaz | O21: Saad | W21: HERION Solenoid valve | X21: Completed | Y21: https://www.imi-precision.com/de/de/uber/kontakt https://www.imi-precision.com/de/de/uber/kontakt/deutschland https://www.google.com/search?newwindow=1&biw=1745&bih=852&ei=Iw-vXIiQHIjtvgTQ_6WwCA&q=herion+0246+germany&oq=herion+0246+germany&gs_l=psy-ab.3...1515.5505..5866...0.0..0.146.1025.0j8......0....1..gws-wiz.......0i22i30.lvZ-HwWhpcY https://www.google.com/search?newwindow=1&biw=1745&bih=852&ei=Kg-vXITbFJumwgPpo65o&q=herion+0246+germany+suppliers&oq=herion+0246+germany+suppliers&gs_l=psy-ab.3...23575.26870..27847...0.0..0.148.1355.0j10......0....1..gws-wiz.......0i71j33i21.LX0rvF8Snuw https://www.google.com/search?newwindow=1&biw=1745&bih=852&ei=ORCvXOnqOYrovgTQ-omYCg&q=herion+0246+germany+europe+suppliers&oq=herion+0246+germany+europe+suppliers&gs_l=psy-ab.3...28736.33814..34311...1.0..0.121.950.0j8......0....1..gws-wiz.......35i39.NDsA4SD03PI | AA21: 4P84MNZ59QYGXK3 | AB21: =LEFT(AA21,6) -> 4P84MN | AC21: =LEFT(AB21,3) -> 4P8 | AD21: =RIGHT(AB21,3) -> 4MN | AE21: =RIGHT(AA21,7) -> 9QYGXK3 | AF21: =LEFT(AE21,4) -> 9QYG | AG21: =RIGHT(AE21,3) -> XK3 | AH21: =_xludf.CONCAT(AC21,_xludf.CONCAT("-",AD21)) -> #NAME? | AI21: =_xludf.CONCAT(AF21,_xludf.CONCAT("-",AG21)) -> #NAME?
A22: =_xludf.CONCAT(AH22,_xludf.CONCAT("-",AI22)) -> #NAME? | B22: Inquiry letter sent | D22: A. Anwar Khan | F22: QC Lab Chairs and accessories requirement. All details and pictures in Email Office Chair High Bar Chair Dead line 25th april | G22: Muhammad Ali Khan Manager Facilities Getz Pharma (Pvt) Limited 29-30/27, Korangi Industrial Area, Karachi 74900, Pakistan. UAN +9221-111-111-511 Direct +9221-38636559 Ext. 2485 muhammadali@getzpharma.com | I22: 43570 | J22: =IF(X22="","LINKS REQUIRED",IF(X22="Completed","LINKS HARVESTED","LINKS AVAILABLE")) -> LINKS HARVESTED | M22: Maaz | O22: Saad | W22: QC Lab Chairs and accessories CHAIR | X22: Completed | Y22: https://www.google.com/search?newwindow=1&ei=L4C1XNjXGYiSvQSzyLqoCQ&q=office+chair+germany+manufacturer&oq=office+chair+germany+manufacturer&gs_l=psy-ab.3..0i8i30.206628.207674..208059...0.0..0.147.1027.0j8......0....1..gws-wiz.......0i71j35i304i39j0i13j0i8i7i30j0i8i13i30.x-FDtkNKJqw https://www.google.com/search?newwindow=1&ei=AIG1XP23Noz1vgSP1YroAQ&q=office+chair+europe++manufacturer&oq=office+chair+europe++manufacturer&gs_l=psy-ab.3..0i8i30.33587.34658..35010...0.0..0.126.818.0j7......0....1..gws-wiz.......0i13j0i8i7i30.bznC2Oae0VE https://www.google.com/search?newwindow=1&ei=JYG1XKX-BoT4vgTVoISIBg&q=High+Bar+Chair+europe++manufacturer&oq=High+Bar+Chair+europe++manufacturer&gs_l=psy-ab.3...19649.19649..20525...0.0..0.118.118.0j1......0....2j1..gws-wiz.......0i71.rWAELsA6bvg https://www.google.com/search?newwindow=1&ei=OoG1XIbgKozgvgS25J7wCQ&q=High+Bar+Chair+Germany++manufacturer&oq=High+Bar+Chair+Germany++manufacturer&gs_l=psy-ab.3...8485.10157..10485...0.0..0.132.1100.0j9......0....1..gws-wiz.......0i71._tud15ETwCQ | AA22: 4Q5Q449ABIMYDO9 | AB22: =LEFT(AA22,6) -> 4Q5Q44 | AC22: =LEFT(AB22,3) -> 4Q5 | AD22: =RIGHT(AB22,3) -> Q44 | AE22: =RIGHT(AA22,7) -> BIMYDO9 | AF22: =LEFT(AE22,4) -> BIMY | AG22: =RIGHT(AE22,3) -> DO9 | AH22: =_xludf.CONCAT(AC22,_xludf.CONCAT("-",AD22)) -> #NAME? | AI22: =_xludf.CONCAT(AF22,_xludf.CONCAT("-",AG22)) -> #NAME?
A23: =_xludf.CONCAT(AH23,_xludf.CONCAT("-",AI23)) -> #NAME? | B23: Inquiry letter sent | D23: A. Anwar Khan | F23: QC Lab Chairs and accessories requirement. All details and pictures in Email Lab High Height Stool Lab High Height Stainless Steel Stool Dead line 25th april | G23: Muhammad Ali Khan Manager Facilities Getz Pharma (Pvt) Limited 29-30/27, Korangi Industrial Area, Karachi 74900, Pakistan. UAN +9221-111-111-511 Direct +9221-38636559 Ext. 2485 muhammadali@getzpharma.com | I23: 43570 | J23: =IF(X23="","LINKS REQUIRED",IF(X23="Completed","LINKS HARVESTED","LINKS AVAILABLE")) -> LINKS HARVESTED | M23: Maaz | O23: Saad | W23: QC Lab Chairs and accessories STOOL | X23: Completed | Y23: https://www.google.com/search?newwindow=1&ei=RoG1XN3HEMvkvAS9oqmwBA&q=Lab+High+Height+Stool++Germany++manufacturer&oq=Lab+High+Height+Stool++Germany++manufacturer&gs_l=psy-ab.3...21771.21771..22408...0.0..0.125.125.0j1......0....2j1..gws-wiz.......0i71.-N_TQXLQ7Xs https://www.google.com/search?newwindow=1&ei=XYG1XMPfMsLZvgSDmJC4BQ&q=Lab+High+Height+Stool++europe+manufacturer&oq=Lab+High+Height+Stool++europe+manufacturer&gs_l=psy-ab.3...19106.20136..20258...0.0..0.132.731.0j6......0....1..gws-wiz.......0i71.vU7R0WyyacM https://www.google.com/search?newwindow=1&ei=pYG1XOLrNInfvAS2_riQCg&q=Lab+High+Height+Stainless+Steel+Stool+europe+manufacturer+-%22alibaba%22+-%22amazon%22&oq=Lab+High+Height+Stainless+Steel+Stool+europe+manufacturer+-%22alibaba%22+-%22amazon%22&gs_l=psy-ab.3...12541.15627..15924...0.0..0.115.1069.0j10......0....1..gws-wiz.rxPG30p3ciE https://www.google.com/search?newwindow=1&ei=toG1XPX9LsqDvQSTwo7oCA&q=Lab+High+Height+Stainless+Steel+Stool+Germany+manufacturer+-%22alibaba%22+-%22amazon%22&oq=Lab+High+Height+Stainless+Steel+Stool+Germany+manufacturer+-%22alibaba%22+-%22amazon%22&gs_l=psy-ab.3...43909.44725..44877...0.0..0.115.746.0j7......0....1..gws-wiz.68-wl-Lvf1E | AA23: 4RYCZE6TW1X8BVQ | AB23: =LEFT(AA23,6) -> 4RYCZE | AC23: =LEFT(AB23,3) -> 4RY | AD23: =RIGHT(AB23,3) -> CZE | AE23: =RIGHT(AA23,7) -> W1X8BVQ | AF23: =LEFT(AE23,4) -> W1X8 | AG23: =RIGHT(AE23,3) -> BVQ | AH23: =_xludf.CONCAT(AC23,_xludf.CONCAT("-",AD23)) -> #NAME? | AI23: =_xludf.CONCAT(AF23,_xludf.CONCAT("-",AG23)) -> #NAME?
A24: =_xludf.CONCAT(AH24,_xludf.CONCAT("-",AI24)) -> #NAME? | B24: Quotation Sent | C24: Revised quotation sent | D24: A. Anwar Khan | F24: We are looking for good quality Label Printers and Scanner devices for our project of SAP System implementation of Warehouse Management module Zebra ZT600 Series Industrial Printer Model: ZT620 Make: Zebra | G24: Abdul Sattar Controller IS AGP Limited B-23, S.I.T.E.,Karachi - 75700, Pakistan Tel #: +9221 111 247 247 Ext. 379 URL: www.agp.com.pk | H24: Price in Pakistan http://www.barcode.com.pk/en/rfid-printer-pakistan/181-zebra-zt620-rfid-industrial-printer.html Hasan: Quotation sent on 18-04-19 Hasan: Quotation validity reminder sent on 07-05-19 Maaz : database is ready Model no. ZT420 as per anwar sahab order | I24: 43571 | J24: =IF(X24="","LINKS REQUIRED",IF(X24="Completed","LINKS HARVESTED","LINKS AVAILABLE")) -> LINKS HARVESTED | M24: Maaz | O24: Saad | W24: ZT600 Series Industrial Printer (Zebra) Updated Model: ZT420 | X24: Completed | Y24: ZT600 https://www.google.com/search?newwindow=1&ei=nr22XL_MLcX6z7sP0P606As&q=Zebra+ZT620&oq=Zebra+ZT620&gs_l=psy-ab.3..0i7i30j0l9.3118.3998..4167...0.0..0.217.865.0j5j1......0....1..gws-wiz.......0i71j35i304i39.GzZ1fZm6e5w https://www.google.com/search?newwindow=1&ei=o722XMXJNcDjz7sPoa29-Aw&q=Zebra+ZT620+Suppliers&oq=Zebra+ZT620+Suppliers&gs_l=psy-ab.3..33i160.20379.22378..22460...0.0..0.158.1198.0j9......0....1..gws-wiz.......0i71j0j0i67j0i22i30j0i22i10i30.ugibiOfBoiM https://www.google.com/search?newwindow=1&ei=_L22XKC6KvPYz7sP0cOJ2AY&q=Zebra+ZT620+distributors+-%22pk%22&oq=Zebra+ZT620+distributors+-%22pk%22&gs_l=psy-ab.3...4687.4687..4974...0.0..0.106.106.0j1......0....1..gws-wiz._Q_mLE1VKUI ZT420 https://www.google.com/search?newwindow=1&ei=hJ3BXKqwDMWDvQSHgYWIBA&q=ZT420+-%22amazon%22+-%22ebay%22&oq=ZT420+-%22amazon%22+-%22ebay%22&gs_l=psy-ab.3...11011.14026..14947...0.0..0.269.1599.2-6......0....1j2..gws-wiz.......0i71.DqYjRvd_5J0 | AA24: 4TFLK2D44MNGQE4 | AB24: =LEFT(AA24,6) -> 4TFLK2 | AC24: =LEFT(AB24,3) -> 4TF | AD24: =RIGHT(AB24,3) -> LK2 | AE24: =RIGHT(AA24,7) -> 4MNGQE4 | AF24: =LEFT(AE24,4) -> 4MNG | AG24: =RIGHT(AE24,3) -> QE4 | AH24: =_xludf.CONCAT(AC24,_xludf.CONCAT("-",AD24)) -> #NAME? | AI24: =_xludf.CONCAT(AF24,_xludf.CONCAT("-",AG24)) -> #NAME?
A25: =_xludf.CONCAT(AH25,_xludf.CONCAT("-",AI25)) -> #NAME? | B25: Request for further information sent to customer | D25: A. Anwar Khan | F25: Datalogic / Motorolla long range scanner with industrial browser installed | G25: Abdul Sattar Controller IS AGP Limited B-23, S.I.T.E.,Karachi - 75700, Pakistan Tel #: +9221 111 247 247 Ext. 379 URL: www.agp.com.pk | H25: Model Confirmation sent | I25: 43571 | J25: =IF(X25="","LINKS REQUIRED",IF(X25="Completed","LINKS HARVESTED","LINKS AVAILABLE")) -> LINKS REQUIRED | AA25: 4XCGXQ9KWZIRKXD | AB25: =LEFT(AA25,6) -> 4XCGXQ | AC25: =LEFT(AB25,3) -> 4XC | AD25: =RIGHT(AB25,3) -> GXQ | AE25: =RIGHT(AA25,7) -> WZIRKXD | AF25: =LEFT(AE25,4) -> WZIR | AG25: =RIGHT(AE25,3) -> KXD | AH25: =_xludf.CONCAT(AC25,_xludf.CONCAT("-",AD25)) -> #NAME? | AI25: =_xludf.CONCAT(AF25,_xludf.CONCAT("-",AG25)) -> #NAME?
A26: =_xludf.CONCAT(AH26,_xludf.CONCAT("-",AI26)) -> #NAME? | B26: Closed | D26: A. Anwar Khan | F26: Body Fat Analyzer Machine for budget 2019 working | G26: Hina Kousar -ACMA Sr. Purchase Officer Liaquat National Hospital Ph# 92-21-34412419 Email: h.kousar@lnh.edu.pk | I26: 43572 | J26: =IF(X26="","LINKS REQUIRED",IF(X26="Completed","LINKS HARVESTED","LINKS AVAILABLE")) -> LINKS HARVESTED | M26: Maaz | O26: Saad | W26: Body Fat Analyzer Machine | X26: Completed | Y26: https://www.google.com/search?newwindow=1&ei=98K2XNWsAvfEz7sPoeWk8Ao&q=Body+Fat+Analyzer+Machine&oq=Body+Fat+Analyzer+Machine&gs_l=psy-ab.3..0i7i30j0i67j0j0i30j0i8i30.1860.2234..2755...0.0..0.122.238.0j2......0....1..gws-wiz.......0i71.O7m_66R2qkQ https://www.google.com/search?newwindow=1&ei=2NG2XNGXEI2S9QP596i4Bg&q=Body+Fat+Analyzer+Machine+manufacturers+-%22%25india%25%22+-%22alibaba%22&oq=Body+Fat+Analyzer+Machine+manufacturers+-%22%25india%25%22+-%22alibaba%22&gs_l=psy-ab.3..35i302i39.5460.16979..17098...0.0..0.142.2574.2j24......0....1..gws-wiz.......0i71.5j7LOuOpUvk | AA26: 4YXI6JJTYIZ26GK | AB26: =LEFT(AA26,6) -> 4YXI6J | AC26: =LEFT(AB26,3) -> 4YX | AD26: =RIGHT(AB26,3) -> I6J | AE26: =RIGHT(AA26,7) -> YIZ26GK | AF26: =LEFT(AE26,4) -> YIZ2 | AG26: =RIGHT(AE26,3) -> 6GK | AH26: =_xludf.CONCAT(AC26,_xludf.CONCAT("-",AD26)) -> #NAME? | AI26: =_xludf.CONCAT(AF26,_xludf.CONCAT("-",AG26)) -> #NAME?
A27: =_xludf.CONCAT(AH27,_xludf.CONCAT("-",AI27)) -> #NAME? | B27: Inquiry letter sent | D27: A. Anwar Khan | F27: For our upcoming pipping project at Chevron Pakistan 4" carbon steel A-106 Gr.B Sch # 40 approx. length 100 m 2" carbon steel A-106 Gr.B Sch # 40 approx. length 250 m 3/4" carbon steel pipe A-106 Gr. B Sch #40 lengths of approx. 80 m Elbows, Tee's, sockets, reducers approx. 20 pcs each of same specs. | G27: pictechnologyengineeringworks@gmail.com | H27: again database fly in new letter | I27: 43572 | J27: =IF(X27="","LINKS REQUIRED",IF(X27="Completed","LINKS HARVESTED","LINKS AVAILABLE")) -> LINKS HARVESTED | M27: Maaz | O27: Saad | W27: carbon steel pipe | X27: Completed | Y27: https://www.google.com/search?newwindow=1&biw=1745&bih=852&ei=Wgy3XPqUD9K4kwXV94PIDA&q=carbon+steel+A106+Gr.B+Sch+%23+40&oq=carbon+steel+A106+Gr.B+Sch+%23+40&gs_l=psy-ab.3...1225.1757..2176...0.0..0.211.211.2-1......0....1..gws-wiz.......0i71.WAJpMPCg2os https://www.google.com/search?newwindow=1&biw=1745&bih=852&ei=YAy3XKKuBIjjkgWr0ZWoAw&q=carbon+steel+A106+Gr.B+Sch+%23+40+MANUFACTURERS&oq=carbon+steel+A106+Gr.B+Sch+%23+40+MANUFACTURERS&gs_l=psy-ab.3..33i160.18848.21480..21616...0.0..0.569.4209.0j1j5j4j2j1......0....1..gws-wiz.......0i71j33i22i29i30j33i21.1krIn-nJ2CQ https://www.google.com/search?newwindow=1&biw=1745&bih=852&ei=hQy3XLW5DIT9kwXw_46IDA&q=carbon+steel+A106+Gr.B+Sch+%23+40+SUPPLIERS+-%22INDIA%22&oq=carbon+steel+A106+Gr.B+Sch+%23+40+SUPPLIERS+-%22INDIA%22&gs_l=psy-ab.3...3870.6580..6748...0.0..0.375.1991.0j2j4j2......0....1..gws-wiz.......0i71j35i302i39._HrW7EgbLaM https://www.google.com/search?newwindow=1&biw=1745&bih=852&ei=jQy3XNiVKcLUsAeMkYEY&q=carbon+steel+A106+Gr.B+Sch+%23+40+CHINA+SUPPLIERS+-%22INDIA%22&oq=carbon+steel+A106+Gr.B+Sch+%23+40+CHINA+SUPPLIERS+-%22INDIA%22&gs_l=psy-ab.3...10741.11588..11739...0.0..0.221.889.0j4j1......0....1..gws-wiz.......0i71.h9090kxfyfE | AA27: 4ZAHUZKX641VF0Y | AB27: =LEFT(AA27,6) -> 4ZAHUZ | AC27: =LEFT(AB27,3) -> 4ZA | AD27: =RIGHT(AB27,3) -> HUZ | AE27: =RIGHT(AA27,7) -> 641VF0Y | AF27: =LEFT(AE27,4) -> 641V | AG27: =RIGHT(AE27,3) -> F0Y | AH27: =_xludf.CONCAT(AC27,_xludf.CONCAT("-",AD27)) -> #NAME? | AI27: =_xludf.CONCAT(AF27,_xludf.CONCAT("-",AG27)) -> #NAME?
A28: Waqas Qureshi <wqureshi@otsuka.pk> | B28: Quotation Sent | D28: A. Anwar Khan | F28: GRATE COOLER HYDRAULIC CYLINDER 1. Cylinder should be including bearings and pins in assembled form. 2. Bearing Eye should be integral part of piston rod. 3. Piston should have lock nut on rod. 4. Hydraulic fitting should be attached with cylinder as shown in attached drawing. 5. Hydraulic cylinder should be tested on designed pressure. 6. Origin : Germany | G28: STAR IMPEX INTERNATIONAL Suite # 5, 3rd Floor Imtiaz Centre, Gulberg II, Main Market, Lahore, 54660, Pakistan Mohammad Abdullah | Manager Commercial Tel: +92-42-35712969 Email: abdullah@starimpex.com RFQ7483 | H28: Hasan: Quotation sent on 21-04-19 Hasan: Quotation validity reminder sent on 28-05-19 | I28: 43573 | J28: =IF(X28="","LINKS REQUIRED",IF(X28="Completed","LINKS HARVESTED","LINKS AVAILABLE")) -> LINKS HARVESTED | M28: Maaz | O28: Saad | W28: GRATE COOLER HYDRAULIC CYLINDER | X28: Completed | Y28: https://www.google.com/search?q=GRATE+COOLER+HYDRAULIC+CYLINDER&oq=GRATE+COOLER+HYDRAULIC+CYLINDER&aqs=chrome..69i57.740j0j7&sourceid=chrome&ie=UTF-8 https://www.google.com/search?newwindow=1&ei=Jim4XK3-B4KHyAOI-rbIDA&q=GRATE+COOLER+HYDRAULIC+CYLINDER+manufacturers&oq=GRATE+COOLER+HYDRAULIC+CYLINDER+manufacturers&gs_l=psy-ab.3...17602.20056..20392...0.0..0.219.2036.0j13j1......0....1..gws-wiz.......35i39j33i21j33i160.eSekJRgzR6g https://www.google.com/search?newwindow=1&ei=Oym4XMTkLZX9rQHpo4LAAQ&q=GRATE+COOLER+HYDRAULIC+CYLINDER+Germany+manufacturers&oq=GRATE+COOLER+HYDRAULIC+CYLINDER+Germany+manufacturers&gs_l=psy-ab.3...7060.8012..8084...0.0..0.139.902.0j7......0....1..gws-wiz.......0i71j35i304i39.EG3yFapBShs https://www.google.com/search?newwindow=1&ei=RCm4XN6HL9ev9QO72rPgDA&q=GRATE+COOLER+HYDRAULIC+CYLINDER+Germany&oq=GRATE+COOLER+HYDRAULIC+CYLINDER+Germany&gs_l=psy-ab.3..35i39.9945.10496..10737...0.0..0.136.268.0j2......0....1..gws-wiz.hOwlgEzvZoM | AA28: 5X8X662AIMAJJ60 | AB28: =LEFT(AA28,6) -> 5X8X66 | AC28: =LEFT(AB28,3) -> 5X8 | AD28: =RIGHT(AB28,3) -> X66 | AE28: =RIGHT(AA28,7) -> IMAJJ60 | AF28: =LEFT(AE28,4) -> IMAJ | AG28: =RIGHT(AE28,3) -> J60 | AH28: =_xludf.CONCAT(AC28,_xludf.CONCAT("-",AD28)) -> #NAME? | AI28: =_xludf.CONCAT(AF28,_xludf.CONCAT("-",AG28)) -> #NAME?
A29: =_xludf.CONCAT(AH29,_xludf.CONCAT("-",AI29)) -> #NAME? | B29: Inquiry received by e-mail | D29: Qamar uddin | F29: Solution Mixer Capacity 150 with 3 Nozzle spray guns. Double jacketed Tank with slow mixer 150 liters Material of construction SS 316L. Sheet thickness 14 S.W.G. Outlet cladding sheet material SS 304. Inlet and outlet provision. With slow mixer with VFD. Mirror finish from inside and outside. With four legs Electric heaters provision for solution temperature maintain up to 75 c. 150Peristaltic pump Motor operated with variable speed with (VFD) Spray gun with three nozzles for spray | G29: CCL Pharmaceuticals 65 Quaid-e-Azam Industrial Estate, Kot-Lakhpat, Lahore, - Pakistan Sammer Ismail Awan Assisstant Manager – Procurement e: sammer.awan@cclpharma.com p: +92(42) 111 225 678 | H29: Forwarded to Qamar becuase he have a contact who cna make it | I29: 43573 | J29: =IF(X29="","LINKS REQUIRED",IF(X29="Completed","LINKS HARVESTED","LINKS AVAILABLE")) -> LINKS REQUIRED | AA29: 5XXAPUYX1JSNNXP | AB29: =LEFT(AA29,6) -> 5XXAPU | AC29: =LEFT(AB29,3) -> 5XX | AD29: =RIGHT(AB29,3) -> APU | AE29: =RIGHT(AA29,7) -> 1JSNNXP | AF29: =LEFT(AE29,4) -> 1JSN | AG29: =RIGHT(AE29,3) -> NXP | AH29: =_xludf.CONCAT(AC29,_xludf.CONCAT("-",AD29)) -> #NAME? | AI29: =_xludf.CONCAT(AF29,_xludf.CONCAT("-",AG29)) -> #NAME?
A30: =_xludf.CONCAT(AH30,_xludf.CONCAT("-",AI30)) -> #NAME? | B30: Closed | D30: A. Anwar Khan | F30: wire loop with handle coordinate with Mr. Tauheed on 0320-121-2483 wireloop holders as mentioned in below picture. These are having nichrome loop of 10uL volume with aluminum insulated handle. These are reusable and rapidly cooling due to nichrome. Autoclave-able is not required. | G30: Nabeel Ahmed Assistant Manager Procurement Supply Chain Department Getz Pharma (Pvt) Limited 29-30/27, Korangi Industrial Area, Karachi 74900, Pakistan. UAN +9221-111-111-511 Ext. 2304 Direct # +92-213-863-6225 Cell # +92-320-121-2513 Fax: +9221-5057592 Web address: www.getzpharma.com, email: info@getzpharma.com | I30: 43574 | J30: =IF(X30="","LINKS REQUIRED",IF(X30="Completed","LINKS HARVESTED","LINKS AVAILABLE")) -> LINKS HARVESTED | M30: Maaz | O30: Maaz | W30: wire loop with handle | X30: Completed | Y30: https://www.google.com/search?newwindow=1&ei=_Gu5XJyCHuvbz7sPiLqE0AU&q=Inoculating+Loops+and+Needles&oq=Inoculating+Loops+and+Needles&gs_l=psy-ab.3..0i7i30l3j0j0i30j0i8i30.12495093.12497240..12497761...0.0..0.189.307.0j2......0....2j1..gws-wiz.......0i71.L9c0wMV3ACg https://www.google.com/search?newwindow=1&ei=AKe5XNDGIbSEmgfRgZ2wCA&q=Inoculating+Loops+and+Needles+manufacturers&oq=Inoculating+Loops+and+Needles+manufacturers&gs_l=psy-ab.3...26773.29172..29371...0.0..0.181.1899.0j14......0....1..gws-wiz.......0i71j0i22i30j33i22i29i30j33i160j33i21.cSbm3pio794 https://www.google.com/search?newwindow=1&ei=Hqe5XKSbK5DYz7sPpoaMsAk&q=Inoculating+Loops+and+Needles+suppliers&oq=Inoculating+Loops+and+Needles+suppliers&gs_l=psy-ab.3...8213.10707..10859...0.0..0.145.1319.0j10......0....1..gws-wiz.......0i71j35i39j0i22i30j33i22i29i30j33i160j33i21.ORm2p8SMaRg | AA30: 511X68X69PS3C0Z | AB30: =LEFT(AA30,6) -> 511X68 | AC30: =LEFT(AB30,3) -> 511 | AD30: =RIGHT(AB30,3) -> X68 | AE30: =RIGHT(AA30,7) -> 9PS3C0Z | AF30: =LEFT(AE30,4) -> 9PS3 | AG30: =RIGHT(AE30,3) -> C0Z | AH30: =_xludf.CONCAT(AC30,_xludf.CONCAT("-",AD30)) -> #NAME? | AI30: =_xludf.CONCAT(AF30,_xludf.CONCAT("-",AG30)) -> #NAME?
A31: =_xludf.CONCAT(AH31,_xludf.CONCAT("-",AI31)) -> #NAME? | B31: Data is ready | D31: Qamar uddin | F31: inspection system for label inspection further details in email . | G31: Fatronic Automation - Innovating Factory Automation A: 4C 6/2 Nazimabad No. 4 Karachi 74600 P: +92-334-3768-450 E: faizan@fatronicautomation.com W: http://fatronicautomation.com | I31: 43574 | J31: =IF(X31="","LINKS REQUIRED",IF(X31="Completed","LINKS HARVESTED","LINKS AVAILABLE")) -> LINKS HARVESTED | M31: Maaz | W31: inspection system for label inspection | X31: Completed | Y31: https://www.google.com/search?q=inspection+system+for+label+inspection&oq=inspection+system+for+label+inspection&aqs=chrome..69i57j69i60&sourceid=chrome&ie=UTF-8 https://www.google.com/search?newwindow=1&ei=dm-9XP6VCdDhz7sProyOiAw&q=label+inspection+system+machine+manufacturers&oq=label+inspection+system+machine+&gs_l=psy-ab.1.0.33i22i29i30l4.27785.30495..32320...0.0..0.131.381.0j3......0....1..gws-wiz.......0i71j0i7i30j35i39j0i22i30j0i20i263j0.pOnuABhmn18 http://www.vaia-tech.com/contact-us/ https://www.digisystem.com/solutions/SOL00066/ | AA31: 52WQ2GYXT6ZR78G | AB31: =LEFT(AA31,6) -> 52WQ2G | AC31: =LEFT(AB31,3) -> 52W | AD31: =RIGHT(AB31,3) -> Q2G | AE31: =RIGHT(AA31,7) -> T6ZR78G | AF31: =LEFT(AE31,4) -> T6ZR | AG31: =RIGHT(AE31,3) -> 78G | AH31: =_xludf.CONCAT(AC31,_xludf.CONCAT("-",AD31)) -> #NAME? | AI31: =_xludf.CONCAT(AF31,_xludf.CONCAT("-",AG31)) -> #NAME?
A32: =_xludf.CONCAT(AH32,_xludf.CONCAT("-",AI32)) -> #NAME? | B32: Quotation Validity Reminder Sent | D32: A. Anwar Khan | F32: INDUCTION MOTOR 3-PHASE, 7.2KW,400V, TYPE:DHAD 560-4,1380 RPM,13.3A,S1 CLASS, 50HZ,IP55,INS CL. F, ART NR:C90-56004, TEMP. 50C, P.F:0.78, FLANGE MOUNTED SPI # 2190 RFQ # 6311-ELEC | G32: Muhammad Rehan Anwar Procurement Officer Procurement Department– Processing Team quotations1@bestway.com.pk | H32: Hasan: Quotation sent on 03-05-19 Hasan: Quotation validity reminder sent on 10-05-19 | I32: 43574 | J32: =IF(X32="","LINKS REQUIRED",IF(X32="Completed","LINKS HARVESTED","LINKS AVAILABLE")) -> LINKS HARVESTED | M32: Maaz | O32: Maaz | W32: INDUCTION MOTOR 3-PHASE DHAD 560-4 | X32: Completed | Y32: https://www.google.com/search?q=DHAD+560-4&oq=DHAD+560-4&aqs=chrome..69i57&sourceid=chrome&ie=UTF-8 https://www.google.com/search?newwindow=1&ei=6bO5XKu1LOXaz7sP94KPgAc&q=dhad+560-4+motor+suppliers&oq=dhad+560-4+motor+suppliers&gs_l=psy-ab.3...5276.6723..7051...0.0..0.145.797.0j6......0....1..gws-wiz.......35i304i39.ba-jrzjrwe8 | AA32: 54J8UUW5HGDD1ZS | AB32: =LEFT(AA32,6) -> 54J8UU | AC32: =LEFT(AB32,3) -> 54J | AD32: =RIGHT(AB32,3) -> 8UU | AE32: =RIGHT(AA32,7) -> HGDD1ZS | AF32: =LEFT(AE32,4) -> HGDD | AG32: =RIGHT(AE32,3) -> 1ZS | AH32: =_xludf.CONCAT(AC32,_xludf.CONCAT("-",AD32)) -> #NAME? | AI32: =_xludf.CONCAT(AF32,_xludf.CONCAT("-",AG32)) -> #NAME?
A33: =_xludf.CONCAT(AH33,_xludf.CONCAT("-",AI33)) -> #NAME? | B33: Quotation Validity Reminder Sent | D33: A. Anwar Khan | F33: MOTOR INDUCTION, 0.75 KW,1385 RPM, 400V, 3-PHASE, 1.8A, TYPE: Y80M2-4, ,1.5A,400V,DUTY CLASS S1, INS. CL "F" IP54,COS 0.87, FLANGE MOUNTED, SHAFT SIZE: 19MM, LENGTH:40MM, MAKE:SIEMENS/ABB/NORD SPI # 2190 RFQ # 6311-ELEC | G33: Muhammad Rehan Anwar Procurement Officer Procurement Department– Processing Team quotations1@bestway.com.pk | H33: Arsalan: sending Abb and nord suppliers from previous quotations 1- Kevin.Chambers@esrmotors.com/ABB 2- \ronny.wilk@nord.com/NORD Hasan: Quotation sent on 24-04-19 Hasan: Quotation validity reminder sent on 03-05-19 | I33: 43574 | J33: =IF(X33="","LINKS REQUIRED",IF(X33="Completed","LINKS HARVESTED","LINKS AVAILABLE")) -> LINKS HARVESTED | M33: Maaz | W33: MOTOR INDUCTION Y80M2-4 | X33: Completed | Y33: https://www.google.com/search?newwindow=1&ei=A7S5XJ7NL_rfz7sPk9O7-Ac&q=Y80M2-4+-%22ali%22&oq=Y80M2-4+-%22ali%22&gs_l=psy-ab.3...6503.11101..11373...0.0..0.135.775.0j7......0....1..gws-wiz.......0i30j0i22i30.yze2Y1fJs5U https://www.google.com/search?newwindow=1&ei=ELS5XN_ECZWGmgf_17uoDA&q=motor+Y80M2-4+-%22ali%22&oq=motor+Y80M2-4+-%22ali%22&gs_l=psy-ab.3...13646.16662..16997...1.0..0.106.930.0j9......0....1..gws-wiz.5DzRveAnOgM | AA33: 57TCHLUXCG27R3M | AB33: =LEFT(AA33,6) -> 57TCHL | AC33: =LEFT(AB33,3) -> 57T | AD33: =RIGHT(AB33,3) -> CHL | AE33: =RIGHT(AA33,7) -> CG27R3M | AF33: =LEFT(AE33,4) -> CG27 | AG33: =RIGHT(AE33,3) -> R3M | AH33: =_xludf.CONCAT(AC33,_xludf.CONCAT("-",AD33)) -> #NAME? | AI33: =_xludf.CONCAT(AF33,_xludf.CONCAT("-",AG33)) -> #NAME?
A34: =_xludf.CONCAT(AH34,_xludf.CONCAT("-",AI34)) -> #NAME? | B34: Quotation Validity Reminder Sent | C34: second quotatioin sent | D34: Qamar uddin | F34: HPLC Column Techsphere NH2,5um 300mm x 3.9mm Qty 1 HPLC Column 3.9mm x 15cm, 5 Micron (L-11) Qty1 HPLC Column C-18 100-10 4.6mm, 250cm L-1 Packing Qty 10 HPLC Column 250mmx4.6mm 5Micro Lichrospher 100 NH2 (L-8) Qty 1 HPLC- Column 4.6mm x 10cm, 3um (L1) Qty 1 HPLC- Column 4.6mm x 12.5cm, 4um (L1) Qty 1 HPLC Column 4.0mm x125mm (L1) Qty 1 HPLC Column C-18 100-5 150mm x 4.0mm L-1 Packing Qty 1 HPLC Column C-18 100-5 150mm x 4.6mm L-1 Packing Qty 3 HPLC Column C-18 100-5 4.6mm, 250cm L-1 Packing Qty 5 HPLC- Column 25cm x 4.6mm, 5um (L10) Qty 01 HPLC- Column 4.6mm x 50mm (L7) Qty 01 HPLC Column 150 x4.6mm 7 Micro Allsep Anion Qty 01 HPLC- Column 4.6mm x 125mm, 5um (L7) Qty 1 | G34: Regards Saeed Ahmed 03423577585 saeed.ahmed@BarrettHodgson.com RFQ PR# 10000317 (HPLC Columns) | H34: Hasan: Quotation sent on 24-04-19 Hasan: 2nd Quotation sent on 25-04-19 Hasan: Quotation validity reminder sent on 03-05-19 | J34: =IF(X34="","LINKS REQUIRED",IF(X34="Completed","LINKS HARVESTED","LINKS AVAILABLE")) -> LINKS REQUIRED | AA34: 58XAXYLAI3O4D4K | AB34: =LEFT(AA34,6) -> 58XAXY | AC34: =LEFT(AB34,3) -> 58X | AD34: =RIGHT(AB34,3) -> AXY | AE34: =RIGHT(AA34,7) -> I3O4D4K | AF34: =LEFT(AE34,4) -> I3O4 | AG34: =RIGHT(AE34,3) -> D4K | AH34: =_xludf.CONCAT(AC34,_xludf.CONCAT("-",AD34)) -> #NAME? | AI34: =_xludf.CONCAT(AF34,_xludf.CONCAT("-",AG34)) -> #NAME?
A35: =_xludf.CONCAT(AH35,_xludf.CONCAT("-",AI35)) -> #NAME? | B35: Quotation Validity Reminder Sent | D35: Qamar uddin | F35: HPLC- 6-Port Valve Rotor Seal Assy 228-21217-97 EA 2 HPLC- 6-Port Valve Stator Seal Assy 228-21220-94 EA 2 HPLC- 6-Position Valve (L.Pressure) Motor 228-39233 EA 2 HPLC- Drain Valve O-Ring 670-11518 EA 10 HPLC- Male Nut Peek 228-18565-84 EA 5 HPLC- Needle Seal Vespel 228-41540-04 EA 3 HPLC- Plunger Seal 228-35145 EA 3 HPLC- Ring Back Up 22-35934 EA 7 HPLC- Ring Seal 228-35935 EA 7 HPLC- Standard Sample Loop 228-39436-91, SIL-10ADVP EA 2 HPLC- Suction Filter 228-45707-91 EA 15 | G35: Regards Saeed Ahmed 03423577585 saeed.ahmed@BarrettHodgson.com RFQ PR# 10000317 (Parts) | H35: Arsalan: Shimadzu parts sales@sciencix.com Maaz: Enquiry fly on lab equipment merge database as per boss order Hasan: Quotation sent on 30-04-19 Hasan: Quotation validity reminder sent on 07-05-19 | J35: =IF(X35="","LINKS REQUIRED",IF(X35="Completed","LINKS HARVESTED","LINKS AVAILABLE")) -> LINKS HARVESTED | M35: Maaz | W35: shimadzu hplc parts | X35: Completed | Y35: https://www.google.com/search?newwindow=1&ei=bmm9XML_M4T1rQHwiouICw&q=shimadzu+hplc+parts&oq=shimadzu+hplc+parts&gs_l=psy-ab.3..35i39j0i22i30l4.2167822.2172486..2172600...1.0..0.125.1130.0j10......0....1..gws-wiz.......0i71j0j0i20i263j35i304i39j0i13.ZjCf5WLgGjg | AA35: 5892UMSAR7ST4NE | AB35: =LEFT(AA35,6) -> 5892UM | AC35: =LEFT(AB35,3) -> 589 | AD35: =RIGHT(AB35,3) -> 2UM | AE35: =RIGHT(AA35,7) -> R7ST4NE | AF35: =LEFT(AE35,4) -> R7ST | AG35: =RIGHT(AE35,3) -> 4NE | AH35: =_xludf.CONCAT(AC35,_xludf.CONCAT("-",AD35)) -> #NAME? | AI35: =_xludf.CONCAT(AF35,_xludf.CONCAT("-",AG35)) -> #NAME?
A36: =_xludf.CONCAT(AH36,_xludf.CONCAT("-",AI36)) -> #NAME? | B36: Inquiry letter sent | D36: Qamar uddin | F36: Control Standard Endotoxin (CSE) 125ug 1 G Control Standard Endotoxin (CSE)0.5 ug/ 05 EA LAL Reagent Water 100ml 10 BT Pyrotell 0.06 EU/ml 25 EA | G36: Regards Saeed Ahmed 03423577585 saeed.ahmed@BarrettHodgson.com RFQ PR#10000317 | J36: =IF(X36="","LINKS REQUIRED",IF(X36="Completed","LINKS HARVESTED","LINKS AVAILABLE")) -> LINKS HARVESTED | M36: Maaz | O36: Maaz | W36: Control Standard Endotoxin | X36: Completed | Y36: https://www.google.com/search?newwindow=1&ei=c4O9XPTXOcSDmges0Z8g&q=Control+Standard+Endotoxin+%28CSE%29+125ug+suppliers&oq=Control+Standard+Endotoxin+%28CSE%29+125ug+suppliers&gs_l=psy-ab.3...16786.20481..21001...0.0..0.253.1512.0j9j1......0....1..gws-wiz.......0i71j35i302i39j33i21j33i160j33i10i160.5U5FLRZSXo8 https://www.google.com/search?newwindow=1&ei=yIO9XPfhNP_Tz7sPjduYiAc&q=Control+Standard+Endotoxin+%28CSE%290.5+ug+suppliers&oq=Control+Standard+Endotoxin+%28CSE%290.5+ug+suppliers&gs_l=psy-ab.3...54872.57703..58134...0.0..0.171.1440.0j10......0....1..gws-wiz.......0i71j35i302i39j33i21j33i160.OlmYx8wy9T4 https://www.google.com/search?newwindow=1&ei=wIO9XMPqA8zZz7sP4tGCoAI&q=Pyrotell+0.06+EU%2Fml+suppliers&oq=Pyrotell+0.06+EU%2Fml+suppliers&gs_l=psy-ab.3...73202.76072..76506...0.0..0.162.1429.0j10......0....1..gws-wiz.......0i71j33i160.B8ZK6cZQ7hU https://www.google.com/search?newwindow=1&ei=tIO9XMj8H8DYz7sP1e6x4AY&q=LAL+Reagent+Water+100ml+supplliers&oq=LAL+Reagent+Water+100ml+supplliers&gs_l=psy-ab.3..33i160.95233.99470..100439...0.0..0.181.1547.0j11......0....1..gws-wiz.......0i22i30j33i21.8m7QNx-QkiE | AA36: 58J1TMXQLGXU1KE | AB36: =LEFT(AA36,6) -> 58J1TM | AC36: =LEFT(AB36,3) -> 58J | AD36: =RIGHT(AB36,3) -> 1TM | AE36: =RIGHT(AA36,7) -> LGXU1KE | AF36: =LEFT(AE36,4) -> LGXU | AG36: =RIGHT(AE36,3) -> 1KE | AH36: =_xludf.CONCAT(AC36,_xludf.CONCAT("-",AD36)) -> #NAME? | AI36: =_xludf.CONCAT(AF36,_xludf.CONCAT("-",AG36)) -> #NAME?
A37: =_xludf.CONCAT(AH37,_xludf.CONCAT("-",AI37)) -> #NAME? | B37: Inquiry received by e-mail | D37: Qamar uddin | G37: mohammad-zain.a.arsalan-baig@gsk.com | H37: Boss is Worked on it Tube dimensions sent to Maaz for enquiry letter | J37: =IF(X37="","LINKS REQUIRED",IF(X37="Completed","LINKS HARVESTED","LINKS AVAILABLE")) -> LINKS REQUIRED | AA37: 5AT3IURAXRQR61H | AB37: =LEFT(AA37,6) -> 5AT3IU | AC37: =LEFT(AB37,3) -> 5AT | AD37: =RIGHT(AB37,3) -> 3IU | AE37: =RIGHT(AA37,7) -> XRQR61H | AF37: =LEFT(AE37,4) -> XRQR | AG37: =RIGHT(AE37,3) -> 61H | AH37: =_xludf.CONCAT(AC37,_xludf.CONCAT("-",AD37)) -> #NAME? | AI37: =_xludf.CONCAT(AF37,_xludf.CONCAT("-",AG37)) -> #NAME?
A38: =_xludf.CONCAT(AH38,_xludf.CONCAT("-",AI38)) -> #NAME? | B38: Request for further information sent to customer | D38: Qamar uddin | F38: Lab Oil Bath | G38: Regards Saeed Ahmed 03423577585 saeed.ahmed@BarrettHodgson.com RFQ PR#0010004963" | H38: mAAZ: DATA AVAILABLE | J38: =IF(X38="","LINKS REQUIRED",IF(X38="Completed","LINKS HARVESTED","LINKS AVAILABLE")) -> LINKS REQUIRED | AA38: 5EXB43RJKNCVWD6 | AB38: =LEFT(AA38,6) -> 5EXB43 | AC38: =LEFT(AB38,3) -> 5EX | AD38: =RIGHT(AB38,3) -> B43 | AE38: =RIGHT(AA38,7) -> KNCVWD6 | AF38: =LEFT(AE38,4) -> KNCV | AG38: =RIGHT(AE38,3) -> WD6 | AH38: =_xludf.CONCAT(AC38,_xludf.CONCAT("-",AD38)) -> #NAME? | AI38: =_xludf.CONCAT(AF38,_xludf.CONCAT("-",AG38)) -> #NAME?
A39: =_xludf.CONCAT(AH39,_xludf.CONCAT("-",AI39)) -> #NAME? | B39: Quotation Validity Reminder Sent | D39: A. Anwar Khan | F39: HPLC Column, Shodax Asahipak ODP-50, L67 250X4.6, 5um Part Number: F7620003 | G39: Nabeel Ahmed Assistant Manager Procurement Supply Chain Department Getz Pharma (Pvt) Limited 29-30/27, Korangi Industrial Area, Karachi 74900, Pakistan. UAN +9221-111-111-511 Ext. 2304 Direct # +92-213-863-6225 Fax: +9221-5057592 Web address: www.getzpharma.com, email: info@getzpharma.com | H39: Hasan: Quotation sent on 29-04-19 Hasan: Quotation validity reminder sent on 06-05-19 | J39: =IF(X39="","LINKS REQUIRED",IF(X39="Completed","LINKS HARVESTED","LINKS AVAILABLE")) -> LINKS HARVESTED | M39: Maaz | O39: Maaz | W39: HPLC Column (Shodax Asahipak) | X39: Completed | Y39: https://www.google.com/search?q=F7620003&oq=F7620003&aqs=chrome..69i57&sourceid=chrome&ie=UTF-8 https://www.google.com/search?newwindow=1&ei=dOO-XNOpCITgz7sPwqODgAs&q=F7620003+suppliers&oq=F7620003+suppliers&gs_l=psy-ab.3...936486.938036..938149...0.0..0.217.1172.0j8j1......0....1..gws-wiz.......33i10.nvNO4w15ODA | AA39: 5F6AXUCXX7PX6RB | AB39: =LEFT(AA39,6) -> 5F6AXU | AC39: =LEFT(AB39,3) -> 5F6 | AD39: =RIGHT(AB39,3) -> AXU | AE39: =RIGHT(AA39,7) -> X7PX6RB | AF39: =LEFT(AE39,4) -> X7PX | AG39: =RIGHT(AE39,3) -> 6RB | AH39: =_xludf.CONCAT(AC39,_xludf.CONCAT("-",AD39)) -> #NAME? | AI39: =_xludf.CONCAT(AF39,_xludf.CONCAT("-",AG39)) -> #NAME?
A40: =_xludf.CONCAT(AH40,_xludf.CONCAT("-",AI40)) -> #NAME? | B40: Inquiry letter sent | F40: USA California AIR freight forwarders | G40: IPEX ENQUIRY | J40: =IF(X40="","LINKS REQUIRED",IF(X40="Completed","LINKS HARVESTED","LINKS AVAILABLE")) -> LINKS HARVESTED | M40: Maaz | O40: Maaz | W40: USA California AIR freight forwarders | X40: Completed | Y40: https://www.google.com/search?newwindow=1&ei=rue-XO7iOuDUz7sPmImC4Ag&q=california+air+freight+forwarders&oq=california+air+freight+forwarders&gs_l=psy-ab.3...45162.45617..45761...0.0..0.137.495.0j4......0....1..gws-wiz.......0i71j35i304i39j0i8i7i30j0i13i30j0i13i5i30j0i8i13i30.SPMOu-2XCkg https://www.google.com/search?newwindow=1&ei=3ee-XJOVNNL6z7sPqv2_uAM&q=california+cheap+air+freight+forwarders+&oq=california+cheap+air+freight+forwarders+&gs_l=psy-ab.3...25505.32775..33127...0.0..0.195.939.0j7......0....1..gws-wiz.......0i71.9_s5eBeYu4c https://www.google.com/search?newwindow=1&ei=AOi-XOvmArLfz7sPzMCsgAk&q=california+low+cost+air+freight+forwarders&oq=california+low+cost+air+freight+forwarders&gs_l=psy-ab.3...10784.13503..13591...0.0..0.134.1729.0j14......0....1..gws-wiz.......0i71j35i304i39j35i39.XaIrKF2_yt0 https://www.google.com/search?newwindow=1&ei=Dui-XM3nLPbSz7sPveyn-AM&q=california+low+cost+and+best+air+freight+forwarders&oq=california+low+cost+and+best+air+freight+forwarders&gs_l=psy-ab.3...12655.13630..13694...0.0..0.135.1021.0j8......0....1..gws-wiz.......0i71j35i304i39.TQ1rsXC0s6k | AA40: 5HB5A5ALIXO3LOM | AB40: =LEFT(AA40,6) -> 5HB5A5 | AC40: =LEFT(AB40,3) -> 5HB | AD40: =RIGHT(AB40,3) -> 5A5 | AE40: =RIGHT(AA40,7) -> IXO3LOM | AF40: =LEFT(AE40,4) -> IXO3 | AG40: =RIGHT(AE40,3) -> LOM | AH40: =_xludf.CONCAT(AC40,_xludf.CONCAT("-",AD40)) -> #NAME? | AI40: =_xludf.CONCAT(AF40,_xludf.CONCAT("-",AG40)) -> #NAME?
A41: =_xludf.CONCAT(AH41,_xludf.CONCAT("-",AI41)) -> #NAME? | B41: Quotation Validity Reminder Sent | D41: A. Anwar Khan | F41: CONICAL BRAKE MOTOR, TYPE: YEZ160M-4, 13 KW, 380V, 30A, 50HZ, 1400 RPM, B5 MOUNTING, MADE: CHINA | G41: Muhammad Rehan Anwar Procurement Officer Procurement Department– Processing Team quotations1@bestway.com.pk | H41: Hasan: Quotation sent on 07-05-19 Hasan: Quotation validity reminder sent on 14-05-19 | J41: =IF(X41="","LINKS REQUIRED",IF(X41="Completed","LINKS HARVESTED","LINKS AVAILABLE")) -> LINKS HARVESTED | M41: Maaz | O41: Saad | W41: CONICAL BRAKE MOTOR YEZ160M-4 | X41: Completed | Y41: https://www.google.com/search?q=YEZ160M-4&oq=YEZ160M-4&aqs=chrome..69i57&sourceid=chrome&ie=UTF-8 https://www.google.com/search?newwindow=1&ei=U67BXMyWDv7Uz7sPnZW5IA&q=YEZ160M-4+suppliers&oq=YEZ160M-4+suppliers&gs_l=psy-ab.3...336709.340667..341106...0.0..0.309.2979.2-7j3......0....1..gws-wiz.......33i160.PL_oLQytSD4 | AA41: 5IQAX3I7JJZFENK | AB41: =LEFT(AA41,6) -> 5IQAX3 | AC41: =LEFT(AB41,3) -> 5IQ | AD41: =RIGHT(AB41,3) -> AX3 | AE41: =RIGHT(AA41,7) -> JJZFENK | AF41: =LEFT(AE41,4) -> JJZF | AG41: =RIGHT(AE41,3) -> ENK | AH41: =_xludf.CONCAT(AC41,_xludf.CONCAT("-",AD41)) -> #NAME? | AI41: =_xludf.CONCAT(AF41,_xludf.CONCAT("-",AG41)) -> #NAME?
A42: =_xludf.CONCAT(AH42,_xludf.CONCAT("-",AI42)) -> #NAME? | B42: Quotation Validity Reminder Sent | D42: A. Anwar Khan | F42: MOTOR, TYPE: Y2-80M2-4-WS05076, 0.75KW,2.05A, 380V, INCL F, IP54, CODE: EN60034-1 & EN60204-1, PF 0.76,IM B3, MAKE CHINA. | G42: Muhammad Rehan Anwar Procurement Officer Procurement Department– Processing Team quotations1@bestway.com.pk | H42: Hasan: Quotation validity reminder sent on 07-05-19 | J42: =IF(X42="","LINKS REQUIRED",IF(X42="Completed","LINKS HARVESTED","LINKS AVAILABLE")) -> LINKS HARVESTED | M42: Maaz | O42: Saad | W42: MOTOR Y2-80M2-4 | X42: Completed | Y42: https://www.google.com/search?newwindow=1&ei=W67BXPL_MbG88QPQ3aeoDA&q=Y2-80M2-4&oq=Y2-80M2-4&gs_l=psy-ab.3..35i39j0i30.10033.10895..11824...0.0..0.279.830.2-3......0....1..gws-wiz.DfN6aekEexo https://www.google.com/search?newwindow=1&ei=aK7BXLP6K4Lgz7sPvrC8qAw&q=Y2-80M2-4+suppliers&oq=Y2-80M2-4+suppliers&gs_l=psy-ab.3..33i160.338947.341522..341859...0.0..0.326.2388.2-5j3......0....1..gws-wiz.......0i30.EEdZ4g0TRRs | AA42: 5JLT54H2TM8YYJ4 | AB42: =LEFT(AA42,6) -> 5JLT54 | AC42: =LEFT(AB42,3) -> 5JL | AD42: =RIGHT(AB42,3) -> T54 | AE42: =RIGHT(AA42,7) -> TM8YYJ4 | AF42: =LEFT(AE42,4) -> TM8Y | AG42: =RIGHT(AE42,3) -> YJ4 | AH42: =_xludf.CONCAT(AC42,_xludf.CONCAT("-",AD42)) -> #NAME? | AI42: =_xludf.CONCAT(AF42,_xludf.CONCAT("-",AG42)) -> #NAME?
A43: =_xludf.CONCAT(AH43,_xludf.CONCAT("-",AI43)) -> #NAME? | B43: Inquiry letter sent | D43: A. Anwar Khan | F43: Boiler drum water level gauge 01 set (consist of 02 pcs.) Boiler type : Fire tube Max . Capacity : 4 tons / hr. Hydraulic pressure test up to : 19.5 bar Working steam pressure : 10.78 bar Steam temperature at 10.78 bar :180 degree centigrade (Pics attached) | G43: Archroma Pakistan Limited Plot No.LX 10 & 11, | Landhi Industrial Tarding Estate, | Karachi – 75120, Pakistan UAN: +92 (21) 111 330 330 Muhammad Asif (Mr.) Purchase Executive, Email: muhammad.asif@archroma.com CC: muhammed.haroon@archroma.com, bashir.ahmed@archroma.com, abdul.kalam@archroma.com | H43: Arsalan: customer questions send | I43: 43583 | J43: =IF(X43="","LINKS REQUIRED",IF(X43="Completed","LINKS HARVESTED","LINKS AVAILABLE")) -> LINKS HARVESTED | M43: Maaz | O43: Maaz | W43: Boiler drum water level gauge | X43: Completed | Y43: https://www.google.com/search?newwindow=1&biw=1745&bih=852&ei=iZHGXO_sLYngkgX1hZfIBA&q=drum+water+level+gauge+manufacturers+-%22india%22+-%22%25ali%25%22&oq=drum+water+level+gauge+manufacturers+-%22india%22+-%22%25ali%25%22&gs_l=psy-ab.3...6073.12304..12537...0.0..0.258.975.0j4j1......0....1..gws-wiz.1PA5eLhcbu4 https://www.google.com/search?newwindow=1&biw=1745&bih=852&ei=35HGXKyzHe_isAecr6O4BQ&q=Boiler+drum+water+level+gauge+manufacturers+-%22india%22+&oq=Boiler+drum+water+level+gauge+manufacturers+-%22india%22+&gs_l=psy-ab.3...12776.13304..13840...0.0..0.182.363.0j2......0....1..gws-wiz.-qgipJY-w98 | AA43: 5KJXM7YIL6SENSP | AB43: =LEFT(AA43,6) -> 5KJXM7 | AC43: =LEFT(AB43,3) -> 5KJ | AD43: =RIGHT(AB43,3) -> XM7 | AE43: =RIGHT(AA43,7) -> L6SENSP | AF43: =LEFT(AE43,4) -> L6SE | AG43: =RIGHT(AE43,3) -> NSP | AH43: =_xludf.CONCAT(AC43,_xludf.CONCAT("-",AD43)) -> #NAME? | AI43: =_xludf.CONCAT(AF43,_xludf.CONCAT("-",AG43)) -> #NAME?
A44: =_xludf.CONCAT(AH44,_xludf.CONCAT("-",AI44)) -> #NAME? | B44: Inquiry letter sent | D44: A. Anwar Khan | F44: Boiler blow down valve (Flanged) 01 no. Pressure : PN 40 Size : DN50 Make : Klinger (Austria) | G44: Archroma Pakistan Limited Plot No.LX 10 & 11, | Landhi Industrial Tarding Estate, | Karachi – 75120, Pakistan UAN: +92 (21) 111 330 330 Muhammad Asif (Mr.) Purchase Executive, Email: muhammad.asif@archroma.com CC: muhammed.haroon@archroma.com, bashir.ahmed@archroma.com, abdul.kalam@archroma.com | H44: Arsalan: customer questions send | I44: 43583 | J44: =IF(X44="","LINKS REQUIRED",IF(X44="Completed","LINKS HARVESTED","LINKS AVAILABLE")) -> LINKS HARVESTED | M44: Maaz | O44: Maaz | W44: Boiler blow down valve flanged (Klinger) | X44: Completed | Y44: https://www.klinger-international.com/en/klinger-group/locations https://www.klinger-international.com/en/contact https://www.google.com/search?q=Boiler+blow+down+valve+Flanged&newwindow=1&source=lnms&sa=X&ved=0ahUKEwjYiePj3PThAhUBI1AKHfWjDikQ_AUICSgA&biw=1422&bih=978&dpr=0.9 | AA44: 5KRJSTXLF6T65QT | AB44: =LEFT(AA44,6) -> 5KRJST | AC44: =LEFT(AB44,3) -> 5KR | AD44: =RIGHT(AB44,3) -> JST | AE44: =RIGHT(AA44,7) -> F6T65QT | AF44: =LEFT(AE44,4) -> F6T6 | AG44: =RIGHT(AE44,3) -> 5QT | AH44: =_xludf.CONCAT(AC44,_xludf.CONCAT("-",AD44)) -> #NAME? | AI44: =_xludf.CONCAT(AF44,_xludf.CONCAT("-",AG44)) -> #NAME?
A45: =_xludf.CONCAT(AH45,_xludf.CONCAT("-",AI45)) -> #NAME? | B45: Quotation Validity Reminder Sent | C45: second quotatioin sent | D45: A. Anwar Khan | F45: MACHINE NAME: SKINETTA ASK 4507 BUNDLING MACHINE Spares for the Machine 1. PC BOARD VARI SPEED MOTOR P/N.72200017 Qty:2 2. SERVO MOTOR. P/N.72180114 Qty:2 3. MOTOR WITH GEAR P/N.72180004 Qty:2 4. DC MOTOR 0.25 KW P/N. 72180008 Qty:2 | G45: Business Links International Karachi Pakistan Imran ul haq Snr. Sales Manager Cell # +92 300 8244608 Email: imran@businesslinks-pk.com | H45: Hasan: Quotation sent on 03-05-19 Hasan: Quotation validity reminder sent on 10-05-19 Hasan: 2nd Quotation validity reminder sent on 21-05-19 Maaz: database updated and fly(new letters) on 06-may-2019 | I45: 43581 | J45: =IF(X45="","LINKS REQUIRED",IF(X45="Completed","LINKS HARVESTED","LINKS AVAILABLE")) -> LINKS HARVESTED | M45: Maaz | O45: Maaz | W45: BUNDLING MACHINE Spares (SKINETTA) | X45: Completed | Y45: https://www.google.com/search?newwindow=1&biw=1745&bih=852&ei=j4bGXMaVF5LHwAKd26jABw&q=SKINETTA&oq=SKINETTA&gs_l=psy-ab.3..35i39l2j0j0i20i263l2j0i30l3j0i10i30j0i30.4773.5019..5349...0.0..0.275.543.2-2......0....1..gws-wiz.mt-pWW9pyPc https://www.google.com/search?newwindow=1&biw=1745&bih=852&ei=yIbGXInfJsbWwAL5mrkI&q=skinetta+ask+spare+parts+-%22india%22&oq=skinetta+ask+spare+parts+-%22india%22&gs_l=psy-ab.3...16911.23790..24399...1.0..0.318.2747.2-8j2......0....1..gws-wiz.......0i71.41IyN4l5prI https://www.google.com/search?newwindow=1&ei=nJDGXMPBOczQkwXv1r-QBg&q=SKINETTA++MACHINE+spare+parts&oq=SKINETTA++MACHINE+spare+parts&gs_l=psy-ab.3...8954.8954..9318...0.0..0.213.213.2-1......0....1..gws-wiz.......0i71.pEdueLHx8SA https://www.google.com/search?newwindow=1&q=SKINETTA+spare+parts&spell=1&sa=X&ved=0ahUKEwix0bme6vThAhUHyKQKHWRnANgQBQgoKAA&biw=1745&bih=852 ------------------------------------------------------------ https://www.google.com/search?newwindow=1&biw=1422&bih=978&ei=AP7PXN2AM86bsAfgi5ygAQ&q=KGOG+623+G130-10&oq=KGOG+623+G130-10&gs_l=psy-ab.3..35i39.182337.182337..182881...0.0..0.187.187.0j1......0....1..gws-wiz.......0i71.Q1JxzyCAZXI https://www.google.com/search?newwindow=1&biw=1422&bih=978&ei=lQfQXK3XPMedkwX6zqTYCw&q=DFS56M&oq=DFS56M&gs_l=psy-ab.3..35i39l2j0i30j0i5i30.16228.16228..17141...0.0..0.190.190.0j1......0....1..gws-wiz.2jxTyyfgwIA https://www.google.com/search?newwindow=1&biw=1422&bih=978&ei=PwjQXMHBB5CzsAfhp5joBQ&q=DFS56M%2FTF%2FRH1M%2FSM11&oq=DFS56M%2FTF%2FRH1M%2FSM11&gs_l=psy-ab.3..35i39.5099.6316..7354...0.0..0.192.564.0j3......0....1j2..gws-wiz.......0i30.GpuR96Snz0g | AA45: 5L6NXXLWQDOM05Z | AB45: =LEFT(AA45,6) -> 5L6NXX | AC45: =LEFT(AB45,3) -> 5L6 | AD45: =RIGHT(AB45,3) -> NXX | AE45: =RIGHT(AA45,7) -> QDOM05Z | AF45: =LEFT(AE45,4) -> QDOM | AG45: =RIGHT(AE45,3) -> 05Z | AH45: =_xludf.CONCAT(AC45,_xludf.CONCAT("-",AD45)) -> #NAME? | AI45: =_xludf.CONCAT(AF45,_xludf.CONCAT("-",AG45)) -> #NAME?
A46: =_xludf.CONCAT(AH46,_xludf.CONCAT("-",AI46)) -> #NAME? | B46: Quotation Validity Reminder Sent | D46: Qamar uddin | F46: cone type ss 316L seive with food grade certification. Seive lenth 220mm Top dia 65mm Hole 6mm Required quantity 01no | G46: Ashraf Butt Procurement Officer GlaxoSmithKline Consumer Healthcare Pakistan Ltd. 35 - Dockyard Road, west wharf , Karachi Tel: 35274744 (Ext: 4744) | H46: Hasan: Quotation sent on 15-05-19 Rates Given by Mr. Qamar Hasan: Quotation validity reminder sent on 22-05-19 | I46: 43584 | J46: =IF(X46="","LINKS REQUIRED",IF(X46="Completed","LINKS HARVESTED","LINKS AVAILABLE")) -> LINKS REQUIRED | AA46: 5LKBC8GZZYBS0UO | AB46: =LEFT(AA46,6) -> 5LKBC8 | AC46: =LEFT(AB46,3) -> 5LK | AD46: =RIGHT(AB46,3) -> BC8 | AE46: =RIGHT(AA46,7) -> ZYBS0UO | AF46: =LEFT(AE46,4) -> ZYBS | AG46: =RIGHT(AE46,3) -> 0UO | AH46: =_xludf.CONCAT(AC46,_xludf.CONCAT("-",AD46)) -> #NAME? | AI46: =_xludf.CONCAT(AF46,_xludf.CONCAT("-",AG46)) -> #NAME?
A47: =_xludf.CONCAT(AH47,_xludf.CONCAT("-",AI47)) -> #NAME? | B47: Quotation Validity Reminder Sent | C47: Multiple quotation sent | D47: Qamar uddin | F47: Busch vacuum pump spares. Filter cartridge "O2" (For RA 0100 F) 0532 000 002 Qty 02 Exhaust filter d 72 x 250 with silencer insert (For RA 0100 F) 0532 140 157 Qty 04 Oil filter d 76 x 79 (For RA 0100 F) 0531 000 001 Qty 02 Filter cartridge "O2" (For RA 0202 D) 0532 000 004 Qty 02 Exhaust filter single wrapped d 72 x 375 with silencer insert (For RA 0202 D) 0532 140 159 Qty 04 Oil filter W 940/15/N (For RA 0202 D) 0531 000 001 Qty 2 Busch Vacuum Pump VM 100 (1 CAN = 5L) 0831 000 059 qty 04 | G47: Ashraf Butt Procurement Officer GlaxoSmithKline Consumer Healthcare Pakistan Ltd. 35 - Dockyard Road, west wharf , Karachi Tel: 35274744 (Ext: 4744) | H47: Hasan: Quotation sent on 06-05-19 Hasan: Quotation validity reminder sent on 13-05-19 | I47: 43587 | J47: =IF(X47="","LINKS REQUIRED",IF(X47="Completed","LINKS HARVESTED","LINKS AVAILABLE")) -> LINKS HARVESTED | M47: Maaz | O47: Saad | W47: Busch vacuum pump spares (merged file) | X47: Completed | Y47: https://www.google.com/search?newwindow=1&ei=vsXKXMDUK9-f1fAP-aax4Ak&q=BUSCH+filter+0532+000+002&oq=BUSCH+filter+0532+000+002&gs_l=psy-ab.3...145231.145610..146433...0.0..0.246.424.0j1j1......0....2j1..gws-wiz.6Sl_wVqSbjg https://www.google.com/search?newwindow=1&ei=c8bKXInzIM6HmwW2-ZmoBQ&q=BUSCH+filter+0532+140+157&oq=BUSCH+filter+0532+140+157&gs_l=psy-ab.3...9904.10430..11157...0.0..0.195.376.0j2......0....2j1..gws-wiz.r1gV4rVcL9c https://www.google.com/search?newwindow=1&ei=k8bKXPn6IM2XmwW-nYqgBA&q=BUSCH+0531+000+001&oq=BUSCH+0531+000+001&gs_l=psy-ab.3...4453.6130..6458...0.0..0.259.1219.0j4j2......0....1..gws-wiz.A1KJPbLKGTw https://www.google.com/search?newwindow=1&ei=f8bKXMemJPGRmwWYh7GADQ&q=BUSCH+filter+0532+000+004&oq=BUSCH+filter+0532+000+004&gs_l=psy-ab.3...42872.42872..43405...0.0..0.188.188.0j1......0....2j1..gws-wiz.26WPKIE0-Ew https://www.google.com/search?newwindow=1&ei=UsbKXO-YD8yymwXQ9aLwDQ&q=BUSCH+filter+0532+140+159&oq=BUSCH+filter+0532+140+159&gs_l=psy-ab.3...116526.116526..117224...0.0..0.185.185.0j1......0....2j1..gws-wiz.fJCzloa7O-8 https://www.google.com/search?newwindow=1&ei=s83KXNDdL-qKjLsPu--y-A0&q=busch+0831+000+059+-%22pdf%22&oq=busch+0831+000+059+-%22pdf%22&gs_l=psy-ab.3...5832.8456..8495...0.0..0.238.1039.0j2j3......0....1..gws-wiz.......0i71.8_MgCP5DJow | AA47: 5NN5GWHQ3TP53KB | AB47: =LEFT(AA47,6) -> 5NN5GW | AC47: =LEFT(AB47,3) -> 5NN | AD47: =RIGHT(AB47,3) -> 5GW | AE47: =RIGHT(AA47,7) -> 3TP53KB | AF47: =LEFT(AE47,4) -> 3TP5 | AG47: =RIGHT(AE47,3) -> 3KB | AH47: =_xludf.CONCAT(AC47,_xludf.CONCAT("-",AD47)) -> #NAME? | AI47: =_xludf.CONCAT(AF47,_xludf.CONCAT("-",AG47)) -> #NAME?
A48: =_xludf.CONCAT(AH48,_xludf.CONCAT("-",AI48)) -> #NAME? | B48: Inquiry letter sent | D48: Qamar uddin | F48: HPLC Auto sampler Tray (Rack # 2) Model: 10AVP Shimadzu Latest by 06-05-2019 | G48: Saeed Ahmed Jamali saeed.ahmed@BarrettHodgson.com | I48: 43587 | J48: =IF(X48="","LINKS REQUIRED",IF(X48="Completed","LINKS HARVESTED","LINKS AVAILABLE")) -> LINKS HARVESTED | K48: Done | M48: Maaz | O48: Saad | W48: HPLC Auto sampler Tray 10AVP (Shimadzu) | X48: Completed | Y48: https://www.google.com/search?q=10AVP+Shimadzu&oq=10AVP+Shimadzu&aqs=chrome..69i57j0l2.703j0j4&sourceid=chrome&ie=UTF-8 https://www.google.com/search?newwindow=1&ei=e9bKXIbjJ8KLk74P6KOZkAw&q=10AVP+Shimadzu+supplier&oq=10AVP+Shimadzu+supplier&gs_l=psy-ab.3..33i160.63898.65776..66185...0.0..0.256.1969.0j1j8......0....1..gws-wiz.......0i71j0i22i30j33i21.bvVnDRDgkJc | AA48: 5XXRBRGX5UWBL2D | AB48: =LEFT(AA48,6) -> 5XXRBR | AC48: =LEFT(AB48,3) -> 5XX | AD48: =RIGHT(AB48,3) -> RBR | AE48: =RIGHT(AA48,7) -> 5UWBL2D | AF48: =LEFT(AE48,4) -> 5UWB | AG48: =RIGHT(AE48,3) -> L2D | AH48: =_xludf.CONCAT(AC48,_xludf.CONCAT("-",AD48)) -> #NAME? | AI48: =_xludf.CONCAT(AF48,_xludf.CONCAT("-",AG48)) -> #NAME?
A49: =_xludf.CONCAT(AH49,_xludf.CONCAT("-",AI49)) -> #NAME? | B49: Quotation Validity Reminder Sent | D49: Qamar uddin | F49: Stainless Steel 2000 Ltr. Pressure Vessel having 20HP Silverson inside. All contact parts 316L | G49: Elko Organization Pvt Limited Plot No. 27 & 28, Sector 12/B, Noth Karachi Fahad@elko-Organization.com Mr. Mohsin Manager Engineering | I49: 43587 | J49: =IF(X49="","LINKS REQUIRED",IF(X49="Completed","LINKS HARVESTED","LINKS AVAILABLE")) -> LINKS REQUIRED | AA49: 5QNBK1XAQRFW5D5 | AB49: =LEFT(AA49,6) -> 5QNBK1 | AC49: =LEFT(AB49,3) -> 5QN | AD49: =RIGHT(AB49,3) -> BK1 | AE49: =RIGHT(AA49,7) -> QRFW5D5 | AF49: =LEFT(AE49,4) -> QRFW | AG49: =RIGHT(AE49,3) -> 5D5 | AH49: =_xludf.CONCAT(AC49,_xludf.CONCAT("-",AD49)) -> #NAME? | AI49: =_xludf.CONCAT(AF49,_xludf.CONCAT("-",AG49)) -> #NAME?
A50: =_xludf.CONCAT(AH50,_xludf.CONCAT("-",AI50)) -> #NAME? | B50: Quotation Validity Reminder Sent | D50: Qamar uddin | F50: Autocartoner for Liquid Syrup Bottle with speed of 350 bottles per minute. attached in email User Requirement Specification | G50: Mohammad Salman Khan Ghauri Barrett Hodgson Pakistan (Pvt.) Ltd. Phones: 2570651-57 / 2568810-14, ( Ext: 2118 ) Cell: +92 300 2365690 | H50: Hasan: Quotation sent on 14-05-19 Hasan: Quotation validity reminder sent on 21-05-19 | I50: 43587 | J50: =IF(X50="","LINKS REQUIRED",IF(X50="Completed","LINKS HARVESTED","LINKS AVAILABLE")) -> LINKS HARVESTED | K50: Done | M50: Maaz | O50: Saad | W50: Autocartoner for Liquid Syrup Bottle | X50: Completed | Y50: https://www.google.com/search?newwindow=1&q=Auto+Cartoner+for+Liquid+Syrup+Bottle+with+speed+of+350+bottles+per+minute.&spell=1&sa=X&ved=0ahUKEwiyh-Cc2v7hAhVP66QKHc4PCOcQBQgoKAA&biw=1745&bih=852 https://www.google.com/search?newwindow=1&biw=1745&bih=852&ei=39vLXIKRAsOUkgX62L2gDw&q=Auto+Cartoner+manufacturers+for+Liquid+Syrup+Bottle+with+speed+of+350+bottles+per+minute.&oq=Auto+Cartoner+manufacturers+for+Liquid+Syrup+Bottle+with+speed+of+350+bottles+per+minute.&gs_l=psy-ab.3...87077.89876..89995...0.0..0.260.2863.0j2j11......0....1..gws-wiz.kGVg96IazyA | AA50: 5RUXHCSRH3LYQFI | AB50: =LEFT(AA50,6) -> 5RUXHC | AC50: =LEFT(AB50,3) -> 5RU | AD50: =RIGHT(AB50,3) -> XHC | AE50: =RIGHT(AA50,7) -> H3LYQFI | AF50: =LEFT(AE50,4) -> H3LY | AG50: =RIGHT(AE50,3) -> QFI | AH50: =_xludf.CONCAT(AC50,_xludf.CONCAT("-",AD50)) -> #NAME? | AI50: =_xludf.CONCAT(AF50,_xludf.CONCAT("-",AG50)) -> #NAME?
A51: =_xludf.CONCAT(AH51,_xludf.CONCAT("-",AI51)) -> #NAME? | B51: Inquiry letter sent | D51: A. Anwar Khan | F51: CYLINDER PART NO.:9.901.0017.03 WITHOUT THREAD SHAFT. Part No: 641PM1-4 HAVER ROTO-PACKERS TY.8RS-FE 641PM1-4 Qty:12 | G51: Nasir Ali Assistant Manager (Imports) Askari Cement Limited Ph#051-9272434-5 nasir@askaricement.com.pk CP/Comm/18/00551 | H51: Maaz: only 9 emails found Arsalan: Machine number required | I51: 43588 | J51: =IF(X51="","LINKS REQUIRED",IF(X51="Completed","LINKS HARVESTED","LINKS AVAILABLE")) -> LINKS HARVESTED | M51: Maaz | O51: Saad | W51: HAVER ROTO-PACKERS | X51: Completed | Y51: https://www.haverboecker.com/en/contact/contact/ https://www.google.com/search?newwindow=1&ei=QdnLXIv4HYazsAfWzLLQDw&q=9.901.0017.03+-%22ebay%22&oq=9.901.0017.03+-%22ebay%22&gs_l=psy-ab.3...272403.274955..275234...0.0..0.265.1576.0j6j2......0....1..gws-wiz.qxXfwfM8-aA | AA51: 5SF5IX3BCX4ODW4 | AB51: =LEFT(AA51,6) -> 5SF5IX | AC51: =LEFT(AB51,3) -> 5SF | AD51: =RIGHT(AB51,3) -> 5IX | AE51: =RIGHT(AA51,7) -> CX4ODW4 | AF51: =LEFT(AE51,4) -> CX4O | AG51: =RIGHT(AE51,3) -> DW4 | AH51: =_xludf.CONCAT(AC51,_xludf.CONCAT("-",AD51)) -> #NAME? | AI51: =_xludf.CONCAT(AF51,_xludf.CONCAT("-",AG51)) -> #NAME?
A52: =_xludf.CONCAT(AH52,_xludf.CONCAT("-",AI52)) -> #NAME? | B52: Inquiry letter sent | D52: A. Anwar Khan | F52: ACCUMULATOR AND FITTINGS FOR HYDRAULIC THRUST DEVICE HTD-80 WITH ACCESSORIES ITEM # 9317300-PDB ROTARY KILN TYPE FOLAX 4.15 X 64 M FOR HYDRAULIC THRUST DIVICE OF KILN MAKE : FLS / IMPORTED Qty:1 | G52: Nasir Ali Assistant Manager (Imports) Askari Cement Limited Ph#051-9272434-5 nasir@askaricement.com.pk CP/Comm/18/00552 | H52: Maaz: only 16 emails found | I52: 43588 | J52: =IF(X52="","LINKS REQUIRED",IF(X52="Completed","LINKS HARVESTED","LINKS AVAILABLE")) -> LINKS HARVESTED | M52: Maaz | O52: Saad | W52: ACCUMULATOR AND FITTINGS FOR HYDRAULIC THRUST DEVICE (FLS) | X52: Completed | Y52: https://www.google.com/search?q=%22%40flsmidth.com%22+emails&oq=%22%40flsmidth.com%22+emails&aqs=chrome..69i57.5183j1j4&sourceid=chrome&ie=UTF-8 https://www.google.com/search?newwindow=1&ei=S9PLXMClIYSBi-gP4qyZ2A8&q=FLSmidth+HTD-80&oq=FLSmidth+HTD-80&gs_l=psy-ab.3...183812.183812..184658...0.0..0.175.175.0j1......0....2j1..gws-wiz.......0i71.rCCB2qS8QMo https://www.google.com/search?newwindow=1&ei=BdTLXOTVC9LXkwXLxa3ACw&q=FLSmidth+HTD-80+spareparts&oq=FLSmidth+HTD-80+spareparts&gs_l=psy-ab.3..33i21j33i160.20480.22536..22739...0.0..0.261.2362.0j5j6......0....1..gws-wiz.......0i71j35i302i39j33i13i21.xmNTsh7pj60 https://www.flsmidth.com/en-gb/services/spare-parts | AA52: 5UX98Z6LP6GZZQT | AB52: =LEFT(AA52,6) -> 5UX98Z | AC52: =LEFT(AB52,3) -> 5UX | AD52: =RIGHT(AB52,3) -> 98Z | AE52: =RIGHT(AA52,7) -> P6GZZQT | AF52: =LEFT(AE52,4) -> P6GZ | AG52: =RIGHT(AE52,3) -> ZQT | AH52: =_xludf.CONCAT(AC52,_xludf.CONCAT("-",AD52)) -> #NAME? | AI52: =_xludf.CONCAT(AF52,_xludf.CONCAT("-",AG52)) -> #NAME?
A53: =_xludf.CONCAT(AH53,_xludf.CONCAT("-",AI53)) -> #NAME? | B53: Quotation Validity Reminder Sent | C53: Revised quotation sent | D53: A. Anwar Khan | F53: SEALING RINGS OF FELT MARK # 45 X 10 X 15500 LINE # 20 SHEET # 01 MANUFACTURE NO. 5.500485 SPL NO. 9.012069 MILL TYPE: S-46X14 FLS REF # 561-BM1-205 Make: Vickers Qty:4 | G53: Nasir Ali Assistant Manager (Imports) Askari Cement Limited Ph#051-9272434-5 nasir@askaricement.com.pk CP/Comm/18/00553 | H53: Maaz: only 23 emails found Hasan: Quotation sent on 07-05-19 Hasan: Quotation validity reminder sent on 14-05-19 | I53: 43588 | J53: =IF(X53="","LINKS REQUIRED",IF(X53="Completed","LINKS HARVESTED","LINKS AVAILABLE")) -> LINKS HARVESTED | M53: Maaz | O53: Saad | W53: SEALING RINGS OF FELT MARK (Vickers) | X53: Completed | Y53: https://www.google.com/search?newwindow=1&biw=1745&bih=852&ei=W9jLXKOhMND6kwXxqKGICw&q=5.500485&oq=5.500485&gs_l=psy-ab.3..35i39.2277.3757..4022...0.0..0.178.1045.0j6......0....1..gws-wiz.7wiYN_fIjVY https://www.google.com/search?newwindow=1&biw=1745&bih=852&ei=AtnLXP2RJc-hkwXmxq3wDA&q=Vicker+5.500485&oq=Vicker+5.500485&gs_l=psy-ab.3..35i39.4031.4391..4663...0.0..0.184.364.0j2......0....1..gws-wiz.......0i71.XO_kNXb4LVw https://www.google.com/search?q=VICKERS+-+5.500485+MILL+TYPE%3A+S-46+X+14&oq=VICKERS+-+5.500485+MILL+TYPE%3A+S-46+X+14+&aqs=chrome..69i57j69i60.1650j0j4&sourceid=chrome&ie=UTF-8 https://www.google.com/search?newwindow=1&q=Vicker+5.500485+spare+parts&spell=1&sa=X&ved=0ahUKEwjdqdfT1_7hAhUF-6QKHVWtD8cQBQgoKAA&biw=1745&bih=852 | AA53: 5X9FQTQEGX9U42B | AB53: =LEFT(AA53,6) -> 5X9FQT | AC53: =LEFT(AB53,3) -> 5X9 | AD53: =RIGHT(AB53,3) -> FQT | AE53: =RIGHT(AA53,7) -> GX9U42B | AF53: =LEFT(AE53,4) -> GX9U | AG53: =RIGHT(AE53,3) -> 42B | AH53: =_xludf.CONCAT(AC53,_xludf.CONCAT("-",AD53)) -> #NAME? | AI53: =_xludf.CONCAT(AF53,_xludf.CONCAT("-",AG53)) -> #NAME?
A54: =_xludf.CONCAT(AH54,_xludf.CONCAT("-",AI54)) -> #NAME? | B54: Order Arrived | C54: Revised quotation sent | D54: A. Anwar Khan | F54: BRAKE DISC HS ES010-D08-D09 (UHLMANN BLISTER B1240) [Art. # BAU2581540] BAUER Brake Disc HS ES010-D08-D09 Material Number 30404639 durchm.19, KUNSTSTOFF FDW10 T2701 POS.2.1 QTY: 12 Nos | G54: Faisal Waqas Assistant Manager Procurement Getz Pharma (Pvt) Limited | H54: Hasan: Quotation/Revised sent on 07-05-19 | I54: 43588 | J54: =IF(X54="","LINKS REQUIRED",IF(X54="Completed","LINKS HARVESTED","LINKS AVAILABLE")) -> LINKS HARVESTED | K54: Done | M54: Maaz | O54: Saad | W54: BRAKE DISC (Bauer) | X54: Completed | Y54: https://www.google.com/search?q=HS+ES010-D08-D09&oq=HS+ES010-D08-D09&aqs=chrome..69i57.462j0j4&sourceid=chrome&ie=UTF-8 https://www.google.com/search?q=BAU2581540&oq=BAU2581540&aqs=chrome..69i57&sourceid=chrome&ie=UTF-8 https://www.google.com/search?q=Bauer+Geared+Motors&oq=Bauer+Geared+Motors&aqs=chrome..69i57j69i60&sourceid=chrome&ie=UTF-8 https://www.bauergears.com/company/contact-us | AA54: 5XPGR55NXBFFPSS | AB54: =LEFT(AA54,6) -> 5XPGR5 | AC54: =LEFT(AB54,3) -> 5XP | AD54: =RIGHT(AB54,3) -> GR5 | AE54: =RIGHT(AA54,7) -> XBFFPSS | AF54: =LEFT(AE54,4) -> XBFF | AG54: =RIGHT(AE54,3) -> PSS | AH54: =_xludf.CONCAT(AC54,_xludf.CONCAT("-",AD54)) -> #NAME? | AI54: =_xludf.CONCAT(AF54,_xludf.CONCAT("-",AG54)) -> #NAME?
A55: =_xludf.CONCAT(AH55,_xludf.CONCAT("-",AI55)) -> #NAME? | B55: Inquiry received by e-mail | D55: Qamar uddin | F55: Dissolution tester Qty 2 EA Erweka DT-700 , Copley DIS 8000 | G55: Saeed Ahmed Jamali saeed.ahmed@BarrettHodgson.com Barrett Hodgson Pakistan (Pvt.) Ltd. | H55: Arsalan: No need to work i am handling this inquiry Yasir: Erweka info sheet has been sent to Barrett by boss order and hard copy will e given to qamar they dont need new they want repairing | I55: 43588 | J55: =IF(X55="","LINKS REQUIRED",IF(X55="Completed","LINKS HARVESTED","LINKS AVAILABLE")) -> LINKS REQUIRED | AA55: 61CGXBNDT7N7UV9 | AB55: =LEFT(AA55,6) -> 61CGXB | AC55: =LEFT(AB55,3) -> 61C | AD55: =RIGHT(AB55,3) -> GXB | AE55: =RIGHT(AA55,7) -> T7N7UV9 | AF55: =LEFT(AE55,4) -> T7N7 | AG55: =RIGHT(AE55,3) -> UV9 | AH55: =_xludf.CONCAT(AC55,_xludf.CONCAT("-",AD55)) -> #NAME? | AI55: =_xludf.CONCAT(AF55,_xludf.CONCAT("-",AG55)) -> #NAME?
A56: =_xludf.CONCAT(AH56,_xludf.CONCAT("-",AI56)) -> #NAME? | B56: Quotation Validity Reminder Sent | D56: A. Anwar Khan | F56: GEAR PUMP TYPE QT5243-63-25 A Qty:- 02 NOS DELIVERY : 60-20 LIT/MIN PRESSURE : 4.9 MPa - 18.6 MPa MAKE SUMITOMO DRIVE TECHNOLOGY | G56: ARIF MEMON MANAGER PURCHASE POWER CEMENT LIMITED formerly Al-Abbas Cement Industries Limited A Subsidiary of Arif Habib Group Head Office: Arif Habib Center 23, M.T .Khan Road, Karachi - 74000, Pakistan Phone: +92 21 32468231-2, 32468350-1, Fax No. : +92 21 32463209 Email: arif.memon@powercement.pk Website: www.powercement.com.pk SPR # 206-1699 | H56: Hasan: Quotation sent on 06-05-19 Hasan: Quotation validity reminder sent on 13-05-19 | I56: 43588 | J56: =IF(X56="","LINKS REQUIRED",IF(X56="Completed","LINKS HARVESTED","LINKS AVAILABLE")) -> LINKS HARVESTED | K56: Done | M56: Maaz | O56: Maaz | W56: GEAR PUMP (SUMITOMO DRIVE TECHNOLOGY) | X56: Completed | Y56: https://www.google.com/search?q=QT5243-63-25+A&oq=QT5243-63-25+A&aqs=chrome..69i57&sourceid=chrome&ie=UTF-8 https://www.google.com/search?newwindow=1&ei=Xj_MXKr_BoWVsAffh4LwAQ&q=QT5243-63-25+A+suppliers&oq=QT5243-63-25+A+suppliers&gs_l=psy-ab.3...2312.4023..4471...0.0..0.221.1059.2-5......0....1..gws-wiz.......33i10.QRZ07HCb-Vg https://www.google.com/search?q=Sumitomo+QT5243-63-25A&oq=Sumitomo+QT5243-63-25A&aqs=chrome..69i57j69i60&sourceid=chrome&ie=UTF-8 | AA56: 61II6X5B8FBYJJV | AB56: =LEFT(AA56,6) -> 61II6X | AC56: =LEFT(AB56,3) -> 61I | AD56: =RIGHT(AB56,3) -> I6X | AE56: =RIGHT(AA56,7) -> 8FBYJJV | AF56: =LEFT(AE56,4) -> 8FBY | AG56: =RIGHT(AE56,3) -> JJV | AH56: =_xludf.CONCAT(AC56,_xludf.CONCAT("-",AD56)) -> #NAME? | AI56: =_xludf.CONCAT(AF56,_xludf.CONCAT("-",AG56)) -> #NAME?
A57: =_xludf.CONCAT(AH57,_xludf.CONCAT("-",AI57)) -> #NAME? | B57: Inquiry letter sent | F57: Connector for Thermocouple wires For Analog Input Cards of Paperless Recorder Model No. PR2024 | G57: "Saeed Ahmed Jamali saeed.ahmed@BarrettHodgson.com" 10002014 | I57: 43588 | J57: =IF(X57="","LINKS REQUIRED",IF(X57="Completed","LINKS HARVESTED","LINKS AVAILABLE")) -> LINKS HARVESTED | M57: Maaz | O57: Saad | W57: Connector for Thermocouple wires | X57: Completed | Y57: https://www.google.com/search?newwindow=1&ei=jT_MXPjAG5K8kwW8r7rQAg&q=Brainchild+PR2024+&oq=Brainchild+PR2024+&gs_l=psy-ab.3...23392.23860..24964...0.0..0.202.401.0j1j1......0....2j1..gws-wiz.Z8f6irvzZp4 https://www.google.com/search?newwindow=1&ei=pz_MXO2HGIi5kwWbjaqAAw&q=Brainchild+PR2024+spare+parts&oq=Brainchild+PR2024+spare+parts&gs_l=psy-ab.3..33i21.7570.9305..9537...0.0..0.281.2333.2-10......0....1..gws-wiz.......33i160.y3f5SkGTV0E | AA57: 634GZNZFYF5NFAN | AB57: =LEFT(AA57,6) -> 634GZN | AC57: =LEFT(AB57,3) -> 634 | AD57: =RIGHT(AB57,3) -> GZN | AE57: =RIGHT(AA57,7) -> YF5NFAN | AF57: =LEFT(AE57,4) -> YF5N | AG57: =RIGHT(AE57,3) -> FAN | AH57: =_xludf.CONCAT(AC57,_xludf.CONCAT("-",AD57)) -> #NAME? | AI57: =_xludf.CONCAT(AF57,_xludf.CONCAT("-",AG57)) -> #NAME?
A58: =_xludf.CONCAT(AH58,_xludf.CONCAT("-",AI58)) -> #NAME? | B58: Request for further information sent to customer | D58: A. Anwar Khan | F58: WOERNER- GREASE PUMP GMF-B/30 PART# 7850.37837.2 POS#10 SERIAL #202212 RATIO316:1 MANUFACTUR WOERNER GMBH & CO KG KOPPERN Make: China, ONLY INDENTED TYPE OF PUMP REQUIRED | G58: Nasir Ali Assistant Manager (Imports) Askari Cement Limited Ph#051-9272434-5 | H58: Yasir: Since customer have not given us specifications i have emailed Woener for price of this pump and email for specification also sent to customer | I58: 43591 | J58: =IF(X58="","LINKS REQUIRED",IF(X58="Completed","LINKS HARVESTED","LINKS AVAILABLE")) -> LINKS REQUIRED | AA58: 64GKFX8XLWG88MY | AB58: =LEFT(AA58,6) -> 64GKFX | AC58: =LEFT(AB58,3) -> 64G | AD58: =RIGHT(AB58,3) -> KFX | AE58: =RIGHT(AA58,7) -> LWG88MY | AF58: =LEFT(AE58,4) -> LWG8 | AG58: =RIGHT(AE58,3) -> 8MY | AH58: =_xludf.CONCAT(AC58,_xludf.CONCAT("-",AD58)) -> #NAME? | AI58: =_xludf.CONCAT(AF58,_xludf.CONCAT("-",AG58)) -> #NAME?
A59: =_xludf.CONCAT(AH59,_xludf.CONCAT("-",AI59)) -> #NAME? | B59: Quotation Validity Reminder Sent | D59: Qamar uddin | F59: SS 316L container with SS316L certification 1. SS 316L container with lid and handle Outer dai: 300MM Height: 300MM Wall thickness: 1.5MM 02 nos | G59: Ashraf Butt Procurement Officer GlaxoSmithKline Consumer Healthcare Pakistan Ltd. 35 - Dockyard Road, west wharf , Karachi Tel: 35274744 (Ext: 4744) | H59: Hasan: Quotation sent on 06-05-19 Hasan: Quotation validity reminder sent on 14-05-19 | I59: 43584 | J59: =IF(X59="","LINKS REQUIRED",IF(X59="Completed","LINKS HARVESTED","LINKS AVAILABLE")) -> LINKS REQUIRED | AA59: 65YD7X6Q9KRCD74 | AB59: =LEFT(AA59,6) -> 65YD7X | AC59: =LEFT(AB59,3) -> 65Y | AD59: =RIGHT(AB59,3) -> D7X | AE59: =RIGHT(AA59,7) -> 9KRCD74 | AF59: =LEFT(AE59,4) -> 9KRC | AG59: =RIGHT(AE59,3) -> D74 | AH59: =_xludf.CONCAT(AC59,_xludf.CONCAT("-",AD59)) -> #NAME? | AI59: =_xludf.CONCAT(AF59,_xludf.CONCAT("-",AG59)) -> #NAME?
A60: =_xludf.CONCAT(AH60,_xludf.CONCAT("-",AI60)) -> #NAME? | B60: Quotation Validity Reminder Sent | D60: A. Anwar Khan | F60: Motor 30kW, DRS180L, C1400RPM, 400V, B3, Make SEW (Nameplate attached) Geared Motor 7.5 kW,400V,0.9, Incl F, 1400/35RPM, Make SEW. | G60: Muhammad Rehan Anwar Procurement Officer Procurement Department– Processing Team quotations1@bestway.com.pk SPI # 52523-ELEC | H60: Discard its database Fly on SEW supplier database Hasan: Quotation sent on 13-05-19 Hasan: Quotation validity reminder sent on 21-05-19 | I60: 43592 | J60: =IF(X60="","LINKS REQUIRED",IF(X60="Completed","LINKS HARVESTED","LINKS AVAILABLE")) -> LINKS HARVESTED | K60: ` | M60: Maaz | O60: Saad | W60: Motor 30kW & 18.5kW & 7.5kW Geared (SEW DRIVE) | X60: Completed | Y60: https://www.google.com/search?q=Motor+30kW%2C+1400RPM%2C+400V%2C+B3&oq=Motor+30kW%2C+1400RPM%2C+400V%2C+B3&aqs=chrome..69i57&sourceid=chrome&ie=UTF-8 https://www.google.com/search?q=Motor+18.5+kW%2C+1400rpm%2C+400V%2C+B3&oq=Motor+18.5+kW%2C+1400rpm%2C+400V%2C+B3&aqs=chrome..69i57&sourceid=chrome&ie=UTF-8 https://www.google.com/search?newwindow=1&ei=zC3RXLJkwZGwB5bZkuAG&q=Geared+Motor+7.5+kW+-%22alibaba%22&oq=Geared+Motor+7.5+kW+-%22alibaba%22&gs_l=psy-ab.3...7427.12344..12865...0.0..0.247.2025.0j9j2......0....1..gws-wiz.......0i22i30.VvhtJPu1Ilc | AA60: 66DWLPNJKJ32CAO | AB60: =LEFT(AA60,6) -> 66DWLP | AC60: =LEFT(AB60,3) -> 66D | AD60: =RIGHT(AB60,3) -> WLP | AE60: =RIGHT(AA60,7) -> KJ32CAO | AF60: =LEFT(AE60,4) -> KJ32 | AG60: =RIGHT(AE60,3) -> CAO | AH60: =_xludf.CONCAT(AC60,_xludf.CONCAT("-",AD60)) -> #NAME? | AI60: =_xludf.CONCAT(AF60,_xludf.CONCAT("-",AG60)) -> #NAME?
A61: =_xludf.CONCAT(AH61,_xludf.CONCAT("-",AI61)) -> #NAME? | B61: Quotation Validity Reminder Sent | D61: A. Anwar Khan | F61: Motor 18.5 kW, 1400rpm, 400V, B3. Make ABB | G61: Muhammad Rehan Anwar Procurement Officer Procurement Department– Processing Team quotations1@bestway.com.pk SPI # 52523-ELEC | H61: fly on ABB Merged database Hasan: Quotation sent on above code | I61: 43592 | J61: =IF(X61="","LINKS REQUIRED",IF(X61="Completed","LINKS HARVESTED","LINKS AVAILABLE")) -> LINKS REQUIRED | M61: Internal Office Staff (All for one) | O61: Saad | AA61: 67XEIGECYQ3GQ5K | AB61: =LEFT(AA61,6) -> 67XEIG | AC61: =LEFT(AB61,3) -> 67X | AD61: =RIGHT(AB61,3) -> EIG | AE61: =RIGHT(AA61,7) -> YQ3GQ5K | AF61: =LEFT(AE61,4) -> YQ3G | AG61: =RIGHT(AE61,3) -> Q5K | AH61: =_xludf.CONCAT(AC61,_xludf.CONCAT("-",AD61)) -> #NAME? | AI61: =_xludf.CONCAT(AF61,_xludf.CONCAT("-",AG61)) -> #NAME?
A62: =_xludf.CONCAT(AH62,_xludf.CONCAT("-",AI62)) -> #NAME? | B62: Quotation Validity Reminder Sent | C62: Multiple quotation sent | D62: A. Anwar Khan | F62: Shrink wrapping machine 1. Wrapping height > 2200 MM 2. Turntable Diameter 1500 MM approx. 3. Maximum Weight of load 2000 Kg 4. Power Supply – Battery operated 5. Extended mast for wrapping height 8 Ft max 6. Weight scale system with printer with display for normal / or adhesive paper 7. Have EHS safety feature – Motor cover 8. Speed not less than 8 RMP | G62: Hafiz Muhammad Owais GlaxoSmithKline Pakistan Ltd. Head Office, Karachi 35-Dockyard Road West Wharf Karachi, Pakistan Phone 9.2211114757 hafizmuhammad.x.owais@gsk.com | H62: Maaz: again inquiry letter sent on new database (Stretch pallet wrapping Machine) as per boss order. new code is 686-T69-GT7Y-SPY-1 (14-May-2019) Hasan: Quotation sent on 15-05-19 Hasan: Revised Quotation sent on 17-05-19 | I62: 43594 | J62: =IF(X62="","LINKS REQUIRED",IF(X62="Completed","LINKS HARVESTED","LINKS AVAILABLE")) -> LINKS HARVESTED | M62: Maaz | O62: Maaz | W62: Stretch pallet wrapping Machine | X62: Completed | Y62: https://www.google.com/search?newwindow=1&ei=1eLTXK6QJsebkwW1y6-wAw&q=shrink+wrapping+machine+manufacturers&oq=Shrink+wrapping+machine+manu&gs_l=psy-ab.1.0.0l10.2503.14469..15877...0.0..0.273.1012.0j3j2......0....1..gws-wiz.......0i71j0i67.61zm9YThSmQ https://www.google.com/search?newwindow=1&ei=5uLTXNedLe7jsAf5sZXQBQ&q=shrink+wrapping+machine+europe+manufacturers&oq=shrink+wrapping+machine+europe+manufacturers&gs_l=psy-ab.3...18522.19697..19809...0.0..0.241.1227.0j3j3......0....1..gws-wiz.......0i71j35i304i39j0i13j0i13i30.gP6lGODKy18 https://www.google.com/search?q=shrink+wrap+machine&newwindow=1&source=lnms&sa=X&ved=0ahUKEwjfspiHgpDiAhXK26QKHXU2DxQQ_AUICSgA&biw=1422&bih=978&dpr=0.9 Pallet Stretch Wrapping machine (New links) https://www.google.com/search?q=large+pallet+shrink+wrap+machine&rlz=1C1SQJL_enPK830PK831&source=lnms&tbm=isch&sa=X&ved=0ahUKEwiVlda4tZjiAhXSxoUKHdsjCkIQ_AUIDigB&biw=1536&bih=722 https://www.google.com/search?q=low+profile+stretch+wrap+machine&rlz=1C1SQJL_enPK830PK831&source=lnms&tbm=isch&sa=X&ved=0ahUKEwjK2866tZjiAhUQ1hoKHY1xCqgQ_AUIDigB&biw=1536&bih=722 https://www.google.com/search?q=manual+pallet+shrink+wrap+machine&rlz=1C1SQJL_enPK830PK831&source=lnms&tbm=isch&sa=X&ved=0ahUKEwiC8eu2tZjiAhUB-YUKHYdpA4wQ_AUIDygC&biw=1536&bih=722 https://www.google.com/search?q=manual+stretch+wrap+machine&rlz=1C1SQJL_enPK830PK831&source=lnms&tbm=isch&sa=X&ved=0ahUKEwj3lp-stZjiAhUpyIUKHbcZBaUQ_AUIDygC&biw=1536&bih=722 https://www.google.com/search?q=orbital+stretch+wrap+machine&rlz=1C1SQJL_enPK830PK831&source=lnms&tbm=isch&sa=X&ved=0ahUKEwiex-WutZjiAhVIURoKHQ0jADwQ_AUIDygC&biw=1536&bih=722 https://www.google.com/search?q=orion+stretch+wrapper&rlz=1C1SQJL_enPK830PK831&source=lnms&tbm=isch&sa=X&ved=0ahUKEwjflbK0tZjiAhVRxIUKHZy3BOgQ_AUIDigB&biw=1536&bih=722 https://www.google.com/search?q=pallet+wrapping+machine+rental&rlz=1C1SQJL_enPK830PK831&source=lnms&tbm=isch&sa=X&ved=0ahUKEwig2bOxtZjiAhUrx4UKHfGJAl4Q_AUIDigB&biw=1536&bih=722 https://www.google.com/search?q=portable+pallet+wrapper&rlz=1C1SQJL_enPK830PK831&source=lnms&tbm=isch&sa=X&ved=0ahUKEwjiwNaotZjiAhVEdhoKHRt6CqUQ_AUIDigB&biw=1536&bih=722 https://www.google.com/search?q=stretch+pallet+wrapping+machine&rlz=1C1SQJL_enPK830PK831&oq=stretch+pallet&aqs=chrome.2.0j69i57j0l4.41290j0j7&sourceid=chrome&ie=UTF-8 https://www.google.com/search?q=stretch+pallet+wrapping+machine&rlz=1C1SQJL_enPK830PK831&source=lnms&tbm=isch&sa=X&ved=0ahUKEwii86uHtZjiAhVMXBoKHTvXBkQQ_AUIDigB&biw=1536&bih=722 https://www.google.com/search?rlz=1C1SQJL_enPK830PK831&q=large+pallet+shrink+wrap+machine&sa=X&ved=2ahUKEwii86uHtZjiAhVMXBoKHTvXBkQQ1QIoBnoECAkQBw https://www.google.com/search?rlz=1C1SQJL_enPK830PK831&q=low+profile+stretch+wrap+machine&sa=X&ved=2ahUKEwii86uHtZjiAhVMXBoKHTvXBkQQ1QIoB3oECAkQCA https://www.google.com/search?rlz=1C1SQJL_enPK830PK831&q=manual+pallet+shrink+wrap+machine&sa=X&ved=2ahUKEwii86uHtZjiAhVMXBoKHTvXBkQQ1QIoBXoECAkQBg https://www.google.com/search?rlz=1C1SQJL_enPK830PK831&q=manual+stretch+wrap+machine&sa=X&ved=2ahUKEwii86uHtZjiAhVMXBoKHTvXBkQQ1QIoAXoECAkQAg https://www.google.com/search?rlz=1C1SQJL_enPK830PK831&q=orbital+stretch+wrap+machine&sa=X&ved=2ahUKEwii86uHtZjiAhVMXBoKHTvXBkQQ1QIoAnoECAkQAw https://www.google.com/search?rlz=1C1SQJL_enPK830PK831&q=orion+stretch+wrapper&sa=X&ved=2ahUKEwii86uHtZjiAhVMXBoKHTvXBkQQ1QIoBHoECAkQBQ https://www.google.com/search?rlz=1C1SQJL_enPK830PK831&q=pallet+wrapping+machine+rental&sa=X&ved=2ahUKEwii86uHtZjiAhVMXBoKHTvXBkQQ1QIoA3oECAkQBA https://www.google.com/search?rlz=1C1SQJL_enPK830PK831&q=portable+pallet+wrapper&sa=X&ved=2ahUKEwii86uHtZjiAhVMXBoKHTvXBkQQ1QIoAHoECAkQAQ | AA62: 686T69X1GT7YSPY | AB62: =LEFT(AA62,6) -> 686T69 | AC62: =LEFT(AB62,3) -> 686 | AD62: =RIGHT(AB62,3) -> T69 | AE62: =RIGHT(AA62,7) -> GT7YSPY | AF62: =LEFT(AE62,4) -> GT7Y | AG62: =RIGHT(AE62,3) -> SPY | AH62: =_xludf.CONCAT(AC62,_xludf.CONCAT("-",AD62)) -> #NAME? | AI62: =_xludf.CONCAT(AF62,_xludf.CONCAT("-",AG62)) -> #NAME?
A63: =_xludf.CONCAT(AH63,_xludf.CONCAT("-",AI63)) -> #NAME? | B63: Order Arrived | D63: A. Anwar Khan | F63: MCS MAGNUM Rev 7 (RECN0101006) | G63: hasan_kazmi@colpal.com.pk | H63: Email sent to petra for proforma invoice Hasan: Quotation sent on 17-05-19 Hasan: Quotation validity reminder sent on 24-05-19 | I63: 43594 | J63: =IF(X63="","LINKS REQUIRED",IF(X63="Completed","LINKS HARVESTED","LINKS AVAILABLE")) -> LINKS REQUIRED | AA63: 68QHXHT8F61IWT6 | AB63: =LEFT(AA63,6) -> 68QHXH | AC63: =LEFT(AB63,3) -> 68Q | AD63: =RIGHT(AB63,3) -> HXH | AE63: =RIGHT(AA63,7) -> F61IWT6 | AF63: =LEFT(AE63,4) -> F61I | AG63: =RIGHT(AE63,3) -> WT6 | AH63: =_xludf.CONCAT(AC63,_xludf.CONCAT("-",AD63)) -> #NAME? | AI63: =_xludf.CONCAT(AF63,_xludf.CONCAT("-",AG63)) -> #NAME?
A64: =_xludf.CONCAT(AH64,_xludf.CONCAT("-",AI64)) -> #NAME? | B64: Quotation Validity Reminder Sent | D64: A. Anwar Khan | F64: Bladder Assembly for Hydraulic Accumulator Model: IHV-20-250 /Equivalent With all necessary accessories (Snap & Data Sheet Attached) UOM: Set Req. Qty: 4 | G64: ARIF MEMON MANAGER PURCHASE POWER CEMENT LIMITED formerly Al-Abbas Cement Industries Limited A Subsidiary of Arif Habib Group Head Office: Arif Habib Center 23, M.T .Khan Road, Karachi - 74000, Pakistan Phone: +92 21 32468231-2, 32468350-1, Fax No. : +92 21 32463209 Email: arif.memon@powercement.pk Website: www.powercement.com.pk SPR # 206-1751 | H64: Hasan: Quotation sent on 17-05-19 Hasan: Quotation validity reminder sent on 24-05-19 | I64: 43596 | J64: =IF(X64="","LINKS REQUIRED",IF(X64="Completed","LINKS HARVESTED","LINKS AVAILABLE")) -> LINKS HARVESTED | K64: done | M64: Maaz | O64: Saad | W64: Bladder Assembly for Hydraulic Accumulator | X64: Completed | Y64: https://www.google.com/search?q=IHV-20-250&newwindow=1&source=lnms&sa=X&ved=0ahUKEwj_t4nM2ZfiAhWGzIUKHXtpDn0Q_AUICSgA&biw=1745&bih=852&dpr=1.1 https://www.google.com/search?newwindow=1&biw=1745&bih=852&ei=qfbYXNeDConQkwX34JLAAQ&q=IHV-20-250+suppliers&oq=IHV-20-250+suppliers&gs_l=psy-ab.3..33i160.42978.47273..47466...0.0..0.253.1867.0j2j7......0....1..gws-wiz.......0i71j35i39j0i30.onY-DDCt4V8 | AA64: 69BFNLLWMQBC840 | AB64: =LEFT(AA64,6) -> 69BFNL | AC64: =LEFT(AB64,3) -> 69B | AD64: =RIGHT(AB64,3) -> FNL | AE64: =RIGHT(AA64,7) -> MQBC840 | AF64: =LEFT(AE64,4) -> MQBC | AG64: =RIGHT(AE64,3) -> 840 | AH64: =_xludf.CONCAT(AC64,_xludf.CONCAT("-",AD64)) -> #NAME? | AI64: =_xludf.CONCAT(AF64,_xludf.CONCAT("-",AG64)) -> #NAME?
A65: =_xludf.CONCAT(AH65,_xludf.CONCAT("-",AI65)) -> #NAME? | B65: Quotation Validity Reminder Sent | C65: second quotatioin sent | D65: A. Anwar Khan | F65: COUPLING 1140 COUPLING T10-1140 Qty;_ 01 SET | G65: ARIF MEMON MANAGER PURCHASE POWER CEMENT LIMITED formerly Al-Abbas Cement Industries Limited A Subsidiary of Arif Habib Group Head Office: Arif Habib Center 23, M.T .Khan Road, Karachi - 74000, Pakistan Phone: +92 21 32468231-2, 32468350-1, Fax No. : +92 21 32463209 Email: arif.memon@powercement.pk Website: www.powercement.com.pk SPR # 1752 | H65: Hasan: Quotation sent on 14-05-19 Hasan: 2nd Quotation sent on 16-05-19 Hasan: Quotation validity reminder sent on 21-05-19 | I65: 43596 | J65: =IF(X65="","LINKS REQUIRED",IF(X65="Completed","LINKS HARVESTED","LINKS AVAILABLE")) -> LINKS HARVESTED | K65: done | M65: Maaz | O65: Maaz | W65: COUPLING T10-1140 | X65: Completed | Y65: https://www.google.com/search?q=COUPLING+T10-1140&newwindow=1&source=lnms&sa=X&ved=0ahUKEwj2p87L2pfiAhWkPOwKHXxiAMMQ_AUICSgA&biw=1745&bih=852&dpr=1.1 https://www.google.com/search?newwindow=1&ei=offYXICtOsXVkwX4t6n4Ag&q=COUPLING+T10-1140+supplier&oq=COUPLING+T10-1140+supplier&gs_l=psy-ab.3...48701.50595..50915...0.0..0.249.1786.0j8j1......0....1..gws-wiz.......0i71j35i302i39j33i10.vj_9zgFp26E https://www.google.com/search?newwindow=1&ei=1ffYXMfGKoTXkwXQwaaQCw&q=COUPLING+T10-1140+manufacturer&oq=COUPLING+T10-1140+manufacturer&gs_l=psy-ab.3..33i21l2.110709.113339..113517...0.0..0.296.3408.2-12......0....1..gws-wiz.......0i71j35i39j33i10.FI5lPUDK3Mg | AA65: 69GX83JU7X5KZO9 | AB65: =LEFT(AA65,6) -> 69GX83 | AC65: =LEFT(AB65,3) -> 69G | AD65: =RIGHT(AB65,3) -> X83 | AE65: =RIGHT(AA65,7) -> 7X5KZO9 | AF65: =LEFT(AE65,4) -> 7X5K | AG65: =RIGHT(AE65,3) -> ZO9 | AH65: =_xludf.CONCAT(AC65,_xludf.CONCAT("-",AD65)) -> #NAME? | AI65: =_xludf.CONCAT(AF65,_xludf.CONCAT("-",AG65)) -> #NAME?
A66: =_xludf.CONCAT(AH66,_xludf.CONCAT("-",AI66)) -> #NAME? | B66: Quotation Validity Reminder Sent | D66: A. Anwar Khan | F66: MCB Circuit Breaker , 20~25-Amp, 3- Pole, Make: Schneider & Terasaki (A9F54320 Acti9 iC60H 3P 20A C Miniature Circuit breaker) (A9F44325 Acti9 iC60N 3P 25A C Miniature Circuit breaker) 01 Nos MCB Circuit Breaker , 3-Amp, 1-Pole, Make: Schneider & Siemens (M9F42103 Multi 9 - C60BP - MCB - 1P - 3 A - C Curve - 277 V - 10 kA - UL 489) 16 Nos | G66: Afzal Ghani, Asst.Procurement Officer, Ferozsons Laboratories Limited P.O Ferozsons, Amangarh, Nowshera, K.P.K, |pro.nowshera@ferozsons-labs.com|Website:www.ferozsons-labs.com|0923-560145, 0312-9486757|FAX: 0923-611302| Inquiry # 2691 ,dt:11-05-2019 | H66: Hasan: Quotation sent on 17-05-19 Hasan: Quotation validity reminder sent on 24-05-19 | I66: 43596 | J66: =IF(X66="","LINKS REQUIRED",IF(X66="Completed","LINKS HARVESTED","LINKS AVAILABLE")) -> LINKS HARVESTED | K66: done | M66: Maaz | O66: Saad | W66: MCB Circuit Breaker (Schneider & Terasaki) | X66: Completed | Y66: https://www.google.com/search?newwindow=1&ei=OkLaXKfmNY3bwQKwxrLADA&q=Schneider+Electric+M9F42103&oq=Schneider+Electric+M9F42103&gs_l=psy-ab.3..33i160.313607.313607..314116...0.0..0.251.251.2-1......0....2j1..gws-wiz.J9jYk3I9qhQ https://www.google.com/search?newwindow=1&ei=jUPaXJ-6NMLVkwWIwrnAAg&q=Schneider+A9F44325&oq=Schneider+A9F44325&gs_l=psy-ab.3...4808.4808..5292...0.0..0.183.183.0j1......0....1..gws-wiz.hGhVpRYfHNI https://www.google.com/search?newwindow=1&ei=lEPaXIGYAcL5kwXgzoaQAQ&q=Schneider+A9F54320&oq=Schneider+A9F54320&gs_l=psy-ab.3..0j0i22i30.13745.13745..14239...0.0..0.191.191.0j1......0....2j1..gws-wiz.nB-CuE3gpoQ | AA66: 69SXNCPHXTOJE2V | AB66: =LEFT(AA66,6) -> 69SXNC | AC66: =LEFT(AB66,3) -> 69S | AD66: =RIGHT(AB66,3) -> XNC | AE66: =RIGHT(AA66,7) -> XTOJE2V | AF66: =LEFT(AE66,4) -> XTOJ | AG66: =RIGHT(AE66,3) -> E2V | AH66: =_xludf.CONCAT(AC66,_xludf.CONCAT("-",AD66)) -> #NAME? | AI66: =_xludf.CONCAT(AF66,_xludf.CONCAT("-",AG66)) -> #NAME?
A67: =_xludf.CONCAT(AH67,_xludf.CONCAT("-",AI67)) -> #NAME? | B67: Inquiry letter sent | D67: A. Anwar Khan | F67: Dry Contact Wall Mounted Type HYGROSTATE (Relative Humidity 0-100%) & (Manually Adjustable) , Brand: RANCO , 01 Nos | G67: Afzal Ghani, Asst.Procurement Officer, P.O Ferozsons, Amangarh, Nowshera, K.P.K, |pro.nowshera@ferozsons-labs.com|Website:www.ferozsons-labs.com|0923-560145, 0312-9486757|FAX: 0923-611302| Inquiry # 2691 ,Dated :11-05-2019 URGENT | H67: saleseliwell@invensys.com | I67: 43596 | J67: =IF(X67="","LINKS REQUIRED",IF(X67="Completed","LINKS HARVESTED","LINKS AVAILABLE")) -> LINKS HARVESTED | K67: done | M67: Maaz | O67: Saad | W67: HYGROSTATE (RANCO) | X67: Completed | Y67: https://www.google.com/search?newwindow=1&biw=1745&bih=852&ei=OjzaXNt_zsrAAsa0vPgO&q=RANCO++HYGROSTATE&oq=RANCO++HYGROSTATE&gs_l=psy-ab.3..0i71l8.0.0..809693...0.0..0.0.0.......0......gws-wiz.nUE9LmDir8A | AA67: 6BXK82QNBX0E86F | AB67: =LEFT(AA67,6) -> 6BXK82 | AC67: =LEFT(AB67,3) -> 6BX | AD67: =RIGHT(AB67,3) -> K82 | AE67: =RIGHT(AA67,7) -> BX0E86F | AF67: =LEFT(AE67,4) -> BX0E | AG67: =RIGHT(AE67,3) -> 86F | AH67: =_xludf.CONCAT(AC67,_xludf.CONCAT("-",AD67)) -> #NAME? | AI67: =_xludf.CONCAT(AF67,_xludf.CONCAT("-",AG67)) -> #NAME?
A68: =_xludf.CONCAT(AH68,_xludf.CONCAT("-",AI68)) -> #NAME? | B68: Inquiry letter sent | D68: A. Anwar Khan | F68: Air Seal or Shaking Cylinder Gasket for FBD Shaker Cylinder Model# ALR-A-FA 100*300ST Fluid Bed Dryer Model: YC-FBD-100 Max .Press 9.9 Kg/CM2 Make: Yenchen Machinery Co., Ltd 06 Nos | G68: Afzal Ghani, Asst.Procurement Officer, P.O Ferozsons, Amangarh, Nowshera, K.P.K, |pro.nowshera@ferozsons-labs.com|Website:www.ferozsons-labs.com|0923-560145, 0312-9486757|FAX: 0923-611302| Inquiry # 2691 ,Dated :11-05-2019 Inquiry # Nil ,Dated :11-05-2019 URGENT | H68: yenchen@yenchen.com.tw Maaz: found only 12 emails | I68: 43596 | J68: =IF(X68="","LINKS REQUIRED",IF(X68="Completed","LINKS HARVESTED","LINKS AVAILABLE")) -> LINKS HARVESTED | K68: done | M68: Maaz | O68: Saad | W68: Air Seal or Shaking Cylinder Gasket (Yenchen Machinery) | X68: Completed | Y68: http://www.yenchen.com.tw/en/page/contact-info.html https://www.google.com/search?newwindow=1&ei=yzjaXM_zFMmdkgX-iIPYAw&q=Fluid+Bed+Dryer+YC-FBD-100&oq=Fluid+Bed+Dryer+YC-FBD-100&gs_l=psy-ab.3...254755.254992..255841...0.0..0.204.380.0j1j1......0....2j1..gws-wiz.PRc2dkiiwiU | AA68: 6D4CN3K61ZWQK0T | AB68: =LEFT(AA68,6) -> 6D4CN3 | AC68: =LEFT(AB68,3) -> 6D4 | AD68: =RIGHT(AB68,3) -> CN3 | AE68: =RIGHT(AA68,7) -> 1ZWQK0T | AF68: =LEFT(AE68,4) -> 1ZWQ | AG68: =RIGHT(AE68,3) -> K0T | AH68: =_xludf.CONCAT(AC68,_xludf.CONCAT("-",AD68)) -> #NAME? | AI68: =_xludf.CONCAT(AF68,_xludf.CONCAT("-",AG68)) -> #NAME?
A69: =_xludf.CONCAT(AH69,_xludf.CONCAT("-",AI69)) -> #NAME? | B69: Quotation Validity Reminder Sent | D69: A. Anwar Khan | F69: 1. HELICAL WORM GEAR MOTOR Qty;_ 03 NOS SA57DT90S4 NOMINAL OUTPUT : 0.75 KW RPM : 68 ARTICLE NO. : 13003564 2. GEARED MOTOR 0.75 KW Qty:- 01 NOS RPM : 1380/128 SA47DT80 MAKE: SEW | G69: ARIF MEMON MANAGER PURCHASE POWER CEMENT LIMITED formerly Al-Abbas Cement Industries Limited A Subsidiary of Arif Habib Group Head Office: Arif Habib Center 23, M.T .Khan Road, Karachi - 74000, Pakistan Phone: +92 21 32468231-2, 32468350-1, Fax No. : +92 21 32463209 Email: arif.memon@powercement.pk Website: www.powercement.com.pk SPR # 206-1624 | H69: christine@sogears.com enquiry letter sent to above email email also sent to maker of the machine Hasan: Quotation sent on 21-05-19 | I69: 43598 | J69: =IF(X69="","LINKS REQUIRED",IF(X69="Completed","LINKS HARVESTED","LINKS AVAILABLE")) -> LINKS REQUIRED | AA69: 6EU2DCR7S5FYW3Z | AB69: =LEFT(AA69,6) -> 6EU2DC | AC69: =LEFT(AB69,3) -> 6EU | AD69: =RIGHT(AB69,3) -> 2DC | AE69: =RIGHT(AA69,7) -> S5FYW3Z | AF69: =LEFT(AE69,4) -> S5FY | AG69: =RIGHT(AE69,3) -> W3Z | AH69: =_xludf.CONCAT(AC69,_xludf.CONCAT("-",AD69)) -> #NAME? | AI69: =_xludf.CONCAT(AF69,_xludf.CONCAT("-",AG69)) -> #NAME?
A70: =_xludf.CONCAT(AH70,_xludf.CONCAT("-",AI70)) -> #NAME? | B70: Quotation Validity Reminder Sent | D70: Qamar uddin | F70: 1-OD=21.6,19.80,12.0,11.10,8.5mm. 2-L =66.10,69.50,42.5,33.0,3.1mm. Powder coated as per sample. Qty.=50Pcs each. | G70: Sci-life Pharm.16,K.O.C.H.S,Ameer Khusro Road,Karachi. M.Faisal Sr.Engineering Manager.0321-2777417 | H70: Hasan: Quotation sent on 14-05-19 Rates were given by Mr. Qamar | I70: 43599 | J70: =IF(X70="","LINKS REQUIRED",IF(X70="Completed","LINKS HARVESTED","LINKS AVAILABLE")) -> LINKS REQUIRED | AA70: 6F95PIQTKZVF1CQ | AB70: =LEFT(AA70,6) -> 6F95PI | AC70: =LEFT(AB70,3) -> 6F9 | AD70: =RIGHT(AB70,3) -> 5PI | AE70: =RIGHT(AA70,7) -> KZVF1CQ | AF70: =LEFT(AE70,4) -> KZVF | AG70: =RIGHT(AE70,3) -> 1CQ | AH70: =_xludf.CONCAT(AC70,_xludf.CONCAT("-",AD70)) -> #NAME? | AI70: =_xludf.CONCAT(AF70,_xludf.CONCAT("-",AG70)) -> #NAME?
A71: =_xludf.CONCAT(AH71,_xludf.CONCAT("-",AI71)) -> #NAME? | B71: Quotation Validity Reminder Sent | D71: Qamar uddin | F71: Ex Cekon plug with 3pin,16amp Model:8570/12-306 Make:STAHL Ex Receptacle with 3pin,16amp Model:8570/11-306 Make:STAHL Ex Cekon plug with 5pin,20amp Model:8570/22-505 Make:STAHL Ex Receptacle with 5pin,20amp Model:8570/21-505 Make:STAHL Direct Online (DOL) Motor Starter 5kw make:STHAL Ordering Code:8264/5-SM-ES5,5kW400V-T | G71: Ashraf Butt Procurement Officer GlaxoSmithKline Consumer Healthcare Pakistan Ltd. 35 - Dockyard Road, west wharf , Karachi Tel: 35274744 (Ext: 4744) ashraf.x.butt@gsk.com | H71: Email sent to STAHL ITem 3 and 4 rates already have | I71: 43600 | J71: =IF(X71="","LINKS REQUIRED",IF(X71="Completed","LINKS HARVESTED","LINKS AVAILABLE")) -> LINKS REQUIRED | AA71: 6I3UG85MLD2L967 | AB71: =LEFT(AA71,6) -> 6I3UG8 | AC71: =LEFT(AB71,3) -> 6I3 | AD71: =RIGHT(AB71,3) -> UG8 | AE71: =RIGHT(AA71,7) -> LD2L967 | AF71: =LEFT(AE71,4) -> LD2L | AG71: =RIGHT(AE71,3) -> 967 | AH71: =_xludf.CONCAT(AC71,_xludf.CONCAT("-",AD71)) -> #NAME? | AI71: =_xludf.CONCAT(AF71,_xludf.CONCAT("-",AG71)) -> #NAME?
A72: =_xludf.CONCAT(AH72,_xludf.CONCAT("-",AI72)) -> #NAME? | B72: Quotation Sent | D72: Qamar uddin | F72: Inductive Proximity Sensor Cylindrical Type in metal series Completely Thereaded,Dia 18mm long Type, Sensing range: 6-8mm,PNP,Normally Open, Supply Voltage:10-30vdc Cable lenth:2meter QTY: 2 THIS Specified Sensor is required which meets the standard of ATEX certified II 2GD for zone 1;21 ================================= Cylindrical type Thru-Beam sensor Dia:18mm, Supply Voltage:12 to 24 VDC PNP Normally Open Output Range :12 meter, Connection Cable Length :02 Meter QTY: 2 THIS Specified Sensor is required which meets the standard of ATEX certified II 2GD for zone 1;21 ================================ Capacitive Proximity sensor Cylindrical type in metal series completely threaded, Día 30mm,sensing range:15mm,PNP, Normally open, Supply Voltage:10-30vdc Cable Length :2meter QTY: 4 THIS Specified Sensor is required which meets the standard of ATEX certified II 2GD for zone 1;21 | G72: Ashraf Butt Procurement Officer GlaxoSmithKline Consumer Healthcare Pakistan Ltd. 35 - Dockyard Road, west wharf , Karachi Tel: 35274744 (Ext: 4744) ashraf.x.butt@gsk.com | H72: Maaz: again database updated (23-May-2019) | I72: 43600 | J72: =IF(X72="","LINKS REQUIRED",IF(X72="Completed","LINKS HARVESTED","LINKS AVAILABLE")) -> LINKS HARVESTED | M72: Maaz | O72: Saad | X72: Completed | Y72: https://www.google.com/search?newwindow=1&ei=C6vbXIbFOoSBi-gP0rWxgAg&q=Capacitive+Proximity+sensor+ATEX&oq=Capacitive+Proximity+sensor+ATEX&gs_l=psy-ab.3..0i22i30.2323.3761..4498...0.0..0.192.932.0j5......0....1..gws-wiz.......0i71j0i67j0.VTa3XEFu1lc https://www.google.com/search?newwindow=1&ei=7KrbXOzaHo3SkwXM9YigDw&q=Cylindrical+type+Thru-Beam+sensor+ATEX&oq=Cylindrical+type+Thru-Beam+sensor+ATEX&gs_l=psy-ab.3...40480.41686..42358...0.0..0.367.1207.0j2j2j1......0....1..gws-wiz.......0i71j35i302i39j33i21j33i160.TGfS5O1YwfM https://www.google.com/search?newwindow=1&ei=xKrbXJnGF9GUsAf1zY_AAQ&q=Inductive+Proximity+Sensor+ATEX&oq=Inductive+Proximity+Sensor+ATEX&gs_l=psy-ab.3..0i22i30.89153.90383..91073...0.0..0.198.1140.0j6......0....1..gws-wiz.......0i71j35i39j0i67j0j0i20i263.gb0dqPUNYE0 https://www.google.com/search?newwindow=1&biw=1745&bih=852&ei=UPXkXIT5GcqCvQTlrKGQDQ&q=ATEX+sensor&oq=ATEX+sensor&gs_l=psy-ab.3..0i7i30l2j0j0i30l2j0i5i30j0i8i30l4.581874.584088..584569...0.0..0.200.399.0j1j1......0....1..gws-wiz.DYoSpzSXYnw https://www.google.com/search?newwindow=1&biw=1745&bih=852&ei=mvfkXPadGuaCk74Pu6aA8As&q=ATEX+sensor+manufacturers&oq=ATEX+sensor+manufacturers&gs_l=psy-ab.3...33954.36689..36921...0.0..0.240.2955.2-14....2..0....1..gws-wiz.......0i22i30j0i333j33i21j33i160.2fHPnS-nw4w http://www.bdcelectronic.com/contatti.htm | AA72: 6KCTD8FHP58QI85 | AB72: =LEFT(AA72,6) -> 6KCTD8 | AC72: =LEFT(AB72,3) -> 6KC | AD72: =RIGHT(AB72,3) -> TD8 | AE72: =RIGHT(AA72,7) -> P58QI85 | AF72: =LEFT(AE72,4) -> P58Q | AG72: =RIGHT(AE72,3) -> I85 | AH72: =_xludf.CONCAT(AC72,_xludf.CONCAT("-",AD72)) -> #NAME? | AI72: =_xludf.CONCAT(AF72,_xludf.CONCAT("-",AG72)) -> #NAME?
A73: =_xludf.CONCAT(AH73,_xludf.CONCAT("-",AI73)) -> #NAME? | B73: Quotation Validity Reminder Sent | D73: Qamar uddin | F73: silicon sleeve with food grade certification for Xiaolun granulation 1. Inner dia 160MM length 100MM thickness 03MM 03nos 2. Upper ID 190MM Lower ID 210MM Length 130MM thickness 03MM 02nos | G73: Ashraf Butt Procurement Officer GlaxoSmithKline Consumer Healthcare Pakistan Ltd. 35 - Dockyard Road, west wharf , Karachi Tel: 35274744 (Ext: 4744) ashraf.x.butt@gsk.com | H73: Hasan: Quotation sent on 15-05-19 Rates Given by Mr. Qamar Hasan: Quotation validity reminder sent on 22-05-19 | I73: 43600 | J73: =IF(X73="","LINKS REQUIRED",IF(X73="Completed","LINKS HARVESTED","LINKS AVAILABLE")) -> LINKS REQUIRED | AA73: 6KITIQATTACJPQ9 | AB73: =LEFT(AA73,6) -> 6KITIQ | AC73: =LEFT(AB73,3) -> 6KI | AD73: =RIGHT(AB73,3) -> TIQ | AE73: =RIGHT(AA73,7) -> TACJPQ9 | AF73: =LEFT(AE73,4) -> TACJ | AG73: =RIGHT(AE73,3) -> PQ9 | AH73: =_xludf.CONCAT(AC73,_xludf.CONCAT("-",AD73)) -> #NAME? | AI73: =_xludf.CONCAT(AF73,_xludf.CONCAT("-",AG73)) -> #NAME?
A74: =_xludf.CONCAT(AH74,_xludf.CONCAT("-",AI74)) -> #NAME? | B74: Quotation Validity Reminder Sent | D74: Qamar uddin | F74: SS 316L perforated pipe/Sieve with food grade certification | G74: Ashraf Butt Procurement Officer GlaxoSmithKline Consumer Healthcare Pakistan Ltd. 35 - Dockyard Road, west wharf , Karachi Tel: 35274744 (Ext: 4744) ashraf.x.butt@gsk.com | H74: Hasan: Quotation sent on 15-05-19 Rates Given by Mr. Qamar Hasan: Quotation validity reminder sent on 22-05-19 | I74: 43600 | J74: =IF(X74="","LINKS REQUIRED",IF(X74="Completed","LINKS HARVESTED","LINKS AVAILABLE")) -> LINKS REQUIRED | AA74: 6KXWK2ZUH4X3LN6 | AB74: =LEFT(AA74,6) -> 6KXWK2 | AC74: =LEFT(AB74,3) -> 6KX | AD74: =RIGHT(AB74,3) -> WK2 | AE74: =RIGHT(AA74,7) -> H4X3LN6 | AF74: =LEFT(AE74,4) -> H4X3 | AG74: =RIGHT(AE74,3) -> LN6 | AH74: =_xludf.CONCAT(AC74,_xludf.CONCAT("-",AD74)) -> #NAME? | AI74: =_xludf.CONCAT(AF74,_xludf.CONCAT("-",AG74)) -> #NAME?
A75: =_xludf.CONCAT(AH75,_xludf.CONCAT("-",AI75)) -> #NAME? | B75: Inquiry letter sent | D75: Qamar uddin | F75: 60 Kg Granulation Suite URS Attached | G75: Mohammad Salman Khan Ghauri Barrett Hodgson Pakistan (Pvt.) Ltd. Phones: 2570651-57 / 2568810-14, ( Ext: 2118 ) Cell: +92 300 2365690 salman.ghauri@BarrettHodgson.com | H75: Use old database | I75: 43600 | J75: =IF(X75="","LINKS REQUIRED",IF(X75="Completed","LINKS HARVESTED","LINKS AVAILABLE")) -> LINKS REQUIRED | M75: Internal Office Staff (All for one) | O75: Saad | AA75: 6N8CXY6RZXGKXZE | AB75: =LEFT(AA75,6) -> 6N8CXY | AC75: =LEFT(AB75,3) -> 6N8 | AD75: =RIGHT(AB75,3) -> CXY | AE75: =RIGHT(AA75,7) -> ZXGKXZE | AF75: =LEFT(AE75,4) -> ZXGK | AG75: =RIGHT(AE75,3) -> XZE | AH75: =_xludf.CONCAT(AC75,_xludf.CONCAT("-",AD75)) -> #NAME? | AI75: =_xludf.CONCAT(AF75,_xludf.CONCAT("-",AG75)) -> #NAME?
A76: =_xludf.CONCAT(AH76,_xludf.CONCAT("-",AI76)) -> #NAME? | B76: Closed | D76: A. Anwar Khan | F76: 041-610-510 CONN,WIRE NUT:YELLOW,22 AWG MIN CONNECTOR,WIRE NUT: COLOR: YELLOW MINIMUM CONDUCTOR: 22 AWG MAXIMUM CONDUCTOR: 10 AWG CONNECTOR MATERIAL: CERAMIC PLASTIC TEXT:X-REF SIZE : MEDIUM TEMPERATURE RATING 1000F FAX# (330) 745 - 6688 MFG AKRON PORCELAIN & PLASTIC CO:CSB-17 Qty = 50 | G76: ENGRO FERTILIZERS Muhammad Imran Iqbal 7th Floor, The Harbor Front Building, HC # 3,Marine Drive, Block # 4, Clifton, Karachi, Tel: 021-35297534 miiqbal@engro.com | I76: 43600 | J76: =IF(X76="","LINKS REQUIRED",IF(X76="Completed","LINKS HARVESTED","LINKS AVAILABLE")) -> LINKS REQUIRED | AA76: 6P8XAELG5GID3GJ | AB76: =LEFT(AA76,6) -> 6P8XAE | AC76: =LEFT(AB76,3) -> 6P8 | AD76: =RIGHT(AB76,3) -> XAE | AE76: =RIGHT(AA76,7) -> 5GID3GJ | AF76: =LEFT(AE76,4) -> 5GID | AG76: =RIGHT(AE76,3) -> 3GJ | AH76: =_xludf.CONCAT(AC76,_xludf.CONCAT("-",AD76)) -> #NAME? | AI76: =_xludf.CONCAT(AF76,_xludf.CONCAT("-",AG76)) -> #NAME?
A77: =_xludf.CONCAT(AH77,_xludf.CONCAT("-",AI77)) -> #NAME? | B77: Closed | D77: A. Anwar Khan | F77: 042-365-256 SLV:INSULATION,16MM SLEEVE: TYPE: INSULATION SIZE: 16MM MATERIAL: VARNISH IMPREGNATED GR A TEXT:EMPIRE, TYPE ELECTRICAL INSULATING QUALITY SUPPER SPARES FOR UPS 80KVA 1+1 SINGLE MODULE UPS 12 PULSE WITH EXTERNAL MAINTENANCE BY-PASS CABINET MODEL NO: 5410332 S MAKE: LIEBERT TAG: EE82A, EE82B M/S EMBA CORPORATION PVT LTD KARACHI Qty = 20 Yards | G77: ENGRO FERTILIZERS Muhammad Imran Iqbal 7th Floor, The Harbor Front Building, HC # 3,Marine Drive, Block # 4, Clifton, Karachi, Cell: 0302-8226341 Tel: 021-35297534 miiqbal@engro.com | I77: 43600 | J77: =IF(X77="","LINKS REQUIRED",IF(X77="Completed","LINKS HARVESTED","LINKS AVAILABLE")) -> LINKS REQUIRED | AA77: 6QAAIHQA9M8CY41 | AB77: =LEFT(AA77,6) -> 6QAAIH | AC77: =LEFT(AB77,3) -> 6QA | AD77: =RIGHT(AB77,3) -> AIH | AE77: =RIGHT(AA77,7) -> 9M8CY41 | AF77: =LEFT(AE77,4) -> 9M8C | AG77: =RIGHT(AE77,3) -> Y41 | AH77: =_xludf.CONCAT(AC77,_xludf.CONCAT("-",AD77)) -> #NAME? | AI77: =_xludf.CONCAT(AF77,_xludf.CONCAT("-",AG77)) -> #NAME?
A78: =_xludf.CONCAT(AH78,_xludf.CONCAT("-",AI78)) -> #NAME? | B78: Closed | D78: A. Anwar Khan | F78: 043-190-027 FAN:AXIAL,350 M3/HOUR CAPACITY,220V FAN: TYPE: AXIAL CAPACITY: 350 M3/HOUR ELECTRICAL RATING: 220V TEXT:SPARES FOR UPS 80KVA 1+1 SINGLE MODULE UPS 12 PULSE WITH EXTERNAL MAINTENANCE BY-PASS CABINET MODEL NO: 5410332 S MAKE: LIEBERT TAG: EE82A, EE82B M/S EMBA CORPORATION PVT LTD KARACHI SICE MFG LIEBERT:0700009L Qty = 1 | G78: ENGRO FERTILIZERS Muhammad Imran Iqbal 7th Floor, The Harbor Front Building, HC # 3,Marine Drive, Block # 4, Clifton, Karachi, Tel: 021-35297534 miiqbal@engro.com | I78: 43600 | J78: =IF(X78="","LINKS REQUIRED",IF(X78="Completed","LINKS HARVESTED","LINKS AVAILABLE")) -> LINKS REQUIRED | AA78: 6RMQEKL7PUDHZNL | AB78: =LEFT(AA78,6) -> 6RMQEK | AC78: =LEFT(AB78,3) -> 6RM | AD78: =RIGHT(AB78,3) -> QEK | AE78: =RIGHT(AA78,7) -> PUDHZNL | AF78: =LEFT(AE78,4) -> PUDH | AG78: =RIGHT(AE78,3) -> ZNL | AH78: =_xludf.CONCAT(AC78,_xludf.CONCAT("-",AD78)) -> #NAME? | AI78: =_xludf.CONCAT(AF78,_xludf.CONCAT("-",AG78)) -> #NAME?
A79: =_xludf.CONCAT(AH79,_xludf.CONCAT("-",AI79)) -> #NAME? | B79: Inquiry received by e-mail | D79: A. Anwar Khan | F79: 041-402-080 BATTRY,DRY CELL:ALKALINE,9VDC BATTERY,DRY CELL: TYPE: ALKALINE VOLTAGE: 9 TEXT:GALLON, HYPER LONG LIFE MISCELLANEUS BATTERIES MFG UNIROSS FRANCE:* SONY-EVER-READY:* DURACELL:* NATIONAL:006P - UE 6F22 Qty = 250 | G79: ENGRO FERTILIZERS Muhammad Imran Iqbal 7th Floor, The Harbor Front Building, HC # 3,Marine Drive, Block # 4, Clifton, Karachi, Cell: 0302-8226341 Tel: 021-35297534 miiqbal@engro.com | I79: 43600 | J79: =IF(X79="","LINKS REQUIRED",IF(X79="Completed","LINKS HARVESTED","LINKS AVAILABLE")) -> LINKS REQUIRED | AA79: 6SF2I6C64FGVAO2 | AB79: =LEFT(AA79,6) -> 6SF2I6 | AC79: =LEFT(AB79,3) -> 6SF | AD79: =RIGHT(AB79,3) -> 2I6 | AE79: =RIGHT(AA79,7) -> 4FGVAO2 | AF79: =LEFT(AE79,4) -> 4FGV | AG79: =RIGHT(AE79,3) -> AO2 | AH79: =_xludf.CONCAT(AC79,_xludf.CONCAT("-",AD79)) -> #NAME? | AI79: =_xludf.CONCAT(AF79,_xludf.CONCAT("-",AG79)) -> #NAME?
A80: =_xludf.CONCAT(AH80,_xludf.CONCAT("-",AI80)) -> #NAME? | B80: Quotation Validity Reminder Sent | D80: A. Anwar Khan | F80: 1) GEAR UNIT Qty;_ 01 NOS TYPE : B3DH10 B RATIO : 50 RPM : 1489 P : 135 KW Required for Silo Feeding Bucket Elevator. Make FLENDER | G80: "ARIF MEMON MANAGER PURCHASE POWER CEMENT LIMITED formerly Al-Abbas Cement Industries Limited A Subsidiary of Arif Habib Group Head Office: Arif Habib Center 23, M.T .Khan Road, Karachi - 74000, Pakistan Phone: +92 21 32468231-2, 32468350-1, Fax No. : +92 21 32463209 Email: arif.memon@powercement.pk Website: www.powercement.com.pk SPR # SPR # 206-1821 | H80: Arsalan: info@pts-fzc.com Flender solution partner | I80: 43602 | J80: =IF(X80="","LINKS REQUIRED",IF(X80="Completed","LINKS HARVESTED","LINKS AVAILABLE")) -> LINKS REQUIRED | AA80: 6UAX3DXFL1CWUA6 | AB80: =LEFT(AA80,6) -> 6UAX3D | AC80: =LEFT(AB80,3) -> 6UA | AD80: =RIGHT(AB80,3) -> X3D | AE80: =RIGHT(AA80,7) -> L1CWUA6 | AF80: =LEFT(AE80,4) -> L1CW | AG80: =RIGHT(AE80,3) -> UA6 | AH80: =_xludf.CONCAT(AC80,_xludf.CONCAT("-",AD80)) -> #NAME? | AI80: =_xludf.CONCAT(AF80,_xludf.CONCAT("-",AG80)) -> #NAME?
A81: =_xludf.CONCAT(AH81,_xludf.CONCAT("-",AI81)) -> #NAME? | B81: Quotation Validity Reminder Sent | D81: A. Anwar Khan | F81: GAUGE,PRES:0-4 KG/CM2,63MM DIAL,1/4"MNPT GAUGE,PRESSURE: RANGE: 0-4 KG/CM2 DIAL SIZE: 63MM SIZE/CONNECTION: 1/4" MNPT CONNECTION MATERIAL: 1.4404 316L SS CASE MATERIAL: 1.4301 304 SS TUBE MATERIAL: 1.4404 316L SS BOURDON CONNECTION LOCATION: BACK MOUNT: THREADED FILLED: NON MFG BAUMER:MEX3F50F19 BOURDEN:* | G81: ENGRO FERTILIZERS Muhammad Imran Iqbal 7th Floor, The Harbor Front Building, HC # 3,Marine Drive, Block # 4, Clifton, Karachi, Tel: 021-35297534 miiqbal@engro.com RFQ Number 3700020896 | H81: get all emails from links all near distributor from germany Hasan: Quotation sent on 21-05-19 | I81: 43602 | J81: =IF(X81="","LINKS REQUIRED",IF(X81="Completed","LINKS HARVESTED","LINKS AVAILABLE")) -> LINKS HARVESTED | M81: Maaz | O81: Saad | W81: GAUGE PRES0-4 KG (BOURDEN) | X81: Completed | Y81: http://us.bourdon.baumer.com/en/contact/distributors/ http://us.bourdon.baumer.com/en/contact/distributors/# | AA81: 6WIQHKBDRM9P7G2 | AB81: =LEFT(AA81,6) -> 6WIQHK | AC81: =LEFT(AB81,3) -> 6WI | AD81: =RIGHT(AB81,3) -> QHK | AE81: =RIGHT(AA81,7) -> RM9P7G2 | AF81: =LEFT(AE81,4) -> RM9P | AG81: =RIGHT(AE81,3) -> 7G2 | AH81: =_xludf.CONCAT(AC81,_xludf.CONCAT("-",AD81)) -> #NAME? | AI81: =_xludf.CONCAT(AF81,_xludf.CONCAT("-",AG81)) -> #NAME?
A82: =_xludf.CONCAT(AH82,_xludf.CONCAT("-",AI82)) -> #NAME? | B82: Quotation Validity Reminder Sent | D82: A. Anwar Khan | F82: GERB SPRING UNIT with DAMPING PAD Spring unit type S2 TYPE : S2-44 LOAD CAPACITY : 1.92 KN Qty: 30 NOS Make: Gerb Required for COOLER FAN FOR FOUNDATION VIB. ISOLTION | G82: """ARIF MEMON MANAGER PURCHASE POWER CEMENT LIMITED formerly Al-Abbas Cement Industries Limited A Subsidiary of Arif Habib Group Head Office: Arif Habib Center 23, M.T .Khan Road, Karachi - 74000, Pakistan Phone: +92 21 32468231-2, 32468350-1, Fax No. : +92 21 32463209 Email: arif.memon@powercement.pk Website: www.powercement.com.pk SPR # 206-1822 | H82: Maaz: found only 19 emails Hasan: Quotation sent on 27-05-19 | I82: 43602 | J82: =IF(X82="","LINKS REQUIRED",IF(X82="Completed","LINKS HARVESTED","LINKS AVAILABLE")) -> LINKS HARVESTED | M82: Maaz | O82: Saad | W82: GERB SPRING UNIT with DAMPING PAD | X82: Completed | Y82: https://www.google.com/search?newwindow=1&ei=K2DeXJa-LImjwAKbp4TAAQ&q=GERB+SPRING+UNIT+S2-44&oq=GERB+SPRING+UNIT+S2-44&gs_l=psy-ab.3...287019.287858..288170...0.0..0.191.910.0j5......0....1..gws-wiz.......0i71j35i304i39.au-1JPtklrc | AA82: 6X6RZY6STQGC8EV | AB82: =LEFT(AA82,6) -> 6X6RZY | AC82: =LEFT(AB82,3) -> 6X6 | AD82: =RIGHT(AB82,3) -> RZY | AE82: =RIGHT(AA82,7) -> TQGC8EV | AF82: =LEFT(AE82,4) -> TQGC | AG82: =RIGHT(AE82,3) -> 8EV | AH82: =_xludf.CONCAT(AC82,_xludf.CONCAT("-",AD82)) -> #NAME? | AI82: =_xludf.CONCAT(AF82,_xludf.CONCAT("-",AG82)) -> #NAME?
A83: =_xludf.CONCAT(AH83,_xludf.CONCAT("-",AI83)) -> #NAME? | B83: Quotation Validity Reminder Sent | D83: Qamar uddin | F83: Hersteller-Art.Nr. 77950108 Mahle - Filtration Group: Dust filter element 852 623 TI 15-0.4 21/08 Filter media polyester fleece diameter 115/120 mm Length (mm) 300 Mounting Raw gas side, RD 60x4 shape cylindrical filter area 0.4 m² Max. flow 41 m³ / h Max. operating temperatur 100 ° C Manufacturer: Filtration Group (formerly MAHLE) qty: 12 pictures attached | G83: Ashraf Butt Procurement Officer GlaxoSmithKline Consumer Healthcare Pakistan Ltd. 35 - Dockyard Road, west wharf , Karachi Tel: 35274744 (Ext: 4744) ashraf.x.butt@gsk.com Contact Person: Mr. Zakir Raza - 03112317017 - 0222109534 | H83: industrialfiltration@mahle.com info@filcom-technik.de Hasan: Quotation sent on 22-05-19 | I83: 43602 | J83: =IF(X83="","LINKS REQUIRED",IF(X83="Completed","LINKS HARVESTED","LINKS AVAILABLE")) -> LINKS HARVESTED | M83: Maaz | O83: Saad | W83: Dust filter element (Filtration Group) MAHLE | X83: Completed | Y83: https://www.google.com/search?q=Mahle+852+623+TI+15-0.4&oq=Mahle+852+623+TI+15-0.4&aqs=chrome..69i57j69i60.6231j0j7&sourceid=chrome&ie=UTF-8 https://www.google.com/search?newwindow=1&ei=3H3fXL3eOMqWsAfrpp2QAg&q=MAHLE+77950108&oq=MAHLE+77950108&gs_l=psy-ab.3...142166.143310..143485...0.0..0.186.898.0j5......0....1..gws-wiz.UF4vMnjvOFg https://filtration.group/mahle-industrial-filtration/ | AA83: 6Y45N4P9J70Q2HX | AB83: =LEFT(AA83,6) -> 6Y45N4 | AC83: =LEFT(AB83,3) -> 6Y4 | AD83: =RIGHT(AB83,3) -> 5N4 | AE83: =RIGHT(AA83,7) -> J70Q2HX | AF83: =LEFT(AE83,4) -> J70Q | AG83: =RIGHT(AE83,3) -> 2HX | AH83: =_xludf.CONCAT(AC83,_xludf.CONCAT("-",AD83)) -> #NAME? | AI83: =_xludf.CONCAT(AF83,_xludf.CONCAT("-",AG83)) -> #NAME?
A84: =_xludf.CONCAT(AH84,_xludf.CONCAT("-",AI84)) -> #NAME? | B84: Quotation Validity Reminder Sent | D84: Qamar uddin | F84: Edwards Active pirani gauge APG-MP-NW16 S/S Part no# D02185000 | G84: HIGH-Q B-64, Main Karsaz Road, KDA Scheme 1, Karach, Pakistan. | H84: info@activair.cz info@5pascal.it ITvendite@edwardsvacuum.com admin@acclon.com beneluxsales@edwardsvacuum.com Hasan: Quotation sent on 22-05-19 | I84: 43602 | J84: =IF(X86="","LINKS REQUIRED",IF(X86="Completed","LINKS HARVESTED","LINKS AVAILABLE")) -> LINKS HARVESTED | M84: Maaz | O84: Saad | W84: Edwards Active pirani gauge | Y84: https://www.google.com/search?newwindow=1&biw=1745&bih=852&ei=X37fXOS9CYuWsAfvgquoCQ&q=D02185000&oq=D02185000&gs_l=psy-ab.3...1943.13911..14206...0.0..0.260.1764.0j6j3....2..0....1..gws-wiz.......0i131j0j0i30j0i333.v2_oK9L9pXw https://www.google.com/search?q=Apg-mp-nw16+St-st&oq=Apg-mp-nw16+St-st&aqs=chrome..69i57j69i60&sourceid=chrome&ie=UTF-8 https://www.edwardsvacuum.com/en/talk-to-us | AA84: 6ZJN2A5T756X4Z5 | AB84: =LEFT(AA84,6) -> 6ZJN2A | AC84: =LEFT(AB84,3) -> 6ZJ | AD84: =RIGHT(AB84,3) -> N2A | AE84: =RIGHT(AA84,7) -> 756X4Z5 | AF84: =LEFT(AE84,4) -> 756X | AG84: =RIGHT(AE84,3) -> 4Z5 | AH84: =_xludf.CONCAT(AC84,_xludf.CONCAT("-",AD84)) -> #NAME? | AI84: =_xludf.CONCAT(AF84,_xludf.CONCAT("-",AG84)) -> #NAME?
A85: =_xludf.CONCAT(AH85,_xludf.CONCAT("-",AI85)) -> #NAME? | B85: Quotation Validity Reminder Sent | D85: A. Anwar Khan | F85: Oil press machines to extrect apricot kernel oil with a minimum capacity of 20 to 50 Kgs of RM / hour. | G85: zulfiqarghazi@hotmail.com Zulfiqar Ali Ghazi Farmers Consultant 05811. 441048 03005472979 | H85: Hasan: Quotation sent on 23-05-19 | I85: 43605 | J85: LINKS HARVESTED | M85: Maaz | O85: Saad | W85: Oil press machines | X85: Completed | Y85: https://www.google.com/search?newwindow=1&biw=1745&bih=881&ei=WSHiXIrfLMffwQK12ICYDg&q=European+Oil+press+machines+-%22china%22+-%22alibaba%22&oq=European+Oil+press+machines+-%22china%22+-%22alibaba%22&gs_l=psy-ab.3...3774.7133..7349...0.0..0.274.2392.2-9......0....1..gws-wiz.......0i71.D2I7BFdfowE https://www.google.com/search?newwindow=1&biw=1745&bih=881&ei=mCHiXPHFDIXQwQLkoZyYDg&q=Oil+press+machine+Italy+-%22china%22+-%22alibaba%22&oq=Oil+press+machine+Italy+-%22china%22+-%22alibaba%22&gs_l=psy-ab.3...98784.103647..103752...0.0..0.286.1625.2-6......0....1..gws-wiz.g8nNJS_gBVw https://www.google.com/search?newwindow=1&biw=1745&bih=881&ei=ACLiXOy2NoTdwAKMmZf4DA&q=Oil+press+machine+GErmany+-%22china%22+-%22alibaba%22&oq=Oil+press+machine+GErmany+-%22china%22+-%22alibaba%22&gs_l=psy-ab.3...216736.217631..217784...0.0..0.181.1059.0j6......0....1..gws-wiz.......0i71.dLWikMCxAwk https://www.google.com/search?newwindow=1&biw=1745&bih=881&ei=9CLiXJyEMa7ksAf16YnwBA&q=industrial+Oil+press+machine+Europe+-%22china%22+-%22alibaba%22&oq=industrial+Oil+press+machine+Europe+-%22china%22+-%22alibaba%22&gs_l=psy-ab.3..0i71l8.316603.318026..318179...0.0..0.563.3130.2-8j1j0j1......0....1..gws-wiz.Wr-DE3tCd-w https://www.google.com/search?newwindow=1&biw=1745&bih=852&ei=3iviXKWWK4KZsAfLsp2QCg&q=industrial+oil+press+machine+EU+-%22alibaba%22+-%22china%22&oq=industrial+oil+press+machine+EU+-%22alibaba%22+-%22china%22&gs_l=psy-ab.3...11537.18329..18440...0.0..0.252.3387.0j17j2......0....1..gws-wiz.......0i71j33i22i29i30.CyknPIGtR8c | AA85: 6ZLFXT2U5TS9XX2 | AB85: =LEFT(AA85,6) -> 6ZLFXT | AC85: =LEFT(AB85,3) -> 6ZL | AD85: =RIGHT(AB85,3) -> FXT | AE85: =RIGHT(AA85,7) -> 5TS9XX2 | AF85: =LEFT(AE85,4) -> 5TS9 | AG85: =RIGHT(AE85,3) -> XX2 | AH85: =_xludf.CONCAT(AC85,_xludf.CONCAT("-",AD85)) -> #NAME? | AI85: =_xludf.CONCAT(AF85,_xludf.CONCAT("-",AG85)) -> #NAME?
A86: =_xludf.CONCAT(AH86,_xludf.CONCAT("-",AI86)) -> #NAME? | B86: Inquiry letter sent | D86: Qamar uddin | F86: Quotation required for Flow Meter. Over flow supply nipple 1. Material ss316L size 4"inch 10, 1.2 mtr long 2. level senser+spare+outlet nipple material ss316L size 3" inch 10, 0.4m long | G86: Adnan ams power lahore 03219440109 Adnan | I86: 43605 | J86: =IF(X88="","LINKS REQUIRED",IF(X88="Completed","LINKS HARVESTED","LINKS AVAILABLE")) -> LINKS HARVESTED | M86: Maaz | O86: Saad | W86: Flow Meter & Flow Meter Merged(fly) | X86: Completed | Y86: https://www.google.com/search?q=chemical+flow+meter&oq=chemical+flow+meter&aqs=chrome.0.0l6.4976j0j9&sourceid=chrome&ie=UTF-8 https://www.google.com/search?newwindow=1&ei=nTniXIuCJ9LZwAKYy4rIDQ&q=chemical+flow+meter+china+-%22alibaba%22&oq=chemical+flow+meter+china+-%22alibaba%22&gs_l=psy-ab.3...5674.10681..10818...2.0..0.342.3354.2-10j2......0....1..gws-wiz.......33i22i29i30.fy6SxBRlVrU | AA86: 7X7A1C2RKZ8EN4I | AB86: =LEFT(AA86,6) -> 7X7A1C | AC86: =LEFT(AB86,3) -> 7X7 | AD86: =RIGHT(AB86,3) -> A1C | AE86: =RIGHT(AA86,7) -> KZ8EN4I | AF86: =LEFT(AE86,4) -> KZ8E | AG86: =RIGHT(AE86,3) -> N4I | AH86: =_xludf.CONCAT(AC86,_xludf.CONCAT("-",AD86)) -> #NAME? | AI86: =_xludf.CONCAT(AF86,_xludf.CONCAT("-",AG86)) -> #NAME?
